Workbook

Sheet Dashboard
A1: DASHBOARD
A3: Total catalog items | C3: =COUNTA('Item Catalog'!$A$3:$A$1000) -> 51
A4: Items — In Stock | C4: =COUNTIF('Item Catalog'!$O$3:$O$1000,"In Stock") -> 46
A5: Items — Low | C5: =COUNTIF('Item Catalog'!$O$3:$O$1000,"Low") -> 0
A6: Items — Out | C6: =COUNTIF('Item Catalog'!$O$3:$O$1000,"Out") -> 5
A8: Total Qty Ordered (all-time) | C8: =SUM('Item Catalog'!$L$3:$L$1000) -> 6771
A9: Total Qty Stock Out (all-time) | C9: =SUM('Item Catalog'!$M$3:$M$1000) -> 2606
A10: Total Qty Balance (current stock, all items) | C10: =SUM('Item Catalog'!$N$3:$N$1000) -> 4165
A12: Total spent on restocking to date | C12: ='Restock Orders'!$F$13 -> 522564
A14: Sales this period (Source = Sales Entry only) | C14: =SUMPRODUCT(('Stock Movements'!$G$3:$G$1000="Sales Entry")*('Stock Movements'!$D$3:$D$1000="Out")*('Stock Movements'!$E$3:$E$1000)) -> 0
A16: Note: "Sales this period" only counts Stock Movements rows tagged Source = "Sales Entry" (i.e. real, dated retail sales logged going forward by the app). It reads 0 right now because the historical import rows are tagged "Historical Import", not "Sales Entry" — no per-transaction sales history survives from the original file (see spec, item 11.2). Yearly Sales totals for past years should be computed by the app directly from its own Sales Report data, not from this workbook.

Sheet Item Catalog
A1: ITEM CATALOG (single shared master list)
A2: Item ID | B2: Item Label | C2: Item Name | D2: Code | E2: Category | F2: Packing | G2: Batch Note | H2: Batch Date | I2: Dealer Price | J2: SRP | K2: Low Stock Threshold | L2: Qty Ordered | M2: Qty Stock Out | N2: Qty Balance | O2: Status | P2: Profit / Unit
A3: ITM-001 | B3: =A3&" · "&C3 -> ITM-001 · 5 GAL SLIM CONTAINER W/ CAP BLUE | C3: 5 GAL SLIM CONTAINER W/ CAP BLUE | D3: 10-150-105 | E3: CONTAINERS | F3: 1 PC | G3: SOLD | I3: 105 | J3: 135 | L3: =SUMIFS('Stock Movements'!$E:$E,'Stock Movements'!$C:$C,$B3,'Stock Movements'!$D:$D,"In") -> 526 | M3: =SUMIFS('Stock Movements'!$E:$E,'Stock Movements'!$C:$C,$B3,'Stock Movements'!$D:$D,"Out") -> 526 | N3: =L3-M3 -> 0 | O3: =IF(N3<=0,"Out",IF(AND(K3<>"",N3<=K3),"Low","In Stock")) -> Out | P3: =J3-I3 -> 30
A4: ITM-002 | B4: =A4&" · "&C4 -> ITM-002 · 5 GAL SLIM CONTAINER W/ CAP BLUE-WOW | C4: 5 GAL SLIM CONTAINER W/ CAP BLUE-WOW | D4: 10-150-105 | E4: CONTAINERS | F4: 1 PC | G4: NEW BATCH | H4: 5/15/26 | I4: 110 | J4: 145 | L4: =SUMIFS('Stock Movements'!$E:$E,'Stock Movements'!$C:$C,$B4,'Stock Movements'!$D:$D,"In") -> 200 | M4: =SUMIFS('Stock Movements'!$E:$E,'Stock Movements'!$C:$C,$B4,'Stock Movements'!$D:$D,"Out") -> 53 | N4: =L4-M4 -> 147 | O4: =IF(N4<=0,"Out",IF(AND(K4<>"",N4<=K4),"Low","In Stock")) -> In Stock | P4: =J4-I4 -> 35
A5: ITM-003 | B5: =A5&" · "&C5 -> ITM-003 · 5 GAL SLIM CONTAINER W/ CAP GREEN | C5: 5 GAL SLIM CONTAINER W/ CAP GREEN | D5: 10-150-105 | E5: CONTAINERS | F5: 1 PC | I5: 105 | J5: 140 | L5: =SUMIFS('Stock Movements'!$E:$E,'Stock Movements'!$C:$C,$B5,'Stock Movements'!$D:$D,"In") -> 350 | M5: =SUMIFS('Stock Movements'!$E:$E,'Stock Movements'!$C:$C,$B5,'Stock Movements'!$D:$D,"Out") -> 220 | N5: =L5-M5 -> 130 | O5: =IF(N5<=0,"Out",IF(AND(K5<>"",N5<=K5),"Low","In Stock")) -> In Stock | P5: =J5-I5 -> 35
A6: ITM-004 | B6: =A6&" · "&C6 -> ITM-004 · 5 GAL SLIM CONTAINER W/ CAP YELLOW | C6: 5 GAL SLIM CONTAINER W/ CAP YELLOW | D6: 10-150-105 | E6: CONTAINERS | F6: 1 PC | I6: 105 | J6: 140 | L6: =SUMIFS('Stock Movements'!$E:$E,'Stock Movements'!$C:$C,$B6,'Stock Movements'!$D:$D,"In") -> 350 | M6: =SUMIFS('Stock Movements'!$E:$E,'Stock Movements'!$C:$C,$B6,'Stock Movements'!$D:$D,"Out") -> 58 | N6: =L6-M6 -> 292 | O6: =IF(N6<=0,"Out",IF(AND(K6<>"",N6<=K6),"Low","In Stock")) -> In Stock | P6: =J6-I6 -> 35
A7: ITM-005 | B7: =A7&" · "&C7 -> ITM-005 · 5 GAL (PET) ROUND CONTAINER BLUE W/ CAP (CLASS A) | C7: 5 GAL (PET) ROUND CONTAINER BLUE W/ CAP (CLASS A) | D7: 10-110-103 | E7: CONTAINERS | F7: 1 PC | G7: SOLD | I7: 112 | J7: 130 | L7: =SUMIFS('Stock Movements'!$E:$E,'Stock Movements'!$C:$C,$B7,'Stock Movements'!$D:$D,"In") -> 200 | M7: =SUMIFS('Stock Movements'!$E:$E,'Stock Movements'!$C:$C,$B7,'Stock Movements'!$D:$D,"Out") -> 199 | N7: =L7-M7 -> 1 | O7: =IF(N7<=0,"Out",IF(AND(K7<>"",N7<=K7),"Low","In Stock")) -> In Stock | P7: =J7-I7 -> 18
A8: ITM-006 | B8: =A8&" · "&C8 -> ITM-006 · 5 GAL (PET) ROUND CONTAINER BLUE W/ CAP (CLASS A) | C8: 5 GAL (PET) ROUND CONTAINER BLUE W/ CAP (CLASS A) | D8: 10-110-103/10-120-103 | E8: CONTAINERS | G8: NEW BATCH | H8: 5/15/26 | I8: 116.7 | J8: 150 | L8: =SUMIFS('Stock Movements'!$E:$E,'Stock Movements'!$C:$C,$B8,'Stock Movements'!$D:$D,"In") -> 100 | M8: =SUMIFS('Stock Movements'!$E:$E,'Stock Movements'!$C:$C,$B8,'Stock Movements'!$D:$D,"Out") -> 11 | N8: =L8-M8 -> 89 | O8: =IF(N8<=0,"Out",IF(AND(K8<>"",N8<=K8),"Low","In Stock")) -> In Stock | P8: =J8-I8 -> 33.3
A9: ITM-007 | B9: =A9&" · "&C9 -> ITM-007 · BIG CAP SEAL FOR SLIM LW | C9: BIG CAP SEAL FOR SLIM LW | D9: 10-100-102 | E9: CAPSEALS | F9: 500 PC | I9: 100 | J9: 130 | L9: =SUMIFS('Stock Movements'!$E:$E,'Stock Movements'!$C:$C,$B9,'Stock Movements'!$D:$D,"In") -> 100 | M9: =SUMIFS('Stock Movements'!$E:$E,'Stock Movements'!$C:$C,$B9,'Stock Movements'!$D:$D,"Out") -> 55 | N9: =L9-M9 -> 45 | O9: =IF(N9<=0,"Out",IF(AND(K9<>"",N9<=K9),"Low","In Stock")) -> In Stock | P9: =J9-I9 -> 30
A10: ITM-008 | B10: =A10&" · "&C10 -> ITM-008 · SMALL CAP SEAL FOR SLIM LW | C10: SMALL CAP SEAL FOR SLIM LW | D10: 10-190-101 | E10: CAPSEALS | F10: 1000 PC | I10: 70 | J10: 115 | L10: =SUMIFS('Stock Movements'!$E:$E,'Stock Movements'!$C:$C,$B10,'Stock Movements'!$D:$D,"In") -> 100 | M10: =SUMIFS('Stock Movements'!$E:$E,'Stock Movements'!$C:$C,$B10,'Stock Movements'!$D:$D,"Out") -> 24 | N10: =L10-M10 -> 76 | O10: =IF(N10<=0,"Out",IF(AND(K10<>"",N10<=K10),"Low","In Stock")) -> In Stock | P10: =J10-I10 -> 45
A11: ITM-009 | B11: =A11&" · "&C11 -> ITM-009 · FAUCET SEAL FOR SLIM LW | C11: FAUCET SEAL FOR SLIM LW | E11: CAPSEALS | F11: 1000 PC | I11: 100 | J11: 170 | L11: =SUMIFS('Stock Movements'!$E:$E,'Stock Movements'!$C:$C,$B11,'Stock Movements'!$D:$D,"In") -> 100 | M11: =SUMIFS('Stock Movements'!$E:$E,'Stock Movements'!$C:$C,$B11,'Stock Movements'!$D:$D,"Out") -> 62 | N11: =L11-M11 -> 38 | O11: =IF(N11<=0,"Out",IF(AND(K11<>"",N11<=K11),"Low","In Stock")) -> In Stock | P11: =J11-I11 -> 70
A12: ITM-010 | B12: =A12&" · "&C12 -> ITM-010 · FAUCET SEAL FOR SLIM LW (CLASS B) | C12: FAUCET SEAL FOR SLIM LW (CLASS B) | E12: CAPSEALS | F12: 1000 PC | I12: 95 | J12: 170 | L12: =SUMIFS('Stock Movements'!$E:$E,'Stock Movements'!$C:$C,$B12,'Stock Movements'!$D:$D,"In") -> 25 | M12: =SUMIFS('Stock Movements'!$E:$E,'Stock Movements'!$C:$C,$B12,'Stock Movements'!$D:$D,"Out") -> 0 | N12: =L12-M12 -> 25 | O12: =IF(N12<=0,"Out",IF(AND(K12<>"",N12<=K12),"Low","In Stock")) -> In Stock | P12: =J12-I12 -> 75
A13: ITM-011 | B13: =A13&" · "&C13 -> ITM-011 · UMBRELLA SEAL FOR ROUND LW | C13: UMBRELLA SEAL FOR ROUND LW | D13: 10-220-101 | E13: CAPSEALS | F13: 500 PC | I13: 100 | J13: 130 | L13: =SUMIFS('Stock Movements'!$E:$E,'Stock Movements'!$C:$C,$B13,'Stock Movements'!$D:$D,"In") -> 100 | M13: =SUMIFS('Stock Movements'!$E:$E,'Stock Movements'!$C:$C,$B13,'Stock Movements'!$D:$D,"Out") -> 33 | N13: =L13-M13 -> 67 | O13: =IF(N13<=0,"Out",IF(AND(K13<>"",N13<=K13),"Low","In Stock")) -> In Stock | P13: =J13-I13 -> 30
A14: ITM-012 | B14: =A14&" · "&C14 -> ITM-012 · UMBRELLA SEAL FOR ROUND LW (CLASS B) | C14: UMBRELLA SEAL FOR ROUND LW (CLASS B) | E14: CAPSEALS | F14: 500 PC | I14: 95 | J14: 130 | L14: =SUMIFS('Stock Movements'!$E:$E,'Stock Movements'!$C:$C,$B14,'Stock Movements'!$D:$D,"In") -> 50 | M14: =SUMIFS('Stock Movements'!$E:$E,'Stock Movements'!$C:$C,$B14,'Stock Movements'!$D:$D,"Out") -> 0 | N14: =L14-M14 -> 50 | O14: =IF(N14<=0,"Out",IF(AND(K14<>"",N14<=K14),"Low","In Stock")) -> In Stock | P14: =J14-I14 -> 35
A15: ITM-013 | B15: =A15&" · "&C15 -> ITM-013 · BIG CAP SEAL FOR SLIM GENERIC | C15: BIG CAP SEAL FOR SLIM GENERIC | D15: 10-100-107 | E15: CAPSEALS | F15: 500 PC | G15: SOLD | I15: 100 | J15: 120 | L15: =SUMIFS('Stock Movements'!$E:$E,'Stock Movements'!$C:$C,$B15,'Stock Movements'!$D:$D,"In") -> 100 | M15: =SUMIFS('Stock Movements'!$E:$E,'Stock Movements'!$C:$C,$B15,'Stock Movements'!$D:$D,"Out") -> 100 | N15: =L15-M15 -> 0 | O15: =IF(N15<=0,"Out",IF(AND(K15<>"",N15<=K15),"Low","In Stock")) -> Out | P15: =J15-I15 -> 20
A16: ITM-014 | B16: =A16&" · "&C16 -> ITM-014 · SMALL CAP SEAL FOR SLIM GENERIC | C16: SMALL CAP SEAL FOR SLIM GENERIC | D16: 10-190-107 | E16: CAPSEALS | F16: 1000 PC | I16: 70 | J16: 110 | L16: =SUMIFS('Stock Movements'!$E:$E,'Stock Movements'!$C:$C,$B16,'Stock Movements'!$D:$D,"In") -> 100 | M16: =SUMIFS('Stock Movements'!$E:$E,'Stock Movements'!$C:$C,$B16,'Stock Movements'!$D:$D,"Out") -> 36 | N16: =L16-M16 -> 64 | O16: =IF(N16<=0,"Out",IF(AND(K16<>"",N16<=K16),"Low","In Stock")) -> In Stock | P16: =J16-I16 -> 40
A17: ITM-015 | B17: =A17&" · "&C17 -> ITM-015 · FAUCET SEAL FOR SLIM GENERIC | C17: FAUCET SEAL FOR SLIM GENERIC | D17: 10-140-107 | E17: CAPSEALS | F17: 1000 PC | G17: SOLD | I17: 100 | J17: 170 | L17: =SUMIFS('Stock Movements'!$E:$E,'Stock Movements'!$C:$C,$B17,'Stock Movements'!$D:$D,"In") -> 100 | M17: =SUMIFS('Stock Movements'!$E:$E,'Stock Movements'!$C:$C,$B17,'Stock Movements'!$D:$D,"Out") -> 100 | N17: =L17-M17 -> 0 | O17: =IF(N17<=0,"Out",IF(AND(K17<>"",N17<=K17),"Low","In Stock")) -> Out | P17: =J17-I17 -> 70
A18: ITM-016 | B18: =A18&" · "&C18 -> ITM-016 · FAUCET SEAL FOR SLIM GENERIC | C18: FAUCET SEAL FOR SLIM GENERIC | D18: 10-140-107 | E18: CAPSEALS | F18: 1000 PC | G18: NEW BATCH | H18: 5/15/26 | I18: 115 | J18: 180 | L18: =SUMIFS('Stock Movements'!$E:$E,'Stock Movements'!$C:$C,$B18,'Stock Movements'!$D:$D,"In") -> 100 | M18: =SUMIFS('Stock Movements'!$E:$E,'Stock Movements'!$C:$C,$B18,'Stock Movements'!$D:$D,"Out") -> 11 | N18: =L18-M18 -> 89 | O18: =IF(N18<=0,"Out",IF(AND(K18<>"",N18<=K18),"Low","In Stock")) -> In Stock | P18: =J18-I18 -> 65
A19: ITM-017 | B19: =A19&" · "&C19 -> ITM-017 · UMBRELLA SEAL FOR ROUND GENERIC | C19: UMBRELLA SEAL FOR ROUND GENERIC | D19: 10-220-107 | E19: CAPSEALS | F19: 500 PC | I19: 100 | J19: 125 | L19: =SUMIFS('Stock Movements'!$E:$E,'Stock Movements'!$C:$C,$B19,'Stock Movements'!$D:$D,"In") -> 100 | M19: =SUMIFS('Stock Movements'!$E:$E,'Stock Movements'!$C:$C,$B19,'Stock Movements'!$D:$D,"Out") -> 75 | N19: =L19-M19 -> 25 | O19: =IF(N19<=0,"Out",IF(AND(K19<>"",N19<=K19),"Low","In Stock")) -> In Stock | P19: =J19-I19 -> 25
A20: ITM-018 | B20: =A20&" · "&C20 -> ITM-018 · 1 L SOAP SANITIZER | C20: 1 L SOAP SANITIZER | D20: 25-120-101 | E20: SOAP SANITIZER | F20: 1 PC | I20: 49 | J20: 65 | L20: =SUMIFS('Stock Movements'!$E:$E,'Stock Movements'!$C:$C,$B20,'Stock Movements'!$D:$D,"In") -> 80 | M20: =SUMIFS('Stock Movements'!$E:$E,'Stock Movements'!$C:$C,$B20,'Stock Movements'!$D:$D,"Out") -> 35 | N20: =L20-M20 -> 45 | O20: =IF(N20<=0,"Out",IF(AND(K20<>"",N20<=K20),"Low","In Stock")) -> In Stock | P20: =J20-I20 -> 16
A21: ITM-019 | B21: =A21&" · "&C21 -> ITM-019 · SOAP SANITIZER: SOAP WOW-1LITER | C21: SOAP SANITIZER: SOAP WOW-1LITER | D21: 25-420-101 | E21: SOAP SANITIZER | F21: 1 PC | G21: NEW BATCH | H21: 5/15/26 | I21: 63 | J21: 80 | L21: =SUMIFS('Stock Movements'!$E:$E,'Stock Movements'!$C:$C,$B21,'Stock Movements'!$D:$D,"In") -> 32 | M21: =SUMIFS('Stock Movements'!$E:$E,'Stock Movements'!$C:$C,$B21,'Stock Movements'!$D:$D,"Out") -> 0 | N21: =L21-M21 -> 32 | O21: =IF(N21<=0,"Out",IF(AND(K21<>"",N21<=K21),"Low","In Stock")) -> In Stock | P21: =J21-I21 -> 17
A22: ITM-020 | B22: =A22&" · "&C22 -> ITM-020 · AUSTRALIAN SALT | C22: AUSTRALIAN SALT | D22: 19-150-100 | E22: SALT 50KG | F22: 1 SACK | G22: SOLD | I22: 390 | J22: 520 | L22: =SUMIFS('Stock Movements'!$E:$E,'Stock Movements'!$C:$C,$B22,'Stock Movements'!$D:$D,"In") -> 15 | M22: =SUMIFS('Stock Movements'!$E:$E,'Stock Movements'!$C:$C,$B22,'Stock Movements'!$D:$D,"Out") -> 15 | N22: =L22-M22 -> 0 | O22: =IF(N22<=0,"Out",IF(AND(K22<>"",N22<=K22),"Low","In Stock")) -> Out | P22: =J22-I22 -> 130
A23: ITM-021 | B23: =A23&" · "&C23 -> ITM-021 · INDUSTRIAL SALT ART-COURSE | C23: INDUSTRIAL SALT ART-COURSE | E23: SALT 50KG | F23: 1 SACK | I23: 410 | J23: 520 | L23: =SUMIFS('Stock Movements'!$E:$E,'Stock Movements'!$C:$C,$B23,'Stock Movements'!$D:$D,"In") -> 70 | M23: =SUMIFS('Stock Movements'!$E:$E,'Stock Movements'!$C:$C,$B23,'Stock Movements'!$D:$D,"Out") -> 63 | N23: =L23-M23 -> 7 | O23: =IF(N23<=0,"Out",IF(AND(K23<>"",N23<=K23),"Low","In Stock")) -> In Stock | P23: =J23-I23 -> 110
A24: ITM-022 | B24: =A24&" · "&C24 -> ITM-022 · INDUSTRIAL SALT ART-COURSE | C24: INDUSTRIAL SALT ART-COURSE | E24: SALT 50KG | F24: 1 SACK | G24: NEW BATCH | H24: 5/15/26 | I24: 400 | J24: 520 | L24: =SUMIFS('Stock Movements'!$E:$E,'Stock Movements'!$C:$C,$B24,'Stock Movements'!$D:$D,"In") -> 20 | M24: =SUMIFS('Stock Movements'!$E:$E,'Stock Movements'!$C:$C,$B24,'Stock Movements'!$D:$D,"Out") -> 0 | N24: =L24-M24 -> 20 | O24: =IF(N24<=0,"Out",IF(AND(K24<>"",N24<=K24),"Low","In Stock")) -> In Stock | P24: =J24-I24 -> 120
A25: ITM-023 | B25: =A25&" · "&C25 -> ITM-023 · 5M SF 20SL LW ( MONTHLY (2PC) FOR PURIFIED/MINERAL ) | C25: 5M SF 20SL LW ( MONTHLY (2PC) FOR PURIFIED/MINERAL ) | D25: 14-230-116 | E25: FILTERS | F25: 1 PC | I25: 85 | J25: 110 | L25: =SUMIFS('Stock Movements'!$E:$E,'Stock Movements'!$C:$C,$B25,'Stock Movements'!$D:$D,"In") -> 25 | M25: =SUMIFS('Stock Movements'!$E:$E,'Stock Movements'!$C:$C,$B25,'Stock Movements'!$D:$D,"Out") -> 9 | N25: =L25-M25 -> 16 | O25: =IF(N25<=0,"Out",IF(AND(K25<>"",N25<=K25),"Low","In Stock")) -> In Stock | P25: =J25-I25 -> 25
A26: ITM-024 | B26: =A26&" · "&C26 -> ITM-024 · SEDIMENT: LWS 20" SLIM 5-MIC | C26: SEDIMENT: LWS 20" SLIM 5-MIC | D26: 14-230-116 | E26: FILTERS | F26: 1 PC | I26: 75 | J26: 110 | L26: =SUMIFS('Stock Movements'!$E:$E,'Stock Movements'!$C:$C,$B26,'Stock Movements'!$D:$D,"In") -> 10 | M26: =SUMIFS('Stock Movements'!$E:$E,'Stock Movements'!$C:$C,$B26,'Stock Movements'!$D:$D,"Out") -> 0 | N26: =L26-M26 -> 10 | O26: =IF(N26<=0,"Out",IF(AND(K26<>"",N26<=K26),"Low","In Stock")) -> In Stock | P26: =J26-I26 -> 35
A27: ITM-025 | B27: =A27&" · "&C27 -> ITM-025 · 1M SF 20S LW ( QUARTERLY (2PC) FOR PURIFIED/MINERAL ) | C27: 1M SF 20S LW ( QUARTERLY (2PC) FOR PURIFIED/MINERAL ) | D27: 14-230-115 | E27: FILTERS | F27: 1 PC | I27: 95 | J27: 110 | L27: =SUMIFS('Stock Movements'!$E:$E,'Stock Movements'!$C:$C,$B27,'Stock Movements'!$D:$D,"In") -> 25 | M27: =SUMIFS('Stock Movements'!$E:$E,'Stock Movements'!$C:$C,$B27,'Stock Movements'!$D:$D,"Out") -> 13 | N27: =L27-M27 -> 12 | O27: =IF(N27<=0,"Out",IF(AND(K27<>"",N27<=K27),"Low","In Stock")) -> In Stock | P27: =J27-I27 -> 15
A28: ITM-026 | B28: =A28&" · "&C28 -> ITM-026 · SEDIMENT: LWS 20" SLIM 1-MIC | C28: SEDIMENT: LWS 20" SLIM 1-MIC | D28: 14-230-115 | E28: FILTERS | F28: 1 PC | I28: 85 | J28: 110 | L28: =SUMIFS('Stock Movements'!$E:$E,'Stock Movements'!$C:$C,$B28,'Stock Movements'!$D:$D,"In") -> 5 | M28: =SUMIFS('Stock Movements'!$E:$E,'Stock Movements'!$C:$C,$B28,'Stock Movements'!$D:$D,"Out") -> 0 | N28: =L28-M28 -> 5 | O28: =IF(N28<=0,"Out",IF(AND(K28<>"",N28<=K28),"Low","In Stock")) -> In Stock | P28: =J28-I28 -> 25
A29: ITM-027 | B29: =A29&" · "&C29 -> ITM-027 · 1M SF 10SL LW ( QUARTERLY (1PC) FOR ALKALINE ) (SEDIMENT: LWS 10" SLIM 1-MIC) | C29: 1M SF 10SL LW ( QUARTERLY (1PC) FOR ALKALINE ) (SEDIMENT: LWS 10" SLIM 1-MIC) | D29: 14-230-114 | E29: FILTERS | F29: 1 PC | I29: 61 | J29: 90 | L29: =SUMIFS('Stock Movements'!$E:$E,'Stock Movements'!$C:$C,$B29,'Stock Movements'!$D:$D,"In") -> 15 | M29: =SUMIFS('Stock Movements'!$E:$E,'Stock Movements'!$C:$C,$B29,'Stock Movements'!$D:$D,"Out") -> 6 | N29: =L29-M29 -> 9 | O29: =IF(N29<=0,"Out",IF(AND(K29<>"",N29<=K29),"Low","In Stock")) -> In Stock | P29: =J29-I29 -> 29
A30: ITM-028 | B30: =A30&" · "&C30 -> ITM-028 · HYDROSEP CTO 20SL ( QUARTERLY (2PC) FOR PURIFIED/MINERAL ) | C30: HYDROSEP CTO 20SL ( QUARTERLY (2PC) FOR PURIFIED/MINERAL ) | D30: 14-130-103 | E30: FILTERS | F30: 1 PC | I30: 620 | J30: 750 | L30: =SUMIFS('Stock Movements'!$E:$E,'Stock Movements'!$C:$C,$B30,'Stock Movements'!$D:$D,"In") -> 25 | M30: =SUMIFS('Stock Movements'!$E:$E,'Stock Movements'!$C:$C,$B30,'Stock Movements'!$D:$D,"Out") -> 20 | N30: =L30-M30 -> 5 | O30: =IF(N30<=0,"Out",IF(AND(K30<>"",N30<=K30),"Low","In Stock")) -> In Stock | P30: =J30-I30 -> 130
A31: ITM-029 | B31: =A31&" · "&C31 -> ITM-029 · HYDROSEP CTO 10SL ( QUARTERLY (1PC) FOR ALKALINE ) | C31: HYDROSEP CTO 10SL ( QUARTERLY (1PC) FOR ALKALINE ) | D31: 14-130-101 | E31: FILTERS | F31: 1 PC | I31: 350 | J31: 400 | L31: =SUMIFS('Stock Movements'!$E:$E,'Stock Movements'!$C:$C,$B31,'Stock Movements'!$D:$D,"In") -> 10 | M31: =SUMIFS('Stock Movements'!$E:$E,'Stock Movements'!$C:$C,$B31,'Stock Movements'!$D:$D,"Out") -> 6 | N31: =L31-M31 -> 4 | O31: =IF(N31<=0,"Out",IF(AND(K31<>"",N31<=K31),"Low","In Stock")) -> In Stock | P31: =J31-I31 -> 50
A32: ITM-030 | B32: =A32&" · "&C32 -> ITM-030 · CERAMIC FILTER 10SL ( QUARTERLY (1PC) FOR ALKALINE ) | C32: CERAMIC FILTER 10SL ( QUARTERLY (1PC) FOR ALKALINE ) | D32: 14-150-100 | E32: FILTERS | F32: 1 PC | I32: 500 | J32: 770 | L32: =SUMIFS('Stock Movements'!$E:$E,'Stock Movements'!$C:$C,$B32,'Stock Movements'!$D:$D,"In") -> 10 | M32: =SUMIFS('Stock Movements'!$E:$E,'Stock Movements'!$C:$C,$B32,'Stock Movements'!$D:$D,"Out") -> 3 | N32: =L32-M32 -> 7 | O32: =IF(N32<=0,"Out",IF(AND(K32<>"",N32<=K32),"Low","In Stock")) -> In Stock | P32: =J32-I32 -> 270
A33: ITM-031 | B33: =A33&" · "&C33 -> ITM-031 · BIO FILTER 10SL ( QUARTERLY (1PC) FOR ALKALINE ) | C33: BIO FILTER 10SL ( QUARTERLY (1PC) FOR ALKALINE ) | D33: 14-110-100 | E33: FILTERS | F33: 1 PC | I33: 1018 | J33: 1550 | L33: =SUMIFS('Stock Movements'!$E:$E,'Stock Movements'!$C:$C,$B33,'Stock Movements'!$D:$D,"In") -> 10 | M33: =SUMIFS('Stock Movements'!$E:$E,'Stock Movements'!$C:$C,$B33,'Stock Movements'!$D:$D,"Out") -> 2 | N33: =L33-M33 -> 8 | O33: =IF(N33<=0,"Out",IF(AND(K33<>"",N33<=K33),"Low","In Stock")) -> In Stock | P33: =J33-I33 -> 532
A34: ITM-032 | B34: =A34&" · "&C34 -> ITM-032 · WOW 20" SLIM 5-MIC | C34: WOW 20" SLIM 5-MIC | E34: FILTERS | F34: 1 PC | I34: 70 | J34: 90 | L34: =SUMIFS('Stock Movements'!$E:$E,'Stock Movements'!$C:$C,$B34,'Stock Movements'!$D:$D,"In") -> 25 | M34: =SUMIFS('Stock Movements'!$E:$E,'Stock Movements'!$C:$C,$B34,'Stock Movements'!$D:$D,"Out") -> 10 | N34: =L34-M34 -> 15 | O34: =IF(N34<=0,"Out",IF(AND(K34<>"",N34<=K34),"Low","In Stock")) -> In Stock | P34: =J34-I34 -> 20
A35: ITM-033 | B35: =A35&" · "&C35 -> ITM-033 · WOW 20" SLIM 1-MIC | C35: WOW 20" SLIM 1-MIC | E35: FILTERS | F35: 1 PC | I35: 70 | J35: 90 | L35: =SUMIFS('Stock Movements'!$E:$E,'Stock Movements'!$C:$C,$B35,'Stock Movements'!$D:$D,"In") -> 25 | M35: =SUMIFS('Stock Movements'!$E:$E,'Stock Movements'!$C:$C,$B35,'Stock Movements'!$D:$D,"Out") -> 10 | N35: =L35-M35 -> 15 | O35: =IF(N35<=0,"Out",IF(AND(K35<>"",N35<=K35),"Low","In Stock")) -> In Stock | P35: =J35-I35 -> 20
A36: ITM-034 | B36: =A36&" · "&C36 -> ITM-034 · WOW 10" SLIM 1-MIC | C36: WOW 10" SLIM 1-MIC | E36: FILTERS | F36: 1 PC | I36: 48 | J36: 50 | L36: =SUMIFS('Stock Movements'!$E:$E,'Stock Movements'!$C:$C,$B36,'Stock Movements'!$D:$D,"In") -> 25 | M36: =SUMIFS('Stock Movements'!$E:$E,'Stock Movements'!$C:$C,$B36,'Stock Movements'!$D:$D,"Out") -> 0 | N36: =L36-M36 -> 25 | O36: =IF(N36<=0,"Out",IF(AND(K36<>"",N36<=K36),"Low","In Stock")) -> In Stock | P36: =J36-I36 -> 2
A37: ITM-035 | B37: =A37&" · "&C37 -> ITM-035 · UV LAMPS: UVC-PRO 6 GPM 14W | C37: UV LAMPS: UVC-PRO 6 GPM 14W | D37: 27-130-102 | E37: FILTERS | F37: 1 PC | I37: 1000 | L37: =SUMIFS('Stock Movements'!$E:$E,'Stock Movements'!$C:$C,$B37,'Stock Movements'!$D:$D,"In") -> 4 | M37: =SUMIFS('Stock Movements'!$E:$E,'Stock Movements'!$C:$C,$B37,'Stock Movements'!$D:$D,"Out") -> 0 | N37: =L37-M37 -> 4 | O37: =IF(N37<=0,"Out",IF(AND(K37<>"",N37<=K37),"Low","In Stock")) -> In Stock | P37: =J37-I37 -> -1000
A38: ITM-036 | B38: =A38&" · "&C38 -> ITM-036 · 350 ML PET BOTTLE (WITH CAP) | C38: 350 ML PET BOTTLE (WITH CAP) | D38: 10-170-106 | E38: PET BOTTLE | F38: 288 PCS | I38: 634 | J38: 860 | L38: =SUMIFS('Stock Movements'!$E:$E,'Stock Movements'!$C:$C,$B38,'Stock Movements'!$D:$D,"In") -> 32 | M38: =SUMIFS('Stock Movements'!$E:$E,'Stock Movements'!$C:$C,$B38,'Stock Movements'!$D:$D,"Out") -> 23 | N38: =L38-M38 -> 9 | O38: =IF(N38<=0,"Out",IF(AND(K38<>"",N38<=K38),"Low","In Stock")) -> In Stock | P38: =J38-I38 -> 226
A39: ITM-037 | B39: =A39&" · "&C39 -> ITM-037 · 350 ML PET BOTTLE (WITH CAP) | C39: 350 ML PET BOTTLE (WITH CAP) | D39: 10-170-106 | E39: PET BOTTLE | F39: 250 PCS | G39: SOLD | I39: 674 | J39: 900 | L39: =SUMIFS('Stock Movements'!$E:$E,'Stock Movements'!$C:$C,$B39,'Stock Movements'!$D:$D,"In") -> 15 | M39: =SUMIFS('Stock Movements'!$E:$E,'Stock Movements'!$C:$C,$B39,'Stock Movements'!$D:$D,"Out") -> 15 | N39: =L39-M39 -> 0 | O39: =IF(N39<=0,"Out",IF(AND(K39<>"",N39<=K39),"Low","In Stock")) -> Out | P39: =J39-I39 -> 226
A40: ITM-038 | B40: =A40&" · "&C40 -> ITM-038 · 500 ML PET BOTTLE (WITH CAP) | C40: 500 ML PET BOTTLE (WITH CAP) | D40: 10-170-115 | E40: PET BOTTLE | F40: 220 PCS | I40: 559 | J40: 760 | L40: =SUMIFS('Stock Movements'!$E:$E,'Stock Movements'!$C:$C,$B40,'Stock Movements'!$D:$D,"In") -> 10 | M40: =SUMIFS('Stock Movements'!$E:$E,'Stock Movements'!$C:$C,$B40,'Stock Movements'!$D:$D,"Out") -> 4 | N40: =L40-M40 -> 6 | O40: =IF(N40<=0,"Out",IF(AND(K40<>"",N40<=K40),"Low","In Stock")) -> In Stock | P40: =J40-I40 -> 201
A41: ITM-039 | B41: =A41&" · "&C41 -> ITM-039 · 1000 ML PET BOTTLE (WITH CAP) | C41: 1000 ML PET BOTTLE (WITH CAP) | E41: PET BOTTLE | F41: 120 PCS | I41: 552 | J41: 650 | L41: =SUMIFS('Stock Movements'!$E:$E,'Stock Movements'!$C:$C,$B41,'Stock Movements'!$D:$D,"In") -> 10 | M41: =SUMIFS('Stock Movements'!$E:$E,'Stock Movements'!$C:$C,$B41,'Stock Movements'!$D:$D,"Out") -> 3 | N41: =L41-M41 -> 7 | O41: =IF(N41<=0,"Out",IF(AND(K41<>"",N41<=K41),"Low","In Stock")) -> In Stock | P41: =J41-I41 -> 98
A42: ITM-040 | B42: =A42&" · "&C42 -> ITM-040 · 350 ML LABEL SHRINKABLE LW | C42: 350 ML LABEL SHRINKABLE LW | D42: 11-120-119 | E42: LABELS | F42: 500 PCS | I42: 280 | J42: 350 | L42: =SUMIFS('Stock Movements'!$E:$E,'Stock Movements'!$C:$C,$B42,'Stock Movements'!$D:$D,"In") -> 34 | M42: =SUMIFS('Stock Movements'!$E:$E,'Stock Movements'!$C:$C,$B42,'Stock Movements'!$D:$D,"Out") -> 19 | N42: =L42-M42 -> 15 | O42: =IF(N42<=0,"Out",IF(AND(K42<>"",N42<=K42),"Low","In Stock")) -> In Stock | P42: =J42-I42 -> 70
A43: ITM-041 | B43: =A43&" · "&C43 -> ITM-041 · 500 ML LABEL SHRINKABLE LW | C43: 500 ML LABEL SHRINKABLE LW | D43: 11-120-120 | E43: LABELS | F43: 500 PCS | I43: 320 | J43: 430 | L43: =SUMIFS('Stock Movements'!$E:$E,'Stock Movements'!$C:$C,$B43,'Stock Movements'!$D:$D,"In") -> 5 | M43: =SUMIFS('Stock Movements'!$E:$E,'Stock Movements'!$C:$C,$B43,'Stock Movements'!$D:$D,"Out") -> 0 | N43: =L43-M43 -> 5 | O43: =IF(N43<=0,"Out",IF(AND(K43<>"",N43<=K43),"Low","In Stock")) -> In Stock | P43: =J43-I43 -> 110
A44: ITM-042 | B44: =A44&" · "&C44 -> ITM-042 · 1000 ML LABEL SHRINKABLE LW | C44: 1000 ML LABEL SHRINKABLE LW | D44: 11-120-108 | E44: LABELS | F44: 500 PCS | I44: 385 | J44: 480 | L44: =SUMIFS('Stock Movements'!$E:$E,'Stock Movements'!$C:$C,$B44,'Stock Movements'!$D:$D,"In") -> 5 | M44: =SUMIFS('Stock Movements'!$E:$E,'Stock Movements'!$C:$C,$B44,'Stock Movements'!$D:$D,"Out") -> 1 | N44: =L44-M44 -> 4 | O44: =IF(N44<=0,"Out",IF(AND(K44<>"",N44<=K44),"Low","In Stock")) -> In Stock | P44: =J44-I44 -> 95
A45: ITM-043 | B45: =A45&" · "&C45 -> ITM-043 · 350 ML LABEL SHRINKABLE REFRESHING | C45: 350 ML LABEL SHRINKABLE REFRESHING | D45: 11-120-111 | E45: LABELS | F45: 500 PCS | I45: 188 | J45: 280 | L45: =SUMIFS('Stock Movements'!$E:$E,'Stock Movements'!$C:$C,$B45,'Stock Movements'!$D:$D,"In") -> 10 | M45: =SUMIFS('Stock Movements'!$E:$E,'Stock Movements'!$C:$C,$B45,'Stock Movements'!$D:$D,"Out") -> 2 | N45: =L45-M45 -> 8 | O45: =IF(N45<=0,"Out",IF(AND(K45<>"",N45<=K45),"Low","In Stock")) -> In Stock | P45: =J45-I45 -> 92
A46: ITM-044 | B46: =A46&" · "&C46 -> ITM-044 · 500 ML LABEL SHRINKABLE REFRESHING | C46: 500 ML LABEL SHRINKABLE REFRESHING | D46: 11-120-109 | E46: LABELS | F46: 500 PCS | I46: 217 | J46: 295 | L46: =SUMIFS('Stock Movements'!$E:$E,'Stock Movements'!$C:$C,$B46,'Stock Movements'!$D:$D,"In") -> 5 | M46: =SUMIFS('Stock Movements'!$E:$E,'Stock Movements'!$C:$C,$B46,'Stock Movements'!$D:$D,"Out") -> 0 | N46: =L46-M46 -> 5 | O46: =IF(N46<=0,"Out",IF(AND(K46<>"",N46<=K46),"Low","In Stock")) -> In Stock | P46: =J46-I46 -> 78
A47: ITM-045 | B47: =A47&" · "&C47 -> ITM-045 · STICKER LW WITH PIOLO - 5 GAL 6X4 | C47: STICKER LW WITH PIOLO - 5 GAL 6X4 | D47: 11-130-106 | E47: STICKER | F47: 100 PCS | I47: 400 | J47: 500 | L47: =SUMIFS('Stock Movements'!$E:$E,'Stock Movements'!$C:$C,$B47,'Stock Movements'!$D:$D,"In") -> 11 | M47: =SUMIFS('Stock Movements'!$E:$E,'Stock Movements'!$C:$C,$B47,'Stock Movements'!$D:$D,"Out") -> 2 | N47: =L47-M47 -> 9 | O47: =IF(N47<=0,"Out",IF(AND(K47<>"",N47<=K47),"Low","In Stock")) -> In Stock | P47: =J47-I47 -> 100
A48: ITM-046 | B48: =A48&" · "&C48 -> ITM-046 · BIG CAP REPLACEMENT - 5 GAL SLIM | C48: BIG CAP REPLACEMENT - 5 GAL SLIM | D48: 10-120-109 | E48: CAPS REPLACEMENT | F48: 1 PC | I48: 10 | J48: 15 | L48: =SUMIFS('Stock Movements'!$E:$E,'Stock Movements'!$C:$C,$B48,'Stock Movements'!$D:$D,"In") -> 500 | M48: =SUMIFS('Stock Movements'!$E:$E,'Stock Movements'!$C:$C,$B48,'Stock Movements'!$D:$D,"Out") -> 259 | N48: =L48-M48 -> 241 | O48: =IF(N48<=0,"Out",IF(AND(K48<>"",N48<=K48),"Low","In Stock")) -> In Stock | P48: =J48-I48 -> 5
A49: ITM-047 | B49: =A49&" · "&C49 -> ITM-047 · SMALL CAP REPLACEMENT - 5 GAL SLIM | C49: SMALL CAP REPLACEMENT - 5 GAL SLIM | D49: 10-120-111 | E49: CAPS REPLACEMENT | F49: 1 PC | I49: 3 | J49: 5 | L49: =SUMIFS('Stock Movements'!$E:$E,'Stock Movements'!$C:$C,$B49,'Stock Movements'!$D:$D,"In") -> 1500 | M49: =SUMIFS('Stock Movements'!$E:$E,'Stock Movements'!$C:$C,$B49,'Stock Movements'!$D:$D,"Out") -> 389 | N49: =L49-M49 -> 1111 | O49: =IF(N49<=0,"Out",IF(AND(K49<>"",N49<=K49),"Low","In Stock")) -> In Stock | P49: =J49-I49 -> 2
A50: ITM-048 | B50: =A50&" · "&C50 -> ITM-048 · FAUCET REPLACEMENT - 5 GAL SLIM | C50: FAUCET REPLACEMENT - 5 GAL SLIM | D50: 10-130-101 | E50: CAPS REPLACEMENT | F50: 1 PC | I50: 22 | J50: 30 | L50: =SUMIFS('Stock Movements'!$E:$E,'Stock Movements'!$C:$C,$B50,'Stock Movements'!$D:$D,"In") -> 500 | M50: =SUMIFS('Stock Movements'!$E:$E,'Stock Movements'!$C:$C,$B50,'Stock Movements'!$D:$D,"Out") -> 2 | N50: =L50-M50 -> 498 | O50: =IF(N50<=0,"Out",IF(AND(K50<>"",N50<=K50),"Low","In Stock")) -> In Stock | P50: =J50-I50 -> 8
A51: ITM-049 | B51: =A51&" · "&C51 -> ITM-049 · WHITE CAP REPLACEMENT - 5 GAL SLIM | C51: WHITE CAP REPLACEMENT - 5 GAL SLIM | D51: 10-120-110 | E51: CAPS REPLACEMENT | F51: 1 PC | I51: 8 | J51: 10 | L51: =SUMIFS('Stock Movements'!$E:$E,'Stock Movements'!$C:$C,$B51,'Stock Movements'!$D:$D,"In") -> 500 | M51: =SUMIFS('Stock Movements'!$E:$E,'Stock Movements'!$C:$C,$B51,'Stock Movements'!$D:$D,"Out") -> 100 | N51: =L51-M51 -> 400 | O51: =IF(N51<=0,"Out",IF(AND(K51<>"",N51<=K51),"Low","In Stock")) -> In Stock | P51: =J51-I51 -> 2
A52: ITM-050 | B52: =A52&" · "&C52 -> ITM-050 · CAP NON SPILL T-BACK - 5 GAL PET ROUND | C52: CAP NON SPILL T-BACK - 5 GAL PET ROUND | D52: 10-120-103 | E52: CAPS REPLACEMENT | F52: 1 PC | I52: 1.5 | J52: 4 | L52: =SUMIFS('Stock Movements'!$E:$E,'Stock Movements'!$C:$C,$B52,'Stock Movements'!$D:$D,"In") -> 500 | M52: =SUMIFS('Stock Movements'!$E:$E,'Stock Movements'!$C:$C,$B52,'Stock Movements'!$D:$D,"Out") -> 32 | N52: =L52-M52 -> 468 | O52: =IF(N52<=0,"Out",IF(AND(K52<>"",N52<=K52),"Low","In Stock")) -> In Stock | P52: =J52-I52 -> 2.5
A53: ITM-051 | B53: =A53&" · "&C53 -> ITM-051 · HOT AND COLD LIVINGWATER | C53: HOT AND COLD LIVINGWATER | D53: 25-240-119 | E53: DISPENSERS | F53: 1 PC | I53: 3700 | J53: 4100 | L53: =SUMIFS('Stock Movements'!$E:$E,'Stock Movements'!$C:$C,$B53,'Stock Movements'!$D:$D,"In") -> 2 | M53: =SUMIFS('Stock Movements'!$E:$E,'Stock Movements'!$C:$C,$B53,'Stock Movements'!$D:$D,"Out") -> 0 | N53: =L53-M53 -> 2 | O53: =IF(N53<=0,"Out",IF(AND(K53<>"",N53<=K53),"Low","In Stock")) -> In Stock | P53: =J53-I53 -> 400

Sheet Stock Movements
A1: STOCK MOVEMENTS (single ledger - replaces the old manual +N chains)
A2: Move ID | B2: Date | C2: Item Label | D2: Direction | E2: Quantity | F2: Buyer | G2: Source | H2: Reference | I2: Note
A3: MV-0001 | B3: 2026-05-16 | C3: ='Item Catalog'!$B$3 -> ITM-001 · 5 GAL SLIM CONTAINER W/ CAP BLUE | D3: In | E3: 526 | G3: Historical Import | H3: Restock (pre-migration cumulative) | I3: Historical cumulative total migrated from STOCK_REPORT.xlsx snapshot
A4: MV-0002 | B4: 2026-05-16 | C4: ='Item Catalog'!$B$3 -> ITM-001 · 5 GAL SLIM CONTAINER W/ CAP BLUE | D4: Out | E4: 87 | F4: A&G (LW-BAAO) | G4: Historical Import | H4: Wholesale/retail dispatch (pre-migration cumulative) | I4: Historical cumulative total migrated from STOCK_REPORT.xlsx snapshot
A5: MV-0003 | B5: 2026-05-16 | C5: ='Item Catalog'!$B$3 -> ITM-001 · 5 GAL SLIM CONTAINER W/ CAP BLUE | D5: Out | E5: 55 | F5: ALKAVIVA (BAAO) | G5: Historical Import | H5: Wholesale/retail dispatch (pre-migration cumulative) | I5: Historical cumulative total migrated from STOCK_REPORT.xlsx snapshot
A6: MV-0004 | B6: 2026-05-16 | C6: ='Item Catalog'!$B$3 -> ITM-001 · 5 GAL SLIM CONTAINER W/ CAP BLUE | D6: Out | E6: 100 | F6: CITY WATER (LW-TAPAYAS) | G6: Historical Import | H6: Wholesale/retail dispatch (pre-migration cumulative) | I6: Historical cumulative total migrated from STOCK_REPORT.xlsx snapshot
A7: MV-0005 | B7: 2026-05-16 | C7: ='Item Catalog'!$B$3 -> ITM-001 · 5 GAL SLIM CONTAINER W/ CAP BLUE | D7: Out | E7: 60 | F7: PURE DROP | G7: Historical Import | H7: Wholesale/retail dispatch (pre-migration cumulative) | I7: Historical cumulative total migrated from STOCK_REPORT.xlsx snapshot
A8: MV-0006 | B8: 2026-05-16 | C8: ='Item Catalog'!$B$3 -> ITM-001 · 5 GAL SLIM CONTAINER W/ CAP BLUE | D8: Out | E8: 19 | F8: LW (BATO) | G8: Historical Import | H8: Wholesale/retail dispatch (pre-migration cumulative) | I8: Historical cumulative total migrated from STOCK_REPORT.xlsx snapshot
A9: MV-0007 | B9: 2026-05-16 | C9: ='Item Catalog'!$B$3 -> ITM-001 · 5 GAL SLIM CONTAINER W/ CAP BLUE | D9: Out | E9: 58 | F9: SARALEX | G9: Historical Import | H9: Wholesale/retail dispatch (pre-migration cumulative) | I9: Historical cumulative total migrated from STOCK_REPORT.xlsx snapshot
A10: MV-0008 | B10: 2026-05-16 | C10: ='Item Catalog'!$B$3 -> ITM-001 · 5 GAL SLIM CONTAINER W/ CAP BLUE | D10: Out | E10: 59 | F10: CRYSTAL REF. STATION | G10: Historical Import | H10: Wholesale/retail dispatch (pre-migration cumulative) | I10: Historical cumulative total migrated from STOCK_REPORT.xlsx snapshot
A11: MV-0009 | B11: 2026-05-16 | C11: ='Item Catalog'!$B$3 -> ITM-001 · 5 GAL SLIM CONTAINER W/ CAP BLUE | D11: Out | E11: 28 | F11: WATER MARKET (BAAO) | G11: Historical Import | H11: Wholesale/retail dispatch (pre-migration cumulative) | I11: Historical cumulative total migrated from STOCK_REPORT.xlsx snapshot
A12: MV-0010 | B12: 2026-05-16 | C12: ='Item Catalog'!$B$3 -> ITM-001 · 5 GAL SLIM CONTAINER W/ CAP BLUE | D12: Out | E12: 25 | F12: AQUARES | G12: Historical Import | H12: Wholesale/retail dispatch (pre-migration cumulative) | I12: Historical cumulative total migrated from STOCK_REPORT.xlsx snapshot
A13: MV-0011 | B13: 2026-05-16 | C13: ='Item Catalog'!$B$3 -> ITM-001 · 5 GAL SLIM CONTAINER W/ CAP BLUE | D13: Out | E13: 35 | F13: ALKAVIVA (BARAS) | G13: Historical Import | H13: Wholesale/retail dispatch (pre-migration cumulative) | I13: Historical cumulative total migrated from STOCK_REPORT.xlsx snapshot
A14: MV-0012 | B14: 2026-05-16 | C14: ='Item Catalog'!$B$4 -> ITM-002 · 5 GAL SLIM CONTAINER W/ CAP BLUE-WOW | D14: In | E14: 200 | G14: Historical Import | H14: Restock (pre-migration cumulative) | I14: Historical cumulative total migrated from STOCK_REPORT.xlsx snapshot
A15: MV-0013 | B15: 2026-05-16 | C15: ='Item Catalog'!$B$4 -> ITM-002 · 5 GAL SLIM CONTAINER W/ CAP BLUE-WOW | D15: Out | E15: 18 | F15: A&G (LW-BAAO) | G15: Historical Import | H15: Wholesale/retail dispatch (pre-migration cumulative) | I15: Historical cumulative total migrated from STOCK_REPORT.xlsx snapshot
A16: MV-0014 | B16: 2026-05-16 | C16: ='Item Catalog'!$B$4 -> ITM-002 · 5 GAL SLIM CONTAINER W/ CAP BLUE-WOW | D16: Out | E16: 5 | F16: ALKAVIVA (BAAO) | G16: Historical Import | H16: Wholesale/retail dispatch (pre-migration cumulative) | I16: Historical cumulative total migrated from STOCK_REPORT.xlsx snapshot
A17: MV-0015 | B17: 2026-05-16 | C17: ='Item Catalog'!$B$4 -> ITM-002 · 5 GAL SLIM CONTAINER W/ CAP BLUE-WOW | D17: Out | E17: 10 | F17: PURE DROP | G17: Historical Import | H17: Wholesale/retail dispatch (pre-migration cumulative) | I17: Historical cumulative total migrated from STOCK_REPORT.xlsx snapshot
A18: MV-0016 | B18: 2026-05-16 | C18: ='Item Catalog'!$B$4 -> ITM-002 · 5 GAL SLIM CONTAINER W/ CAP BLUE-WOW | D18: Out | E18: 20 | F18: CRYSTAL REF. STATION | G18: Historical Import | H18: Wholesale/retail dispatch (pre-migration cumulative) | I18: Historical cumulative total migrated from STOCK_REPORT.xlsx snapshot
A19: MV-0017 | B19: 2026-05-16 | C19: ='Item Catalog'!$B$5 -> ITM-003 · 5 GAL SLIM CONTAINER W/ CAP GREEN | D19: In | E19: 350 | G19: Historical Import | H19: Restock (pre-migration cumulative) | I19: Historical cumulative total migrated from STOCK_REPORT.xlsx snapshot
A20: MV-0018 | B20: 2026-05-16 | C20: ='Item Catalog'!$B$5 -> ITM-003 · 5 GAL SLIM CONTAINER W/ CAP GREEN | D20: Out | E20: 81 | F20: A&G (LW-BAAO) | G20: Historical Import | H20: Wholesale/retail dispatch (pre-migration cumulative) | I20: Historical cumulative total migrated from STOCK_REPORT.xlsx snapshot
A21: MV-0019 | B21: 2026-05-16 | C21: ='Item Catalog'!$B$5 -> ITM-003 · 5 GAL SLIM CONTAINER W/ CAP GREEN | D21: Out | E21: 8 | F21: CRYSTAL REF. STATION | G21: Historical Import | H21: Wholesale/retail dispatch (pre-migration cumulative) | I21: Historical cumulative total migrated from STOCK_REPORT.xlsx snapshot
A22: MV-0020 | B22: 2026-05-16 | C22: ='Item Catalog'!$B$5 -> ITM-003 · 5 GAL SLIM CONTAINER W/ CAP GREEN | D22: Out | E22: 35 | F22: ALKAVIVA (BARAS) | G22: Historical Import | H22: Wholesale/retail dispatch (pre-migration cumulative) | I22: Historical cumulative total migrated from STOCK_REPORT.xlsx snapshot
A23: MV-0021 | B23: 2026-05-16 | C23: ='Item Catalog'!$B$5 -> ITM-003 · 5 GAL SLIM CONTAINER W/ CAP GREEN | D23: Out | E23: 91 | F23: WATER MARKET (BAAO) | G23: Historical Import | H23: Wholesale/retail dispatch (pre-migration cumulative) | I23: Historical cumulative total migrated from STOCK_REPORT.xlsx snapshot
A24: MV-0022 | B24: 2026-05-16 | C24: ='Item Catalog'!$B$5 -> ITM-003 · 5 GAL SLIM CONTAINER W/ CAP GREEN | D24: Out | E24: 5 | F24: AQUARES | G24: Historical Import | H24: Wholesale/retail dispatch (pre-migration cumulative) | I24: Historical cumulative total migrated from STOCK_REPORT.xlsx snapshot
A25: MV-0023 | B25: 2026-05-16 | C25: ='Item Catalog'!$B$6 -> ITM-004 · 5 GAL SLIM CONTAINER W/ CAP YELLOW | D25: In | E25: 350 | G25: Historical Import | H25: Restock (pre-migration cumulative) | I25: Historical cumulative total migrated from STOCK_REPORT.xlsx snapshot
A26: MV-0024 | B26: 2026-05-16 | C26: ='Item Catalog'!$B$6 -> ITM-004 · 5 GAL SLIM CONTAINER W/ CAP YELLOW | D26: Out | E26: 38 | F26: A&G (LW-BAAO) | G26: Historical Import | H26: Wholesale/retail dispatch (pre-migration cumulative) | I26: Historical cumulative total migrated from STOCK_REPORT.xlsx snapshot
A27: MV-0025 | B27: 2026-05-16 | C27: ='Item Catalog'!$B$6 -> ITM-004 · 5 GAL SLIM CONTAINER W/ CAP YELLOW | D27: Out | E27: 10 | F27: CRYSTAL REF. STATION | G27: Historical Import | H27: Wholesale/retail dispatch (pre-migration cumulative) | I27: Historical cumulative total migrated from STOCK_REPORT.xlsx snapshot
A28: MV-0026 | B28: 2026-05-16 | C28: ='Item Catalog'!$B$6 -> ITM-004 · 5 GAL SLIM CONTAINER W/ CAP YELLOW | D28: Out | E28: 10 | F28: ALKAVIVA (BARAS) | G28: Historical Import | H28: Wholesale/retail dispatch (pre-migration cumulative) | I28: Historical cumulative total migrated from STOCK_REPORT.xlsx snapshot
A29: MV-0027 | B29: 2026-05-16 | C29: ='Item Catalog'!$B$7 -> ITM-005 · 5 GAL (PET) ROUND CONTAINER BLUE W/ CAP (CLASS A) | D29: In | E29: 200 | G29: Historical Import | H29: Restock (pre-migration cumulative) | I29: Historical cumulative total migrated from STOCK_REPORT.xlsx snapshot
A30: MV-0028 | B30: 2026-05-16 | C30: ='Item Catalog'!$B$7 -> ITM-005 · 5 GAL (PET) ROUND CONTAINER BLUE W/ CAP (CLASS A) | D30: Out | E30: 35 | F30: A&G (LW-BAAO) | G30: Historical Import | H30: Wholesale/retail dispatch (pre-migration cumulative) | I30: Historical cumulative total migrated from STOCK_REPORT.xlsx snapshot
A31: MV-0029 | B31: 2026-05-16 | C31: ='Item Catalog'!$B$7 -> ITM-005 · 5 GAL (PET) ROUND CONTAINER BLUE W/ CAP (CLASS A) | D31: Out | E31: 5 | F31: ALKAVIVA (BAAO) | G31: Historical Import | H31: Wholesale/retail dispatch (pre-migration cumulative) | I31: Historical cumulative total migrated from STOCK_REPORT.xlsx snapshot
A32: MV-0030 | B32: 2026-05-16 | C32: ='Item Catalog'!$B$7 -> ITM-005 · 5 GAL (PET) ROUND CONTAINER BLUE W/ CAP (CLASS A) | D32: Out | E32: 15 | F32: CITY WATER (LW-TAPAYAS) | G32: Historical Import | H32: Wholesale/retail dispatch (pre-migration cumulative) | I32: Historical cumulative total migrated from STOCK_REPORT.xlsx snapshot
A33: MV-0031 | B33: 2026-05-16 | C33: ='Item Catalog'!$B$7 -> ITM-005 · 5 GAL (PET) ROUND CONTAINER BLUE W/ CAP (CLASS A) | D33: Out | E33: 60 | F33: PURE DROP | G33: Historical Import | H33: Wholesale/retail dispatch (pre-migration cumulative) | I33: Historical cumulative total migrated from STOCK_REPORT.xlsx snapshot
A34: MV-0032 | B34: 2026-05-16 | C34: ='Item Catalog'!$B$7 -> ITM-005 · 5 GAL (PET) ROUND CONTAINER BLUE W/ CAP (CLASS A) | D34: Out | E34: 9 | F34: LW (BATO) | G34: Historical Import | H34: Wholesale/retail dispatch (pre-migration cumulative) | I34: Historical cumulative total migrated from STOCK_REPORT.xlsx snapshot
A35: MV-0033 | B35: 2026-05-16 | C35: ='Item Catalog'!$B$7 -> ITM-005 · 5 GAL (PET) ROUND CONTAINER BLUE W/ CAP (CLASS A) | D35: Out | E35: 6 | F35: SARALEX | G35: Historical Import | H35: Wholesale/retail dispatch (pre-migration cumulative) | I35: Historical cumulative total migrated from STOCK_REPORT.xlsx snapshot
A36: MV-0034 | B36: 2026-05-16 | C36: ='Item Catalog'!$B$7 -> ITM-005 · 5 GAL (PET) ROUND CONTAINER BLUE W/ CAP (CLASS A) | D36: Out | E36: 13 | F36: CRYSTAL REF. STATION | G36: Historical Import | H36: Wholesale/retail dispatch (pre-migration cumulative) | I36: Historical cumulative total migrated from STOCK_REPORT.xlsx snapshot
A37: MV-0035 | B37: 2026-05-16 | C37: ='Item Catalog'!$B$7 -> ITM-005 · 5 GAL (PET) ROUND CONTAINER BLUE W/ CAP (CLASS A) | D37: Out | E37: 9 | F37: WATER MARKET (BAAO) | G37: Historical Import | H37: Wholesale/retail dispatch (pre-migration cumulative) | I37: Historical cumulative total migrated from STOCK_REPORT.xlsx snapshot
A38: MV-0036 | B38: 2026-05-16 | C38: ='Item Catalog'!$B$7 -> ITM-005 · 5 GAL (PET) ROUND CONTAINER BLUE W/ CAP (CLASS A) | D38: Out | E38: 25 | F38: AQUARES | G38: Historical Import | H38: Wholesale/retail dispatch (pre-migration cumulative) | I38: Historical cumulative total migrated from STOCK_REPORT.xlsx snapshot
A39: MV-0037 | B39: 2026-05-16 | C39: ='Item Catalog'!$B$7 -> ITM-005 · 5 GAL (PET) ROUND CONTAINER BLUE W/ CAP (CLASS A) | D39: Out | E39: 22 | F39: ALKAVIVA (BARAS) | G39: Historical Import | H39: Wholesale/retail dispatch (pre-migration cumulative) | I39: Historical cumulative total migrated from STOCK_REPORT.xlsx snapshot
A40: MV-0038 | B40: 2026-05-16 | C40: ='Item Catalog'!$B$8 -> ITM-006 · 5 GAL (PET) ROUND CONTAINER BLUE W/ CAP (CLASS A) | D40: In | E40: 100 | G40: Historical Import | H40: Restock (pre-migration cumulative) | I40: Historical cumulative total migrated from STOCK_REPORT.xlsx snapshot
A41: MV-0039 | B41: 2026-05-16 | C41: ='Item Catalog'!$B$8 -> ITM-006 · 5 GAL (PET) ROUND CONTAINER BLUE W/ CAP (CLASS A) | D41: Out | E41: 5 | F41: A&G (LW-BAAO) | G41: Historical Import | H41: Wholesale/retail dispatch (pre-migration cumulative) | I41: Historical cumulative total migrated from STOCK_REPORT.xlsx snapshot
A42: MV-0040 | B42: 2026-05-16 | C42: ='Item Catalog'!$B$8 -> ITM-006 · 5 GAL (PET) ROUND CONTAINER BLUE W/ CAP (CLASS A) | D42: Out | E42: 1 | F42: WATER MARKET (BAAO) | G42: Historical Import | H42: Wholesale/retail dispatch (pre-migration cumulative) | I42: Historical cumulative total migrated from STOCK_REPORT.xlsx snapshot
A43: MV-0041 | B43: 2026-05-16 | C43: ='Item Catalog'!$B$8 -> ITM-006 · 5 GAL (PET) ROUND CONTAINER BLUE W/ CAP (CLASS A) | D43: Out | E43: 5 | F43: ALKAVIVA (BARAS) | G43: Historical Import | H43: Wholesale/retail dispatch (pre-migration cumulative) | I43: Historical cumulative total migrated from STOCK_REPORT.xlsx snapshot
A44: MV-0042 | B44: 2026-05-16 | C44: ='Item Catalog'!$B$9 -> ITM-007 · BIG CAP SEAL FOR SLIM LW | D44: In | E44: 100 | G44: Historical Import | H44: Restock (pre-migration cumulative) | I44: Historical cumulative total migrated from STOCK_REPORT.xlsx snapshot
A45: MV-0043 | B45: 2026-05-16 | C45: ='Item Catalog'!$B$9 -> ITM-007 · BIG CAP SEAL FOR SLIM LW | D45: Out | E45: 49 | F45: A&G (LW-BAAO) | G45: Historical Import | H45: Wholesale/retail dispatch (pre-migration cumulative) | I45: Historical cumulative total migrated from STOCK_REPORT.xlsx snapshot
A46: MV-0044 | B46: 2026-05-16 | C46: ='Item Catalog'!$B$9 -> ITM-007 · BIG CAP SEAL FOR SLIM LW | D46: Out | E46: 3 | F46: CITY WATER (LW-TAPAYAS) | G46: Historical Import | H46: Wholesale/retail dispatch (pre-migration cumulative) | I46: Historical cumulative total migrated from STOCK_REPORT.xlsx snapshot
A47: MV-0045 | B47: 2026-05-16 | C47: ='Item Catalog'!$B$9 -> ITM-007 · BIG CAP SEAL FOR SLIM LW | D47: Out | E47: 3 | F47: LW (BATO) | G47: Historical Import | H47: Wholesale/retail dispatch (pre-migration cumulative) | I47: Historical cumulative total migrated from STOCK_REPORT.xlsx snapshot
A48: MV-0046 | B48: 2026-05-16 | C48: ='Item Catalog'!$B$10 -> ITM-008 · SMALL CAP SEAL FOR SLIM LW | D48: In | E48: 100 | G48: Historical Import | H48: Restock (pre-migration cumulative) | I48: Historical cumulative total migrated from STOCK_REPORT.xlsx snapshot
A49: MV-0047 | B49: 2026-05-16 | C49: ='Item Catalog'!$B$10 -> ITM-008 · SMALL CAP SEAL FOR SLIM LW | D49: Out | E49: 19 | F49: A&G (LW-BAAO) | G49: Historical Import | H49: Wholesale/retail dispatch (pre-migration cumulative) | I49: Historical cumulative total migrated from STOCK_REPORT.xlsx snapshot
A50: MV-0048 | B50: 2026-05-16 | C50: ='Item Catalog'!$B$10 -> ITM-008 · SMALL CAP SEAL FOR SLIM LW | D50: Out | E50: 1 | F50: CITY WATER (LW-TAPAYAS) | G50: Historical Import | H50: Wholesale/retail dispatch (pre-migration cumulative) | I50: Historical cumulative total migrated from STOCK_REPORT.xlsx snapshot
A51: MV-0049 | B51: 2026-05-16 | C51: ='Item Catalog'!$B$10 -> ITM-008 · SMALL CAP SEAL FOR SLIM LW | D51: Out | E51: 4 | F51: LW (BATO) | G51: Historical Import | H51: Wholesale/retail dispatch (pre-migration cumulative) | I51: Historical cumulative total migrated from STOCK_REPORT.xlsx snapshot
A52: MV-0050 | B52: 2026-05-16 | C52: ='Item Catalog'!$B$11 -> ITM-009 · FAUCET SEAL FOR SLIM LW | D52: In | E52: 100 | G52: Historical Import | H52: Restock (pre-migration cumulative) | I52: Historical cumulative total migrated from STOCK_REPORT.xlsx snapshot
A53: MV-0051 | B53: 2026-05-16 | C53: ='Item Catalog'!$B$11 -> ITM-009 · FAUCET SEAL FOR SLIM LW | D53: Out | E53: 28 | F53: A&G (LW-BAAO) | G53: Historical Import | H53: Wholesale/retail dispatch (pre-migration cumulative) | I53: Historical cumulative total migrated from STOCK_REPORT.xlsx snapshot
A54: MV-0052 | B54: 2026-05-16 | C54: ='Item Catalog'!$B$11 -> ITM-009 · FAUCET SEAL FOR SLIM LW | D54: Out | E54: 5 | F54: CITY WATER (LW-TAPAYAS) | G54: Historical Import | H54: Wholesale/retail dispatch (pre-migration cumulative) | I54: Historical cumulative total migrated from STOCK_REPORT.xlsx snapshot
A55: MV-0053 | B55: 2026-05-16 | C55: ='Item Catalog'!$B$11 -> ITM-009 · FAUCET SEAL FOR SLIM LW | D55: Out | E55: 20 | F55: LW (SORSOGON) | G55: Historical Import | H55: Wholesale/retail dispatch (pre-migration cumulative) | I55: Historical cumulative total migrated from STOCK_REPORT.xlsx snapshot
A56: MV-0054 | B56: 2026-05-16 | C56: ='Item Catalog'!$B$11 -> ITM-009 · FAUCET SEAL FOR SLIM LW | D56: Out | E56: 7 | F56: LW (BATO) | G56: Historical Import | H56: Wholesale/retail dispatch (pre-migration cumulative) | I56: Historical cumulative total migrated from STOCK_REPORT.xlsx snapshot
A57: MV-0055 | B57: 2026-05-16 | C57: ='Item Catalog'!$B$11 -> ITM-009 · FAUCET SEAL FOR SLIM LW | D57: Out | E57: 2 | F57: ALKAVIVA (BARAS) | G57: Historical Import | H57: Wholesale/retail dispatch (pre-migration cumulative) | I57: Historical cumulative total migrated from STOCK_REPORT.xlsx snapshot
A58: MV-0056 | B58: 2026-05-16 | C58: ='Item Catalog'!$B$12 -> ITM-010 · FAUCET SEAL FOR SLIM LW (CLASS B) | D58: In | E58: 25 | G58: Historical Import | H58: Restock (pre-migration cumulative) | I58: Historical cumulative total migrated from STOCK_REPORT.xlsx snapshot
A59: MV-0057 | B59: 2026-05-16 | C59: ='Item Catalog'!$B$13 -> ITM-011 · UMBRELLA SEAL FOR ROUND LW | D59: In | E59: 100 | G59: Historical Import | H59: Restock (pre-migration cumulative) | I59: Historical cumulative total migrated from STOCK_REPORT.xlsx snapshot
A60: MV-0058 | B60: 2026-05-16 | C60: ='Item Catalog'!$B$13 -> ITM-011 · UMBRELLA SEAL FOR ROUND LW | D60: Out | E60: 8 | F60: A&G (LW-BAAO) | G60: Historical Import | H60: Wholesale/retail dispatch (pre-migration cumulative) | I60: Historical cumulative total migrated from STOCK_REPORT.xlsx snapshot
A61: MV-0059 | B61: 2026-05-16 | C61: ='Item Catalog'!$B$13 -> ITM-011 · UMBRELLA SEAL FOR ROUND LW | D61: Out | E61: 2 | F61: CITY WATER (LW-TAPAYAS) | G61: Historical Import | H61: Wholesale/retail dispatch (pre-migration cumulative) | I61: Historical cumulative total migrated from STOCK_REPORT.xlsx snapshot
A62: MV-0060 | B62: 2026-05-16 | C62: ='Item Catalog'!$B$13 -> ITM-011 · UMBRELLA SEAL FOR ROUND LW | D62: Out | E62: 20 | F62: LW (SORSOGON) | G62: Historical Import | H62: Wholesale/retail dispatch (pre-migration cumulative) | I62: Historical cumulative total migrated from STOCK_REPORT.xlsx snapshot
A63: MV-0061 | B63: 2026-05-16 | C63: ='Item Catalog'!$B$13 -> ITM-011 · UMBRELLA SEAL FOR ROUND LW | D63: Out | E63: 2 | F63: LW (BATO) | G63: Historical Import | H63: Wholesale/retail dispatch (pre-migration cumulative) | I63: Historical cumulative total migrated from STOCK_REPORT.xlsx snapshot
A64: MV-0062 | B64: 2026-05-16 | C64: ='Item Catalog'!$B$13 -> ITM-011 · UMBRELLA SEAL FOR ROUND LW | D64: Out | E64: 1 | F64: LANON W.R.S. | G64: Historical Import | H64: Wholesale/retail dispatch (pre-migration cumulative) | I64: Historical cumulative total migrated from STOCK_REPORT.xlsx snapshot
A65: MV-0063 | B65: 2026-05-16 | C65: ='Item Catalog'!$B$14 -> ITM-012 · UMBRELLA SEAL FOR ROUND LW (CLASS B) | D65: In | E65: 50 | G65: Historical Import | H65: Restock (pre-migration cumulative) | I65: Historical cumulative total migrated from STOCK_REPORT.xlsx snapshot
A66: MV-0064 | B66: 2026-05-16 | C66: ='Item Catalog'!$B$15 -> ITM-013 · BIG CAP SEAL FOR SLIM GENERIC | D66: In | E66: 100 | G66: Historical Import | H66: Restock (pre-migration cumulative) | I66: Historical cumulative total migrated from STOCK_REPORT.xlsx snapshot
A67: MV-0065 | B67: 2026-05-16 | C67: ='Item Catalog'!$B$15 -> ITM-013 · BIG CAP SEAL FOR SLIM GENERIC | D67: Out | E67: 5 | F67: ALKAVIVA (BAAO) | G67: Historical Import | H67: Wholesale/retail dispatch (pre-migration cumulative) | I67: Historical cumulative total migrated from STOCK_REPORT.xlsx snapshot
A68: MV-0066 | B68: 2026-05-16 | C68: ='Item Catalog'!$B$15 -> ITM-013 · BIG CAP SEAL FOR SLIM GENERIC | D68: Out | E68: 11 | F68: CITY WATER (LW-TAPAYAS) | G68: Historical Import | H68: Wholesale/retail dispatch (pre-migration cumulative) | I68: Historical cumulative total migrated from STOCK_REPORT.xlsx snapshot
A69: MV-0067 | B69: 2026-05-16 | C69: ='Item Catalog'!$B$15 -> ITM-013 · BIG CAP SEAL FOR SLIM GENERIC | D69: Out | E69: 3 | F69: PURE DROP | G69: Historical Import | H69: Wholesale/retail dispatch (pre-migration cumulative) | I69: Historical cumulative total migrated from STOCK_REPORT.xlsx snapshot
A70: MV-0068 | B70: 2026-05-16 | C70: ='Item Catalog'!$B$15 -> ITM-013 · BIG CAP SEAL FOR SLIM GENERIC | D70: Out | E70: 5 | F70: LW (BATO) | G70: Historical Import | H70: Wholesale/retail dispatch (pre-migration cumulative) | I70: Historical cumulative total migrated from STOCK_REPORT.xlsx snapshot
A71: MV-0069 | B71: 2026-05-16 | C71: ='Item Catalog'!$B$15 -> ITM-013 · BIG CAP SEAL FOR SLIM GENERIC | D71: Out | E71: 5 | F71: SARALEX | G71: Historical Import | H71: Wholesale/retail dispatch (pre-migration cumulative) | I71: Historical cumulative total migrated from STOCK_REPORT.xlsx snapshot
A72: MV-0070 | B72: 2026-05-16 | C72: ='Item Catalog'!$B$15 -> ITM-013 · BIG CAP SEAL FOR SLIM GENERIC | D72: Out | E72: 14 | F72: CRYSTAL REF. STATION | G72: Historical Import | H72: Wholesale/retail dispatch (pre-migration cumulative) | I72: Historical cumulative total migrated from STOCK_REPORT.xlsx snapshot
A73: MV-0071 | B73: 2026-05-16 | C73: ='Item Catalog'!$B$15 -> ITM-013 · BIG CAP SEAL FOR SLIM GENERIC | D73: Out | E73: 20 | F73: WATER MARKET (BAAO) | G73: Historical Import | H73: Wholesale/retail dispatch (pre-migration cumulative) | I73: Historical cumulative total migrated from STOCK_REPORT.xlsx snapshot
A74: MV-0072 | B74: 2026-05-16 | C74: ='Item Catalog'!$B$15 -> ITM-013 · BIG CAP SEAL FOR SLIM GENERIC | D74: Out | E74: 10 | F74: AQUARES | G74: Historical Import | H74: Wholesale/retail dispatch (pre-migration cumulative) | I74: Historical cumulative total migrated from STOCK_REPORT.xlsx snapshot
A75: MV-0073 | B75: 2026-05-16 | C75: ='Item Catalog'!$B$15 -> ITM-013 · BIG CAP SEAL FOR SLIM GENERIC | D75: Out | E75: 1 | F75: LANON W.R.S. | G75: Historical Import | H75: Wholesale/retail dispatch (pre-migration cumulative) | I75: Historical cumulative total migrated from STOCK_REPORT.xlsx snapshot
A76: MV-0074 | B76: 2026-05-16 | C76: ='Item Catalog'!$B$15 -> ITM-013 · BIG CAP SEAL FOR SLIM GENERIC | D76: Out | E76: 2 | F76: W.L.D. REF. STN (BATO) | G76: Historical Import | H76: Wholesale/retail dispatch (pre-migration cumulative) | I76: Historical cumulative total migrated from STOCK_REPORT.xlsx snapshot
A77: MV-0075 | B77: 2026-05-16 | C77: ='Item Catalog'!$B$15 -> ITM-013 · BIG CAP SEAL FOR SLIM GENERIC | D77: Out | E77: 19 | F77: ALKAVIVA (BARAS) | G77: Historical Import | H77: Wholesale/retail dispatch (pre-migration cumulative) | I77: Historical cumulative total migrated from STOCK_REPORT.xlsx snapshot
A78: MV-0076 | B78: 2026-05-16 | C78: ='Item Catalog'!$B$15 -> ITM-013 · BIG CAP SEAL FOR SLIM GENERIC | D78: Out | E78: 5 | F78: SHAUNTI REF. STN. | G78: Historical Import | H78: Wholesale/retail dispatch (pre-migration cumulative) | I78: Historical cumulative total migrated from STOCK_REPORT.xlsx snapshot
A79: MV-0077 | B79: 2026-05-16 | C79: ='Item Catalog'!$B$16 -> ITM-014 · SMALL CAP SEAL FOR SLIM GENERIC | D79: In | E79: 100 | G79: Historical Import | H79: Restock (pre-migration cumulative) | I79: Historical cumulative total migrated from STOCK_REPORT.xlsx snapshot
A80: MV-0078 | B80: 2026-05-16 | C80: ='Item Catalog'!$B$16 -> ITM-014 · SMALL CAP SEAL FOR SLIM GENERIC | D80: Out | E80: 1 | F80: A&G (LW-BAAO) | G80: Historical Import | H80: Wholesale/retail dispatch (pre-migration cumulative) | I80: Historical cumulative total migrated from STOCK_REPORT.xlsx snapshot
A81: MV-0079 | B81: 2026-05-16 | C81: ='Item Catalog'!$B$16 -> ITM-014 · SMALL CAP SEAL FOR SLIM GENERIC | D81: Out | E81: 1 | F81: ALKAVIVA (BAAO) | G81: Historical Import | H81: Wholesale/retail dispatch (pre-migration cumulative) | I81: Historical cumulative total migrated from STOCK_REPORT.xlsx snapshot
A82: MV-0080 | B82: 2026-05-16 | C82: ='Item Catalog'!$B$16 -> ITM-014 · SMALL CAP SEAL FOR SLIM GENERIC | D82: Out | E82: 4 | F82: CITY WATER (LW-TAPAYAS) | G82: Historical Import | H82: Wholesale/retail dispatch (pre-migration cumulative) | I82: Historical cumulative total migrated from STOCK_REPORT.xlsx snapshot
A83: MV-0081 | B83: 2026-05-16 | C83: ='Item Catalog'!$B$16 -> ITM-014 · SMALL CAP SEAL FOR SLIM GENERIC | D83: Out | E83: 1 | F83: PURE DROP | G83: Historical Import | H83: Wholesale/retail dispatch (pre-migration cumulative) | I83: Historical cumulative total migrated from STOCK_REPORT.xlsx snapshot
A84: MV-0082 | B84: 2026-05-16 | C84: ='Item Catalog'!$B$16 -> ITM-014 · SMALL CAP SEAL FOR SLIM GENERIC | D84: Out | E84: 5 | F84: SARALEX | G84: Historical Import | H84: Wholesale/retail dispatch (pre-migration cumulative) | I84: Historical cumulative total migrated from STOCK_REPORT.xlsx snapshot
A85: MV-0083 | B85: 2026-05-16 | C85: ='Item Catalog'!$B$16 -> ITM-014 · SMALL CAP SEAL FOR SLIM GENERIC | D85: Out | E85: 5 | F85: CRYSTAL REF. STATION | G85: Historical Import | H85: Wholesale/retail dispatch (pre-migration cumulative) | I85: Historical cumulative total migrated from STOCK_REPORT.xlsx snapshot
A86: MV-0084 | B86: 2026-05-16 | C86: ='Item Catalog'!$B$16 -> ITM-014 · SMALL CAP SEAL FOR SLIM GENERIC | D86: Out | E86: 5 | F86: WATER MARKET (BAAO) | G86: Historical Import | H86: Wholesale/retail dispatch (pre-migration cumulative) | I86: Historical cumulative total migrated from STOCK_REPORT.xlsx snapshot
A87: MV-0085 | B87: 2026-05-16 | C87: ='Item Catalog'!$B$16 -> ITM-014 · SMALL CAP SEAL FOR SLIM GENERIC | D87: Out | E87: 4 | F87: AQUARES | G87: Historical Import | H87: Wholesale/retail dispatch (pre-migration cumulative) | I87: Historical cumulative total migrated from STOCK_REPORT.xlsx snapshot
A88: MV-0086 | B88: 2026-05-16 | C88: ='Item Catalog'!$B$16 -> ITM-014 · SMALL CAP SEAL FOR SLIM GENERIC | D88: Out | E88: 1 | F88: LANON W.R.S. | G88: Historical Import | H88: Wholesale/retail dispatch (pre-migration cumulative) | I88: Historical cumulative total migrated from STOCK_REPORT.xlsx snapshot
A89: MV-0087 | B89: 2026-05-16 | C89: ='Item Catalog'!$B$16 -> ITM-014 · SMALL CAP SEAL FOR SLIM GENERIC | D89: Out | E89: 2 | F89: W.L.D. REF. STN (BATO) | G89: Historical Import | H89: Wholesale/retail dispatch (pre-migration cumulative) | I89: Historical cumulative total migrated from STOCK_REPORT.xlsx snapshot
A90: MV-0088 | B90: 2026-05-16 | C90: ='Item Catalog'!$B$16 -> ITM-014 · SMALL CAP SEAL FOR SLIM GENERIC | D90: Out | E90: 7 | F90: ALKAVIVA (BARAS) | G90: Historical Import | H90: Wholesale/retail dispatch (pre-migration cumulative) | I90: Historical cumulative total migrated from STOCK_REPORT.xlsx snapshot
A91: MV-0089 | B91: 2026-05-16 | C91: ='Item Catalog'!$B$17 -> ITM-015 · FAUCET SEAL FOR SLIM GENERIC | D91: In | E91: 100 | G91: Historical Import | H91: Restock (pre-migration cumulative) | I91: Historical cumulative total migrated from STOCK_REPORT.xlsx snapshot
A92: MV-0090 | B92: 2026-05-16 | C92: ='Item Catalog'!$B$17 -> ITM-015 · FAUCET SEAL FOR SLIM GENERIC | D92: Out | E92: 2 | F92: A&G (LW-BAAO) | G92: Historical Import | H92: Wholesale/retail dispatch (pre-migration cumulative) | I92: Historical cumulative total migrated from STOCK_REPORT.xlsx snapshot
A93: MV-0091 | B93: 2026-05-16 | C93: ='Item Catalog'!$B$17 -> ITM-015 · FAUCET SEAL FOR SLIM GENERIC | D93: Out | E93: 1 | F93: ALKAVIVA (BAAO) | G93: Historical Import | H93: Wholesale/retail dispatch (pre-migration cumulative) | I93: Historical cumulative total migrated from STOCK_REPORT.xlsx snapshot
A94: MV-0092 | B94: 2026-05-16 | C94: ='Item Catalog'!$B$17 -> ITM-015 · FAUCET SEAL FOR SLIM GENERIC | D94: Out | E94: 28 | F94: CITY WATER (LW-TAPAYAS) | G94: Historical Import | H94: Wholesale/retail dispatch (pre-migration cumulative) | I94: Historical cumulative total migrated from STOCK_REPORT.xlsx snapshot
A95: MV-0093 | B95: 2026-05-16 | C95: ='Item Catalog'!$B$17 -> ITM-015 · FAUCET SEAL FOR SLIM GENERIC | D95: Out | E95: 2 | F95: PURE DROP | G95: Historical Import | H95: Wholesale/retail dispatch (pre-migration cumulative) | I95: Historical cumulative total migrated from STOCK_REPORT.xlsx snapshot
A96: MV-0094 | B96: 2026-05-16 | C96: ='Item Catalog'!$B$17 -> ITM-015 · FAUCET SEAL FOR SLIM GENERIC | D96: Out | E96: 5 | F96: SARALEX | G96: Historical Import | H96: Wholesale/retail dispatch (pre-migration cumulative) | I96: Historical cumulative total migrated from STOCK_REPORT.xlsx snapshot
A97: MV-0095 | B97: 2026-05-16 | C97: ='Item Catalog'!$B$17 -> ITM-015 · FAUCET SEAL FOR SLIM GENERIC | D97: Out | E97: 25 | F97: CRYSTAL REF. STATION | G97: Historical Import | H97: Wholesale/retail dispatch (pre-migration cumulative) | I97: Historical cumulative total migrated from STOCK_REPORT.xlsx snapshot
A98: MV-0096 | B98: 2026-05-16 | C98: ='Item Catalog'!$B$17 -> ITM-015 · FAUCET SEAL FOR SLIM GENERIC | D98: Out | E98: 19 | F98: WATER MARKET (BAAO) | G98: Historical Import | H98: Wholesale/retail dispatch (pre-migration cumulative) | I98: Historical cumulative total migrated from STOCK_REPORT.xlsx snapshot
A99: MV-0097 | B99: 2026-05-16 | C99: ='Item Catalog'!$B$17 -> ITM-015 · FAUCET SEAL FOR SLIM GENERIC | D99: Out | E99: 3 | F99: AQUARES | G99: Historical Import | H99: Wholesale/retail dispatch (pre-migration cumulative) | I99: Historical cumulative total migrated from STOCK_REPORT.xlsx snapshot
A100: MV-0098 | B100: 2026-05-16 | C100: ='Item Catalog'!$B$17 -> ITM-015 · FAUCET SEAL FOR SLIM GENERIC | D100: Out | E100: 2 | F100: LANON W.R.S. | G100: Historical Import | H100: Wholesale/retail dispatch (pre-migration cumulative) | I100: Historical cumulative total migrated from STOCK_REPORT.xlsx snapshot
...

Sheet Buyer Summary
A1: BUYER SUMMARY (auto-computed pivot - do not type into buyer columns)
A2: Item Label | B2: Item Name | C2: A&G (LW-BAAO) | D2: ALKAVIVA (BAAO) | E2: OTHERS (CUSTOMER) | F2: CRISPY KING | G2: CITY WATER (LW-TAPAYAS) | H2: PURE DROP | I2: LW (SORSOGON) | J2: LW (BATO) | K2: SARALEX | L2: CRYSTAL REF. STATION | M2: WATER MARKET (BAAO) | N2: AQUARES | O2: LANON W.R.S. | P2: W.L.D. REF. STN (BATO) | Q2: ALKAVIVA (BARAS) | R2: SHAUNTI REF. STN. | S2: Row Total | T2: Check vs Qty Stock Out
A3: ='Item Catalog'!$B$3 -> ITM-001 · 5 GAL SLIM CONTAINER W/ CAP BLUE | B3: ='Item Catalog'!$C$3 -> 5 GAL SLIM CONTAINER W/ CAP BLUE | C3: =SUMIFS('Stock Movements'!$E:$E,'Stock Movements'!$C:$C,$A3,'Stock Movements'!$F:$F,C$2,'Stock Movements'!$D:$D,"Out") -> 87 | D3: =SUMIFS('Stock Movements'!$E:$E,'Stock Movements'!$C:$C,$A3,'Stock Movements'!$F:$F,D$2,'Stock Movements'!$D:$D,"Out") -> 55 | E3: =SUMIFS('Stock Movements'!$E:$E,'Stock Movements'!$C:$C,$A3,'Stock Movements'!$F:$F,E$2,'Stock Movements'!$D:$D,"Out") -> 0 | F3: =SUMIFS('Stock Movements'!$E:$E,'Stock Movements'!$C:$C,$A3,'Stock Movements'!$F:$F,F$2,'Stock Movements'!$D:$D,"Out") -> 0 | G3: =SUMIFS('Stock Movements'!$E:$E,'Stock Movements'!$C:$C,$A3,'Stock Movements'!$F:$F,G$2,'Stock Movements'!$D:$D,"Out") -> 100 | H3: =SUMIFS('Stock Movements'!$E:$E,'Stock Movements'!$C:$C,$A3,'Stock Movements'!$F:$F,H$2,'Stock Movements'!$D:$D,"Out") -> 60 | I3: =SUMIFS('Stock Movements'!$E:$E,'Stock Movements'!$C:$C,$A3,'Stock Movements'!$F:$F,I$2,'Stock Movements'!$D:$D,"Out") -> 0 | J3: =SUMIFS('Stock Movements'!$E:$E,'Stock Movements'!$C:$C,$A3,'Stock Movements'!$F:$F,J$2,'Stock Movements'!$D:$D,"Out") -> 19 | ... R3: =SUMIFS('Stock Movements'!$E:$E,'Stock Movements'!$C:$C,$A3,'Stock Movements'!$F:$F,R$2,'Stock Movements'!$D:$D,"Out") -> 0 | S3: =SUM(C3:R3) -> 526 | T3: =S3-'Item Catalog'!$M$3 -> 0
A4: ='Item Catalog'!$B$4 -> ITM-002 · 5 GAL SLIM CONTAINER W/ CAP BLUE-WOW | B4: ='Item Catalog'!$C$4 -> 5 GAL SLIM CONTAINER W/ CAP BLUE-WOW | C4: =SUMIFS('Stock Movements'!$E:$E,'Stock Movements'!$C:$C,$A4,'Stock Movements'!$F:$F,C$2,'Stock Movements'!$D:$D,"Out") -> 18 | D4: =SUMIFS('Stock Movements'!$E:$E,'Stock Movements'!$C:$C,$A4,'Stock Movements'!$F:$F,D$2,'Stock Movements'!$D:$D,"Out") -> 5 | E4: =SUMIFS('Stock Movements'!$E:$E,'Stock Movements'!$C:$C,$A4,'Stock Movements'!$F:$F,E$2,'Stock Movements'!$D:$D,"Out") -> 0 | F4: =SUMIFS('Stock Movements'!$E:$E,'Stock Movements'!$C:$C,$A4,'Stock Movements'!$F:$F,F$2,'Stock Movements'!$D:$D,"Out") -> 0 | G4: =SUMIFS('Stock Movements'!$E:$E,'Stock Movements'!$C:$C,$A4,'Stock Movements'!$F:$F,G$2,'Stock Movements'!$D:$D,"Out") -> 0 | H4: =SUMIFS('Stock Movements'!$E:$E,'Stock Movements'!$C:$C,$A4,'Stock Movements'!$F:$F,H$2,'Stock Movements'!$D:$D,"Out") -> 10 | I4: =SUMIFS('Stock Movements'!$E:$E,'Stock Movements'!$C:$C,$A4,'Stock Movements'!$F:$F,I$2,'Stock Movements'!$D:$D,"Out") -> 0 | J4: =SUMIFS('Stock Movements'!$E:$E,'Stock Movements'!$C:$C,$A4,'Stock Movements'!$F:$F,J$2,'Stock Movements'!$D:$D,"Out") -> 0 | ... R4: =SUMIFS('Stock Movements'!$E:$E,'Stock Movements'!$C:$C,$A4,'Stock Movements'!$F:$F,R$2,'Stock Movements'!$D:$D,"Out") -> 0 | S4: =SUM(C4:R4) -> 53 | T4: =S4-'Item Catalog'!$M$4 -> 0
A5: ='Item Catalog'!$B$5 -> ITM-003 · 5 GAL SLIM CONTAINER W/ CAP GREEN | B5: ='Item Catalog'!$C$5 -> 5 GAL SLIM CONTAINER W/ CAP GREEN | C5: =SUMIFS('Stock Movements'!$E:$E,'Stock Movements'!$C:$C,$A5,'Stock Movements'!$F:$F,C$2,'Stock Movements'!$D:$D,"Out") -> 81 | D5: =SUMIFS('Stock Movements'!$E:$E,'Stock Movements'!$C:$C,$A5,'Stock Movements'!$F:$F,D$2,'Stock Movements'!$D:$D,"Out") -> 0 | E5: =SUMIFS('Stock Movements'!$E:$E,'Stock Movements'!$C:$C,$A5,'Stock Movements'!$F:$F,E$2,'Stock Movements'!$D:$D,"Out") -> 0 | F5: =SUMIFS('Stock Movements'!$E:$E,'Stock Movements'!$C:$C,$A5,'Stock Movements'!$F:$F,F$2,'Stock Movements'!$D:$D,"Out") -> 0 | G5: =SUMIFS('Stock Movements'!$E:$E,'Stock Movements'!$C:$C,$A5,'Stock Movements'!$F:$F,G$2,'Stock Movements'!$D:$D,"Out") -> 0 | H5: =SUMIFS('Stock Movements'!$E:$E,'Stock Movements'!$C:$C,$A5,'Stock Movements'!$F:$F,H$2,'Stock Movements'!$D:$D,"Out") -> 0 | I5: =SUMIFS('Stock Movements'!$E:$E,'Stock Movements'!$C:$C,$A5,'Stock Movements'!$F:$F,I$2,'Stock Movements'!$D:$D,"Out") -> 0 | J5: =SUMIFS('Stock Movements'!$E:$E,'Stock Movements'!$C:$C,$A5,'Stock Movements'!$F:$F,J$2,'Stock Movements'!$D:$D,"Out") -> 0 | ... R5: =SUMIFS('Stock Movements'!$E:$E,'Stock Movements'!$C:$C,$A5,'Stock Movements'!$F:$F,R$2,'Stock Movements'!$D:$D,"Out") -> 0 | S5: =SUM(C5:R5) -> 220 | T5: =S5-'Item Catalog'!$M$5 -> 0
A6: ='Item Catalog'!$B$6 -> ITM-004 · 5 GAL SLIM CONTAINER W/ CAP YELLOW | B6: ='Item Catalog'!$C$6 -> 5 GAL SLIM CONTAINER W/ CAP YELLOW | C6: =SUMIFS('Stock Movements'!$E:$E,'Stock Movements'!$C:$C,$A6,'Stock Movements'!$F:$F,C$2,'Stock Movements'!$D:$D,"Out") -> 38 | D6: =SUMIFS('Stock Movements'!$E:$E,'Stock Movements'!$C:$C,$A6,'Stock Movements'!$F:$F,D$2,'Stock Movements'!$D:$D,"Out") -> 0 | E6: =SUMIFS('Stock Movements'!$E:$E,'Stock Movements'!$C:$C,$A6,'Stock Movements'!$F:$F,E$2,'Stock Movements'!$D:$D,"Out") -> 0 | F6: =SUMIFS('Stock Movements'!$E:$E,'Stock Movements'!$C:$C,$A6,'Stock Movements'!$F:$F,F$2,'Stock Movements'!$D:$D,"Out") -> 0 | G6: =SUMIFS('Stock Movements'!$E:$E,'Stock Movements'!$C:$C,$A6,'Stock Movements'!$F:$F,G$2,'Stock Movements'!$D:$D,"Out") -> 0 | H6: =SUMIFS('Stock Movements'!$E:$E,'Stock Movements'!$C:$C,$A6,'Stock Movements'!$F:$F,H$2,'Stock Movements'!$D:$D,"Out") -> 0 | I6: =SUMIFS('Stock Movements'!$E:$E,'Stock Movements'!$C:$C,$A6,'Stock Movements'!$F:$F,I$2,'Stock Movements'!$D:$D,"Out") -> 0 | J6: =SUMIFS('Stock Movements'!$E:$E,'Stock Movements'!$C:$C,$A6,'Stock Movements'!$F:$F,J$2,'Stock Movements'!$D:$D,"Out") -> 0 | ... R6: =SUMIFS('Stock Movements'!$E:$E,'Stock Movements'!$C:$C,$A6,'Stock Movements'!$F:$F,R$2,'Stock Movements'!$D:$D,"Out") -> 0 | S6: =SUM(C6:R6) -> 58 | T6: =S6-'Item Catalog'!$M$6 -> 0
A7: ='Item Catalog'!$B$7 -> ITM-005 · 5 GAL (PET) ROUND CONTAINER BLUE W/ CAP (CLASS A) | B7: ='Item Catalog'!$C$7 -> 5 GAL (PET) ROUND CONTAINER BLUE W/ CAP (CLASS A) | C7: =SUMIFS('Stock Movements'!$E:$E,'Stock Movements'!$C:$C,$A7,'Stock Movements'!$F:$F,C$2,'Stock Movements'!$D:$D,"Out") -> 35 | D7: =SUMIFS('Stock Movements'!$E:$E,'Stock Movements'!$C:$C,$A7,'Stock Movements'!$F:$F,D$2,'Stock Movements'!$D:$D,"Out") -> 5 | E7: =SUMIFS('Stock Movements'!$E:$E,'Stock Movements'!$C:$C,$A7,'Stock Movements'!$F:$F,E$2,'Stock Movements'!$D:$D,"Out") -> 0 | F7: =SUMIFS('Stock Movements'!$E:$E,'Stock Movements'!$C:$C,$A7,'Stock Movements'!$F:$F,F$2,'Stock Movements'!$D:$D,"Out") -> 0 | G7: =SUMIFS('Stock Movements'!$E:$E,'Stock Movements'!$C:$C,$A7,'Stock Movements'!$F:$F,G$2,'Stock Movements'!$D:$D,"Out") -> 15 | H7: =SUMIFS('Stock Movements'!$E:$E,'Stock Movements'!$C:$C,$A7,'Stock Movements'!$F:$F,H$2,'Stock Movements'!$D:$D,"Out") -> 60 | I7: =SUMIFS('Stock Movements'!$E:$E,'Stock Movements'!$C:$C,$A7,'Stock Movements'!$F:$F,I$2,'Stock Movements'!$D:$D,"Out") -> 0 | J7: =SUMIFS('Stock Movements'!$E:$E,'Stock Movements'!$C:$C,$A7,'Stock Movements'!$F:$F,J$2,'Stock Movements'!$D:$D,"Out") -> 9 | ... R7: =SUMIFS('Stock Movements'!$E:$E,'Stock Movements'!$C:$C,$A7,'Stock Movements'!$F:$F,R$2,'Stock Movements'!$D:$D,"Out") -> 0 | S7: =SUM(C7:R7) -> 199 | T7: =S7-'Item Catalog'!$M$7 -> 0
A8: ='Item Catalog'!$B$8 -> ITM-006 · 5 GAL (PET) ROUND CONTAINER BLUE W/ CAP (CLASS A) | B8: ='Item Catalog'!$C$8 -> 5 GAL (PET) ROUND CONTAINER BLUE W/ CAP (CLASS A) | C8: =SUMIFS('Stock Movements'!$E:$E,'Stock Movements'!$C:$C,$A8,'Stock Movements'!$F:$F,C$2,'Stock Movements'!$D:$D,"Out") -> 5 | D8: =SUMIFS('Stock Movements'!$E:$E,'Stock Movements'!$C:$C,$A8,'Stock Movements'!$F:$F,D$2,'Stock Movements'!$D:$D,"Out") -> 0 | E8: =SUMIFS('Stock Movements'!$E:$E,'Stock Movements'!$C:$C,$A8,'Stock Movements'!$F:$F,E$2,'Stock Movements'!$D:$D,"Out") -> 0 | F8: =SUMIFS('Stock Movements'!$E:$E,'Stock Movements'!$C:$C,$A8,'Stock Movements'!$F:$F,F$2,'Stock Movements'!$D:$D,"Out") -> 0 | G8: =SUMIFS('Stock Movements'!$E:$E,'Stock Movements'!$C:$C,$A8,'Stock Movements'!$F:$F,G$2,'Stock Movements'!$D:$D,"Out") -> 0 | H8: =SUMIFS('Stock Movements'!$E:$E,'Stock Movements'!$C:$C,$A8,'Stock Movements'!$F:$F,H$2,'Stock Movements'!$D:$D,"Out") -> 0 | I8: =SUMIFS('Stock Movements'!$E:$E,'Stock Movements'!$C:$C,$A8,'Stock Movements'!$F:$F,I$2,'Stock Movements'!$D:$D,"Out") -> 0 | J8: =SUMIFS('Stock Movements'!$E:$E,'Stock Movements'!$C:$C,$A8,'Stock Movements'!$F:$F,J$2,'Stock Movements'!$D:$D,"Out") -> 0 | ... R8: =SUMIFS('Stock Movements'!$E:$E,'Stock Movements'!$C:$C,$A8,'Stock Movements'!$F:$F,R$2,'Stock Movements'!$D:$D,"Out") -> 0 | S8: =SUM(C8:R8) -> 11 | T8: =S8-'Item Catalog'!$M$8 -> 0
A9: ='Item Catalog'!$B$9 -> ITM-007 · BIG CAP SEAL FOR SLIM LW | B9: ='Item Catalog'!$C$9 -> BIG CAP SEAL FOR SLIM LW | C9: =SUMIFS('Stock Movements'!$E:$E,'Stock Movements'!$C:$C,$A9,'Stock Movements'!$F:$F,C$2,'Stock Movements'!$D:$D,"Out") -> 49 | D9: =SUMIFS('Stock Movements'!$E:$E,'Stock Movements'!$C:$C,$A9,'Stock Movements'!$F:$F,D$2,'Stock Movements'!$D:$D,"Out") -> 0 | E9: =SUMIFS('Stock Movements'!$E:$E,'Stock Movements'!$C:$C,$A9,'Stock Movements'!$F:$F,E$2,'Stock Movements'!$D:$D,"Out") -> 0 | F9: =SUMIFS('Stock Movements'!$E:$E,'Stock Movements'!$C:$C,$A9,'Stock Movements'!$F:$F,F$2,'Stock Movements'!$D:$D,"Out") -> 0 | G9: =SUMIFS('Stock Movements'!$E:$E,'Stock Movements'!$C:$C,$A9,'Stock Movements'!$F:$F,G$2,'Stock Movements'!$D:$D,"Out") -> 3 | H9: =SUMIFS('Stock Movements'!$E:$E,'Stock Movements'!$C:$C,$A9,'Stock Movements'!$F:$F,H$2,'Stock Movements'!$D:$D,"Out") -> 0 | I9: =SUMIFS('Stock Movements'!$E:$E,'Stock Movements'!$C:$C,$A9,'Stock Movements'!$F:$F,I$2,'Stock Movements'!$D:$D,"Out") -> 0 | J9: =SUMIFS('Stock Movements'!$E:$E,'Stock Movements'!$C:$C,$A9,'Stock Movements'!$F:$F,J$2,'Stock Movements'!$D:$D,"Out") -> 3 | ... R9: =SUMIFS('Stock Movements'!$E:$E,'Stock Movements'!$C:$C,$A9,'Stock Movements'!$F:$F,R$2,'Stock Movements'!$D:$D,"Out") -> 0 | S9: =SUM(C9:R9) -> 55 | T9: =S9-'Item Catalog'!$M$9 -> 0
A10: ='Item Catalog'!$B$10 -> ITM-008 · SMALL CAP SEAL FOR SLIM LW | B10: ='Item Catalog'!$C$10 -> SMALL CAP SEAL FOR SLIM LW | C10: =SUMIFS('Stock Movements'!$E:$E,'Stock Movements'!$C:$C,$A10,'Stock Movements'!$F:$F,C$2,'Stock Movements'!$D:$D,"Out") -> 19 | D10: =SUMIFS('Stock Movements'!$E:$E,'Stock Movements'!$C:$C,$A10,'Stock Movements'!$F:$F,D$2,'Stock Movements'!$D:$D,"Out") -> 0 | E10: =SUMIFS('Stock Movements'!$E:$E,'Stock Movements'!$C:$C,$A10,'Stock Movements'!$F:$F,E$2,'Stock Movements'!$D:$D,"Out") -> 0 | F10: =SUMIFS('Stock Movements'!$E:$E,'Stock Movements'!$C:$C,$A10,'Stock Movements'!$F:$F,F$2,'Stock Movements'!$D:$D,"Out") -> 0 | G10: =SUMIFS('Stock Movements'!$E:$E,'Stock Movements'!$C:$C,$A10,'Stock Movements'!$F:$F,G$2,'Stock Movements'!$D:$D,"Out") -> 1 | H10: =SUMIFS('Stock Movements'!$E:$E,'Stock Movements'!$C:$C,$A10,'Stock Movements'!$F:$F,H$2,'Stock Movements'!$D:$D,"Out") -> 0 | I10: =SUMIFS('Stock Movements'!$E:$E,'Stock Movements'!$C:$C,$A10,'Stock Movements'!$F:$F,I$2,'Stock Movements'!$D:$D,"Out") -> 0 | J10: =SUMIFS('Stock Movements'!$E:$E,'Stock Movements'!$C:$C,$A10,'Stock Movements'!$F:$F,J$2,'Stock Movements'!$D:$D,"Out") -> 4 | ... R10: =SUMIFS('Stock Movements'!$E:$E,'Stock Movements'!$C:$C,$A10,'Stock Movements'!$F:$F,R$2,'Stock Movements'!$D:$D,"Out") -> 0 | S10: =SUM(C10:R10) -> 24 | T10: =S10-'Item Catalog'!$M$10 -> 0
A11: ='Item Catalog'!$B$11 -> ITM-009 · FAUCET SEAL FOR SLIM LW | B11: ='Item Catalog'!$C$11 -> FAUCET SEAL FOR SLIM LW | C11: =SUMIFS('Stock Movements'!$E:$E,'Stock Movements'!$C:$C,$A11,'Stock Movements'!$F:$F,C$2,'Stock Movements'!$D:$D,"Out") -> 28 | D11: =SUMIFS('Stock Movements'!$E:$E,'Stock Movements'!$C:$C,$A11,'Stock Movements'!$F:$F,D$2,'Stock Movements'!$D:$D,"Out") -> 0 | E11: =SUMIFS('Stock Movements'!$E:$E,'Stock Movements'!$C:$C,$A11,'Stock Movements'!$F:$F,E$2,'Stock Movements'!$D:$D,"Out") -> 0 | F11: =SUMIFS('Stock Movements'!$E:$E,'Stock Movements'!$C:$C,$A11,'Stock Movements'!$F:$F,F$2,'Stock Movements'!$D:$D,"Out") -> 0 | G11: =SUMIFS('Stock Movements'!$E:$E,'Stock Movements'!$C:$C,$A11,'Stock Movements'!$F:$F,G$2,'Stock Movements'!$D:$D,"Out") -> 5 | H11: =SUMIFS('Stock Movements'!$E:$E,'Stock Movements'!$C:$C,$A11,'Stock Movements'!$F:$F,H$2,'Stock Movements'!$D:$D,"Out") -> 0 | I11: =SUMIFS('Stock Movements'!$E:$E,'Stock Movements'!$C:$C,$A11,'Stock Movements'!$F:$F,I$2,'Stock Movements'!$D:$D,"Out") -> 20 | J11: =SUMIFS('Stock Movements'!$E:$E,'Stock Movements'!$C:$C,$A11,'Stock Movements'!$F:$F,J$2,'Stock Movements'!$D:$D,"Out") -> 7 | ... R11: =SUMIFS('Stock Movements'!$E:$E,'Stock Movements'!$C:$C,$A11,'Stock Movements'!$F:$F,R$2,'Stock Movements'!$D:$D,"Out") -> 0 | S11: =SUM(C11:R11) -> 62 | T11: =S11-'Item Catalog'!$M$11 -> 0
A12: ='Item Catalog'!$B$12 -> ITM-010 · FAUCET SEAL FOR SLIM LW (CLASS B) | B12: ='Item Catalog'!$C$12 -> FAUCET SEAL FOR SLIM LW (CLASS B) | C12: =SUMIFS('Stock Movements'!$E:$E,'Stock Movements'!$C:$C,$A12,'Stock Movements'!$F:$F,C$2,'Stock Movements'!$D:$D,"Out") -> 0 | D12: =SUMIFS('Stock Movements'!$E:$E,'Stock Movements'!$C:$C,$A12,'Stock Movements'!$F:$F,D$2,'Stock Movements'!$D:$D,"Out") -> 0 | E12: =SUMIFS('Stock Movements'!$E:$E,'Stock Movements'!$C:$C,$A12,'Stock Movements'!$F:$F,E$2,'Stock Movements'!$D:$D,"Out") -> 0 | F12: =SUMIFS('Stock Movements'!$E:$E,'Stock Movements'!$C:$C,$A12,'Stock Movements'!$F:$F,F$2,'Stock Movements'!$D:$D,"Out") -> 0 | G12: =SUMIFS('Stock Movements'!$E:$E,'Stock Movements'!$C:$C,$A12,'Stock Movements'!$F:$F,G$2,'Stock Movements'!$D:$D,"Out") -> 0 | H12: =SUMIFS('Stock Movements'!$E:$E,'Stock Movements'!$C:$C,$A12,'Stock Movements'!$F:$F,H$2,'Stock Movements'!$D:$D,"Out") -> 0 | I12: =SUMIFS('Stock Movements'!$E:$E,'Stock Movements'!$C:$C,$A12,'Stock Movements'!$F:$F,I$2,'Stock Movements'!$D:$D,"Out") -> 0 | J12: =SUMIFS('Stock Movements'!$E:$E,'Stock Movements'!$C:$C,$A12,'Stock Movements'!$F:$F,J$2,'Stock Movements'!$D:$D,"Out") -> 0 | ... R12: =SUMIFS('Stock Movements'!$E:$E,'Stock Movements'!$C:$C,$A12,'Stock Movements'!$F:$F,R$2,'Stock Movements'!$D:$D,"Out") -> 0 | S12: =SUM(C12:R12) -> 0 | T12: =S12-'Item Catalog'!$M$12 -> 0
A13: ='Item Catalog'!$B$13 -> ITM-011 · UMBRELLA SEAL FOR ROUND LW | B13: ='Item Catalog'!$C$13 -> UMBRELLA SEAL FOR ROUND LW | C13: =SUMIFS('Stock Movements'!$E:$E,'Stock Movements'!$C:$C,$A13,'Stock Movements'!$F:$F,C$2,'Stock Movements'!$D:$D,"Out") -> 8 | D13: =SUMIFS('Stock Movements'!$E:$E,'Stock Movements'!$C:$C,$A13,'Stock Movements'!$F:$F,D$2,'Stock Movements'!$D:$D,"Out") -> 0 | E13: =SUMIFS('Stock Movements'!$E:$E,'Stock Movements'!$C:$C,$A13,'Stock Movements'!$F:$F,E$2,'Stock Movements'!$D:$D,"Out") -> 0 | F13: =SUMIFS('Stock Movements'!$E:$E,'Stock Movements'!$C:$C,$A13,'Stock Movements'!$F:$F,F$2,'Stock Movements'!$D:$D,"Out") -> 0 | G13: =SUMIFS('Stock Movements'!$E:$E,'Stock Movements'!$C:$C,$A13,'Stock Movements'!$F:$F,G$2,'Stock Movements'!$D:$D,"Out") -> 2 | H13: =SUMIFS('Stock Movements'!$E:$E,'Stock Movements'!$C:$C,$A13,'Stock Movements'!$F:$F,H$2,'Stock Movements'!$D:$D,"Out") -> 0 | I13: =SUMIFS('Stock Movements'!$E:$E,'Stock Movements'!$C:$C,$A13,'Stock Movements'!$F:$F,I$2,'Stock Movements'!$D:$D,"Out") -> 20 | J13: =SUMIFS('Stock Movements'!$E:$E,'Stock Movements'!$C:$C,$A13,'Stock Movements'!$F:$F,J$2,'Stock Movements'!$D:$D,"Out") -> 2 | ... R13: =SUMIFS('Stock Movements'!$E:$E,'Stock Movements'!$C:$C,$A13,'Stock Movements'!$F:$F,R$2,'Stock Movements'!$D:$D,"Out") -> 0 | S13: =SUM(C13:R13) -> 33 | T13: =S13-'Item Catalog'!$M$13 -> 0
A14: ='Item Catalog'!$B$14 -> ITM-012 · UMBRELLA SEAL FOR ROUND LW (CLASS B) | B14: ='Item Catalog'!$C$14 -> UMBRELLA SEAL FOR ROUND LW (CLASS B) | C14: =SUMIFS('Stock Movements'!$E:$E,'Stock Movements'!$C:$C,$A14,'Stock Movements'!$F:$F,C$2,'Stock Movements'!$D:$D,"Out") -> 0 | D14: =SUMIFS('Stock Movements'!$E:$E,'Stock Movements'!$C:$C,$A14,'Stock Movements'!$F:$F,D$2,'Stock Movements'!$D:$D,"Out") -> 0 | E14: =SUMIFS('Stock Movements'!$E:$E,'Stock Movements'!$C:$C,$A14,'Stock Movements'!$F:$F,E$2,'Stock Movements'!$D:$D,"Out") -> 0 | F14: =SUMIFS('Stock Movements'!$E:$E,'Stock Movements'!$C:$C,$A14,'Stock Movements'!$F:$F,F$2,'Stock Movements'!$D:$D,"Out") -> 0 | G14: =SUMIFS('Stock Movements'!$E:$E,'Stock Movements'!$C:$C,$A14,'Stock Movements'!$F:$F,G$2,'Stock Movements'!$D:$D,"Out") -> 0 | H14: =SUMIFS('Stock Movements'!$E:$E,'Stock Movements'!$C:$C,$A14,'Stock Movements'!$F:$F,H$2,'Stock Movements'!$D:$D,"Out") -> 0 | I14: =SUMIFS('Stock Movements'!$E:$E,'Stock Movements'!$C:$C,$A14,'Stock Movements'!$F:$F,I$2,'Stock Movements'!$D:$D,"Out") -> 0 | J14: =SUMIFS('Stock Movements'!$E:$E,'Stock Movements'!$C:$C,$A14,'Stock Movements'!$F:$F,J$2,'Stock Movements'!$D:$D,"Out") -> 0 | ... R14: =SUMIFS('Stock Movements'!$E:$E,'Stock Movements'!$C:$C,$A14,'Stock Movements'!$F:$F,R$2,'Stock Movements'!$D:$D,"Out") -> 0 | S14: =SUM(C14:R14) -> 0 | T14: =S14-'Item Catalog'!$M$14 -> 0
A15: ='Item Catalog'!$B$15 -> ITM-013 · BIG CAP SEAL FOR SLIM GENERIC | B15: ='Item Catalog'!$C$15 -> BIG CAP SEAL FOR SLIM GENERIC | C15: =SUMIFS('Stock Movements'!$E:$E,'Stock Movements'!$C:$C,$A15,'Stock Movements'!$F:$F,C$2,'Stock Movements'!$D:$D,"Out") -> 0 | D15: =SUMIFS('Stock Movements'!$E:$E,'Stock Movements'!$C:$C,$A15,'Stock Movements'!$F:$F,D$2,'Stock Movements'!$D:$D,"Out") -> 5 | E15: =SUMIFS('Stock Movements'!$E:$E,'Stock Movements'!$C:$C,$A15,'Stock Movements'!$F:$F,E$2,'Stock Movements'!$D:$D,"Out") -> 0 | F15: =SUMIFS('Stock Movements'!$E:$E,'Stock Movements'!$C:$C,$A15,'Stock Movements'!$F:$F,F$2,'Stock Movements'!$D:$D,"Out") -> 0 | G15: =SUMIFS('Stock Movements'!$E:$E,'Stock Movements'!$C:$C,$A15,'Stock Movements'!$F:$F,G$2,'Stock Movements'!$D:$D,"Out") -> 11 | H15: =SUMIFS('Stock Movements'!$E:$E,'Stock Movements'!$C:$C,$A15,'Stock Movements'!$F:$F,H$2,'Stock Movements'!$D:$D,"Out") -> 3 | I15: =SUMIFS('Stock Movements'!$E:$E,'Stock Movements'!$C:$C,$A15,'Stock Movements'!$F:$F,I$2,'Stock Movements'!$D:$D,"Out") -> 0 | J15: =SUMIFS('Stock Movements'!$E:$E,'Stock Movements'!$C:$C,$A15,'Stock Movements'!$F:$F,J$2,'Stock Movements'!$D:$D,"Out") -> 5 | ... R15: =SUMIFS('Stock Movements'!$E:$E,'Stock Movements'!$C:$C,$A15,'Stock Movements'!$F:$F,R$2,'Stock Movements'!$D:$D,"Out") -> 5 | S15: =SUM(C15:R15) -> 100 | T15: =S15-'Item Catalog'!$M$15 -> 0
A16: ='Item Catalog'!$B$16 -> ITM-014 · SMALL CAP SEAL FOR SLIM GENERIC | B16: ='Item Catalog'!$C$16 -> SMALL CAP SEAL FOR SLIM GENERIC | C16: =SUMIFS('Stock Movements'!$E:$E,'Stock Movements'!$C:$C,$A16,'Stock Movements'!$F:$F,C$2,'Stock Movements'!$D:$D,"Out") -> 1 | D16: =SUMIFS('Stock Movements'!$E:$E,'Stock Movements'!$C:$C,$A16,'Stock Movements'!$F:$F,D$2,'Stock Movements'!$D:$D,"Out") -> 1 | E16: =SUMIFS('Stock Movements'!$E:$E,'Stock Movements'!$C:$C,$A16,'Stock Movements'!$F:$F,E$2,'Stock Movements'!$D:$D,"Out") -> 0 | F16: =SUMIFS('Stock Movements'!$E:$E,'Stock Movements'!$C:$C,$A16,'Stock Movements'!$F:$F,F$2,'Stock Movements'!$D:$D,"Out") -> 0 | G16: =SUMIFS('Stock Movements'!$E:$E,'Stock Movements'!$C:$C,$A16,'Stock Movements'!$F:$F,G$2,'Stock Movements'!$D:$D,"Out") -> 4 | H16: =SUMIFS('Stock Movements'!$E:$E,'Stock Movements'!$C:$C,$A16,'Stock Movements'!$F:$F,H$2,'Stock Movements'!$D:$D,"Out") -> 1 | I16: =SUMIFS('Stock Movements'!$E:$E,'Stock Movements'!$C:$C,$A16,'Stock Movements'!$F:$F,I$2,'Stock Movements'!$D:$D,"Out") -> 0 | J16: =SUMIFS('Stock Movements'!$E:$E,'Stock Movements'!$C:$C,$A16,'Stock Movements'!$F:$F,J$2,'Stock Movements'!$D:$D,"Out") -> 0 | ... R16: =SUMIFS('Stock Movements'!$E:$E,'Stock Movements'!$C:$C,$A16,'Stock Movements'!$F:$F,R$2,'Stock Movements'!$D:$D,"Out") -> 0 | S16: =SUM(C16:R16) -> 36 | T16: =S16-'Item Catalog'!$M$16 -> 0
A17: ='Item Catalog'!$B$17 -> ITM-015 · FAUCET SEAL FOR SLIM GENERIC | B17: ='Item Catalog'!$C$17 -> FAUCET SEAL FOR SLIM GENERIC | C17: =SUMIFS('Stock Movements'!$E:$E,'Stock Movements'!$C:$C,$A17,'Stock Movements'!$F:$F,C$2,'Stock Movements'!$D:$D,"Out") -> 2 | D17: =SUMIFS('Stock Movements'!$E:$E,'Stock Movements'!$C:$C,$A17,'Stock Movements'!$F:$F,D$2,'Stock Movements'!$D:$D,"Out") -> 1 | E17: =SUMIFS('Stock Movements'!$E:$E,'Stock Movements'!$C:$C,$A17,'Stock Movements'!$F:$F,E$2,'Stock Movements'!$D:$D,"Out") -> 0 | F17: =SUMIFS('Stock Movements'!$E:$E,'Stock Movements'!$C:$C,$A17,'Stock Movements'!$F:$F,F$2,'Stock Movements'!$D:$D,"Out") -> 0 | G17: =SUMIFS('Stock Movements'!$E:$E,'Stock Movements'!$C:$C,$A17,'Stock Movements'!$F:$F,G$2,'Stock Movements'!$D:$D,"Out") -> 28 | H17: =SUMIFS('Stock Movements'!$E:$E,'Stock Movements'!$C:$C,$A17,'Stock Movements'!$F:$F,H$2,'Stock Movements'!$D:$D,"Out") -> 2 | I17: =SUMIFS('Stock Movements'!$E:$E,'Stock Movements'!$C:$C,$A17,'Stock Movements'!$F:$F,I$2,'Stock Movements'!$D:$D,"Out") -> 0 | J17: =SUMIFS('Stock Movements'!$E:$E,'Stock Movements'!$C:$C,$A17,'Stock Movements'!$F:$F,J$2,'Stock Movements'!$D:$D,"Out") -> 0 | ... R17: =SUMIFS('Stock Movements'!$E:$E,'Stock Movements'!$C:$C,$A17,'Stock Movements'!$F:$F,R$2,'Stock Movements'!$D:$D,"Out") -> 5 | S17: =SUM(C17:R17) -> 100 | T17: =S17-'Item Catalog'!$M$17 -> 0
A18: ='Item Catalog'!$B$18 -> ITM-016 · FAUCET SEAL FOR SLIM GENERIC | B18: ='Item Catalog'!$C$18 -> FAUCET SEAL FOR SLIM GENERIC | C18: =SUMIFS('Stock Movements'!$E:$E,'Stock Movements'!$C:$C,$A18,'Stock Movements'!$F:$F,C$2,'Stock Movements'!$D:$D,"Out") -> 0 | D18: =SUMIFS('Stock Movements'!$E:$E,'Stock Movements'!$C:$C,$A18,'Stock Movements'!$F:$F,D$2,'Stock Movements'!$D:$D,"Out") -> 0 | E18: =SUMIFS('Stock Movements'!$E:$E,'Stock Movements'!$C:$C,$A18,'Stock Movements'!$F:$F,E$2,'Stock Movements'!$D:$D,"Out") -> 0 | F18: =SUMIFS('Stock Movements'!$E:$E,'Stock Movements'!$C:$C,$A18,'Stock Movements'!$F:$F,F$2,'Stock Movements'!$D:$D,"Out") -> 0 | G18: =SUMIFS('Stock Movements'!$E:$E,'Stock Movements'!$C:$C,$A18,'Stock Movements'!$F:$F,G$2,'Stock Movements'!$D:$D,"Out") -> 0 | H18: =SUMIFS('Stock Movements'!$E:$E,'Stock Movements'!$C:$C,$A18,'Stock Movements'!$F:$F,H$2,'Stock Movements'!$D:$D,"Out") -> 0 | I18: =SUMIFS('Stock Movements'!$E:$E,'Stock Movements'!$C:$C,$A18,'Stock Movements'!$F:$F,I$2,'Stock Movements'!$D:$D,"Out") -> 0 | J18: =SUMIFS('Stock Movements'!$E:$E,'Stock Movements'!$C:$C,$A18,'Stock Movements'!$F:$F,J$2,'Stock Movements'!$D:$D,"Out") -> 0 | ... R18: =SUMIFS('Stock Movements'!$E:$E,'Stock Movements'!$C:$C,$A18,'Stock Movements'!$F:$F,R$2,'Stock Movements'!$D:$D,"Out") -> 0 | S18: =SUM(C18:R18) -> 11 | T18: =S18-'Item Catalog'!$M$18 -> 0
A19: ='Item Catalog'!$B$19 -> ITM-017 · UMBRELLA SEAL FOR ROUND GENERIC | B19: ='Item Catalog'!$C$19 -> UMBRELLA SEAL FOR ROUND GENERIC | C19: =SUMIFS('Stock Movements'!$E:$E,'Stock Movements'!$C:$C,$A19,'Stock Movements'!$F:$F,C$2,'Stock Movements'!$D:$D,"Out") -> 0 | D19: =SUMIFS('Stock Movements'!$E:$E,'Stock Movements'!$C:$C,$A19,'Stock Movements'!$F:$F,D$2,'Stock Movements'!$D:$D,"Out") -> 4 | E19: =SUMIFS('Stock Movements'!$E:$E,'Stock Movements'!$C:$C,$A19,'Stock Movements'!$F:$F,E$2,'Stock Movements'!$D:$D,"Out") -> 0 | F19: =SUMIFS('Stock Movements'!$E:$E,'Stock Movements'!$C:$C,$A19,'Stock Movements'!$F:$F,F$2,'Stock Movements'!$D:$D,"Out") -> 0 | G19: =SUMIFS('Stock Movements'!$E:$E,'Stock Movements'!$C:$C,$A19,'Stock Movements'!$F:$F,G$2,'Stock Movements'!$D:$D,"Out") -> 3 | H19: =SUMIFS('Stock Movements'!$E:$E,'Stock Movements'!$C:$C,$A19,'Stock Movements'!$F:$F,H$2,'Stock Movements'!$D:$D,"Out") -> 3 | I19: =SUMIFS('Stock Movements'!$E:$E,'Stock Movements'!$C:$C,$A19,'Stock Movements'!$F:$F,I$2,'Stock Movements'!$D:$D,"Out") -> 0 | J19: =SUMIFS('Stock Movements'!$E:$E,'Stock Movements'!$C:$C,$A19,'Stock Movements'!$F:$F,J$2,'Stock Movements'!$D:$D,"Out") -> 0 | ... R19: =SUMIFS('Stock Movements'!$E:$E,'Stock Movements'!$C:$C,$A19,'Stock Movements'!$F:$F,R$2,'Stock Movements'!$D:$D,"Out") -> 0 | S19: =SUM(C19:R19) -> 75 | T19: =S19-'Item Catalog'!$M$19 -> 0
A20: ='Item Catalog'!$B$20 -> ITM-018 · 1 L SOAP SANITIZER | B20: ='Item Catalog'!$C$20 -> 1 L SOAP SANITIZER | C20: =SUMIFS('Stock Movements'!$E:$E,'Stock Movements'!$C:$C,$A20,'Stock Movements'!$F:$F,C$2,'Stock Movements'!$D:$D,"Out") -> 21 | D20: =SUMIFS('Stock Movements'!$E:$E,'Stock Movements'!$C:$C,$A20,'Stock Movements'!$F:$F,D$2,'Stock Movements'!$D:$D,"Out") -> 0 | E20: =SUMIFS('Stock Movements'!$E:$E,'Stock Movements'!$C:$C,$A20,'Stock Movements'!$F:$F,E$2,'Stock Movements'!$D:$D,"Out") -> 0 | F20: =SUMIFS('Stock Movements'!$E:$E,'Stock Movements'!$C:$C,$A20,'Stock Movements'!$F:$F,F$2,'Stock Movements'!$D:$D,"Out") -> 0 | G20: =SUMIFS('Stock Movements'!$E:$E,'Stock Movements'!$C:$C,$A20,'Stock Movements'!$F:$F,G$2,'Stock Movements'!$D:$D,"Out") -> 0 | H20: =SUMIFS('Stock Movements'!$E:$E,'Stock Movements'!$C:$C,$A20,'Stock Movements'!$F:$F,H$2,'Stock Movements'!$D:$D,"Out") -> 0 | I20: =SUMIFS('Stock Movements'!$E:$E,'Stock Movements'!$C:$C,$A20,'Stock Movements'!$F:$F,I$2,'Stock Movements'!$D:$D,"Out") -> 0 | J20: =SUMIFS('Stock Movements'!$E:$E,'Stock Movements'!$C:$C,$A20,'Stock Movements'!$F:$F,J$2,'Stock Movements'!$D:$D,"Out") -> 3 | ... R20: =SUMIFS('Stock Movements'!$E:$E,'Stock Movements'!$C:$C,$A20,'Stock Movements'!$F:$F,R$2,'Stock Movements'!$D:$D,"Out") -> 6 | S20: =SUM(C20:R20) -> 35 | T20: =S20-'Item Catalog'!$M$20 -> 0
A21: ='Item Catalog'!$B$21 -> ITM-019 · SOAP SANITIZER: SOAP WOW-1LITER | B21: ='Item Catalog'!$C$21 -> SOAP SANITIZER: SOAP WOW-1LITER | C21: =SUMIFS('Stock Movements'!$E:$E,'Stock Movements'!$C:$C,$A21,'Stock Movements'!$F:$F,C$2,'Stock Movements'!$D:$D,"Out") -> 0 | D21: =SUMIFS('Stock Movements'!$E:$E,'Stock Movements'!$C:$C,$A21,'Stock Movements'!$F:$F,D$2,'Stock Movements'!$D:$D,"Out") -> 0 | E21: =SUMIFS('Stock Movements'!$E:$E,'Stock Movements'!$C:$C,$A21,'Stock Movements'!$F:$F,E$2,'Stock Movements'!$D:$D,"Out") -> 0 | F21: =SUMIFS('Stock Movements'!$E:$E,'Stock Movements'!$C:$C,$A21,'Stock Movements'!$F:$F,F$2,'Stock Movements'!$D:$D,"Out") -> 0 | G21: =SUMIFS('Stock Movements'!$E:$E,'Stock Movements'!$C:$C,$A21,'Stock Movements'!$F:$F,G$2,'Stock Movements'!$D:$D,"Out") -> 0 | H21: =SUMIFS('Stock Movements'!$E:$E,'Stock Movements'!$C:$C,$A21,'Stock Movements'!$F:$F,H$2,'Stock Movements'!$D:$D,"Out") -> 0 | I21: =SUMIFS('Stock Movements'!$E:$E,'Stock Movements'!$C:$C,$A21,'Stock Movements'!$F:$F,I$2,'Stock Movements'!$D:$D,"Out") -> 0 | J21: =SUMIFS('Stock Movements'!$E:$E,'Stock Movements'!$C:$C,$A21,'Stock Movements'!$F:$F,J$2,'Stock Movements'!$D:$D,"Out") -> 0 | ... R21: =SUMIFS('Stock Movements'!$E:$E,'Stock Movements'!$C:$C,$A21,'Stock Movements'!$F:$F,R$2,'Stock Movements'!$D:$D,"Out") -> 0 | S21: =SUM(C21:R21) -> 0 | T21: =S21-'Item Catalog'!$M$21 -> 0
A22: ='Item Catalog'!$B$22 -> ITM-020 · AUSTRALIAN SALT | B22: ='Item Catalog'!$C$22 -> AUSTRALIAN SALT | C22: =SUMIFS('Stock Movements'!$E:$E,'Stock Movements'!$C:$C,$A22,'Stock Movements'!$F:$F,C$2,'Stock Movements'!$D:$D,"Out") -> 14 | D22: =SUMIFS('Stock Movements'!$E:$E,'Stock Movements'!$C:$C,$A22,'Stock Movements'!$F:$F,D$2,'Stock Movements'!$D:$D,"Out") -> 0 | E22: =SUMIFS('Stock Movements'!$E:$E,'Stock Movements'!$C:$C,$A22,'Stock Movements'!$F:$F,E$2,'Stock Movements'!$D:$D,"Out") -> 0 | F22: =SUMIFS('Stock Movements'!$E:$E,'Stock Movements'!$C:$C,$A22,'Stock Movements'!$F:$F,F$2,'Stock Movements'!$D:$D,"Out") -> 0 | G22: =SUMIFS('Stock Movements'!$E:$E,'Stock Movements'!$C:$C,$A22,'Stock Movements'!$F:$F,G$2,'Stock Movements'!$D:$D,"Out") -> 1 | H22: =SUMIFS('Stock Movements'!$E:$E,'Stock Movements'!$C:$C,$A22,'Stock Movements'!$F:$F,H$2,'Stock Movements'!$D:$D,"Out") -> 0 | I22: =SUMIFS('Stock Movements'!$E:$E,'Stock Movements'!$C:$C,$A22,'Stock Movements'!$F:$F,I$2,'Stock Movements'!$D:$D,"Out") -> 0 | J22: =SUMIFS('Stock Movements'!$E:$E,'Stock Movements'!$C:$C,$A22,'Stock Movements'!$F:$F,J$2,'Stock Movements'!$D:$D,"Out") -> 0 | ... R22: =SUMIFS('Stock Movements'!$E:$E,'Stock Movements'!$C:$C,$A22,'Stock Movements'!$F:$F,R$2,'Stock Movements'!$D:$D,"Out") -> 0 | S22: =SUM(C22:R22) -> 15 | T22: =S22-'Item Catalog'!$M$22 -> 0
A23: ='Item Catalog'!$B$23 -> ITM-021 · INDUSTRIAL SALT ART-COURSE | B23: ='Item Catalog'!$C$23 -> INDUSTRIAL SALT ART-COURSE | C23: =SUMIFS('Stock Movements'!$E:$E,'Stock Movements'!$C:$C,$A23,'Stock Movements'!$F:$F,C$2,'Stock Movements'!$D:$D,"Out") -> 32 | D23: =SUMIFS('Stock Movements'!$E:$E,'Stock Movements'!$C:$C,$A23,'Stock Movements'!$F:$F,D$2,'Stock Movements'!$D:$D,"Out") -> 0 | E23: =SUMIFS('Stock Movements'!$E:$E,'Stock Movements'!$C:$C,$A23,'Stock Movements'!$F:$F,E$2,'Stock Movements'!$D:$D,"Out") -> 0 | F23: =SUMIFS('Stock Movements'!$E:$E,'Stock Movements'!$C:$C,$A23,'Stock Movements'!$F:$F,F$2,'Stock Movements'!$D:$D,"Out") -> 0 | G23: =SUMIFS('Stock Movements'!$E:$E,'Stock Movements'!$C:$C,$A23,'Stock Movements'!$F:$F,G$2,'Stock Movements'!$D:$D,"Out") -> 0 | H23: =SUMIFS('Stock Movements'!$E:$E,'Stock Movements'!$C:$C,$A23,'Stock Movements'!$F:$F,H$2,'Stock Movements'!$D:$D,"Out") -> 0 | I23: =SUMIFS('Stock Movements'!$E:$E,'Stock Movements'!$C:$C,$A23,'Stock Movements'!$F:$F,I$2,'Stock Movements'!$D:$D,"Out") -> 0 | J23: =SUMIFS('Stock Movements'!$E:$E,'Stock Movements'!$C:$C,$A23,'Stock Movements'!$F:$F,J$2,'Stock Movements'!$D:$D,"Out") -> 1 | ... R23: =SUMIFS('Stock Movements'!$E:$E,'Stock Movements'!$C:$C,$A23,'Stock Movements'!$F:$F,R$2,'Stock Movements'!$D:$D,"Out") -> 6 | S23: =SUM(C23:R23) -> 63 | T23: =S23-'Item Catalog'!$M$23 -> 0
A24: ='Item Catalog'!$B$24 -> ITM-022 · INDUSTRIAL SALT ART-COURSE | B24: ='Item Catalog'!$C$24 -> INDUSTRIAL SALT ART-COURSE | C24: =SUMIFS('Stock Movements'!$E:$E,'Stock Movements'!$C:$C,$A24,'Stock Movements'!$F:$F,C$2,'Stock Movements'!$D:$D,"Out") -> 0 | D24: =SUMIFS('Stock Movements'!$E:$E,'Stock Movements'!$C:$C,$A24,'Stock Movements'!$F:$F,D$2,'Stock Movements'!$D:$D,"Out") -> 0 | E24: =SUMIFS('Stock Movements'!$E:$E,'Stock Movements'!$C:$C,$A24,'Stock Movements'!$F:$F,E$2,'Stock Movements'!$D:$D,"Out") -> 0 | F24: =SUMIFS('Stock Movements'!$E:$E,'Stock Movements'!$C:$C,$A24,'Stock Movements'!$F:$F,F$2,'Stock Movements'!$D:$D,"Out") -> 0 | G24: =SUMIFS('Stock Movements'!$E:$E,'Stock Movements'!$C:$C,$A24,'Stock Movements'!$F:$F,G$2,'Stock Movements'!$D:$D,"Out") -> 0 | H24: =SUMIFS('Stock Movements'!$E:$E,'Stock Movements'!$C:$C,$A24,'Stock Movements'!$F:$F,H$2,'Stock Movements'!$D:$D,"Out") -> 0 | I24: =SUMIFS('Stock Movements'!$E:$E,'Stock Movements'!$C:$C,$A24,'Stock Movements'!$F:$F,I$2,'Stock Movements'!$D:$D,"Out") -> 0 | J24: =SUMIFS('Stock Movements'!$E:$E,'Stock Movements'!$C:$C,$A24,'Stock Movements'!$F:$F,J$2,'Stock Movements'!$D:$D,"Out") -> 0 | ... R24: =SUMIFS('Stock Movements'!$E:$E,'Stock Movements'!$C:$C,$A24,'Stock Movements'!$F:$F,R$2,'Stock Movements'!$D:$D,"Out") -> 0 | S24: =SUM(C24:R24) -> 0 | T24: =S24-'Item Catalog'!$M$24 -> 0
A25: ='Item Catalog'!$B$25 -> ITM-023 · 5M SF 20SL LW ( MONTHLY (2PC) FOR PURIFIED/MINERAL ) | B25: ='Item Catalog'!$C$25 -> 5M SF 20SL LW ( MONTHLY (2PC) FOR PURIFIED/MINERAL ) | C25: =SUMIFS('Stock Movements'!$E:$E,'Stock Movements'!$C:$C,$A25,'Stock Movements'!$F:$F,C$2,'Stock Movements'!$D:$D,"Out") -> 7 | D25: =SUMIFS('Stock Movements'!$E:$E,'Stock Movements'!$C:$C,$A25,'Stock Movements'!$F:$F,D$2,'Stock Movements'!$D:$D,"Out") -> 0 | E25: =SUMIFS('Stock Movements'!$E:$E,'Stock Movements'!$C:$C,$A25,'Stock Movements'!$F:$F,E$2,'Stock Movements'!$D:$D,"Out") -> 0 | F25: =SUMIFS('Stock Movements'!$E:$E,'Stock Movements'!$C:$C,$A25,'Stock Movements'!$F:$F,F$2,'Stock Movements'!$D:$D,"Out") -> 0 | G25: =SUMIFS('Stock Movements'!$E:$E,'Stock Movements'!$C:$C,$A25,'Stock Movements'!$F:$F,G$2,'Stock Movements'!$D:$D,"Out") -> 0 | H25: =SUMIFS('Stock Movements'!$E:$E,'Stock Movements'!$C:$C,$A25,'Stock Movements'!$F:$F,H$2,'Stock Movements'!$D:$D,"Out") -> 0 | I25: =SUMIFS('Stock Movements'!$E:$E,'Stock Movements'!$C:$C,$A25,'Stock Movements'!$F:$F,I$2,'Stock Movements'!$D:$D,"Out") -> 0 | J25: =SUMIFS('Stock Movements'!$E:$E,'Stock Movements'!$C:$C,$A25,'Stock Movements'!$F:$F,J$2,'Stock Movements'!$D:$D,"Out") -> 2 | ... R25: =SUMIFS('Stock Movements'!$E:$E,'Stock Movements'!$C:$C,$A25,'Stock Movements'!$F:$F,R$2,'Stock Movements'!$D:$D,"Out") -> 0 | S25: =SUM(C25:R25) -> 9 | T25: =S25-'Item Catalog'!$M$25 -> 0
A26: ='Item Catalog'!$B$26 -> ITM-024 · SEDIMENT: LWS 20" SLIM 5-MIC | B26: ='Item Catalog'!$C$26 -> SEDIMENT: LWS 20" SLIM 5-MIC | C26: =SUMIFS('Stock Movements'!$E:$E,'Stock Movements'!$C:$C,$A26,'Stock Movements'!$F:$F,C$2,'Stock Movements'!$D:$D,"Out") -> 0 | D26: =SUMIFS('Stock Movements'!$E:$E,'Stock Movements'!$C:$C,$A26,'Stock Movements'!$F:$F,D$2,'Stock Movements'!$D:$D,"Out") -> 0 | E26: =SUMIFS('Stock Movements'!$E:$E,'Stock Movements'!$C:$C,$A26,'Stock Movements'!$F:$F,E$2,'Stock Movements'!$D:$D,"Out") -> 0 | F26: =SUMIFS('Stock Movements'!$E:$E,'Stock Movements'!$C:$C,$A26,'Stock Movements'!$F:$F,F$2,'Stock Movements'!$D:$D,"Out") -> 0 | G26: =SUMIFS('Stock Movements'!$E:$E,'Stock Movements'!$C:$C,$A26,'Stock Movements'!$F:$F,G$2,'Stock Movements'!$D:$D,"Out") -> 0 | H26: =SUMIFS('Stock Movements'!$E:$E,'Stock Movements'!$C:$C,$A26,'Stock Movements'!$F:$F,H$2,'Stock Movements'!$D:$D,"Out") -> 0 | I26: =SUMIFS('Stock Movements'!$E:$E,'Stock Movements'!$C:$C,$A26,'Stock Movements'!$F:$F,I$2,'Stock Movements'!$D:$D,"Out") -> 0 | J26: =SUMIFS('Stock Movements'!$E:$E,'Stock Movements'!$C:$C,$A26,'Stock Movements'!$F:$F,J$2,'Stock Movements'!$D:$D,"Out") -> 0 | ... R26: =SUMIFS('Stock Movements'!$E:$E,'Stock Movements'!$C:$C,$A26,'Stock Movements'!$F:$F,R$2,'Stock Movements'!$D:$D,"Out") -> 0 | S26: =SUM(C26:R26) -> 0 | T26: =S26-'Item Catalog'!$M$26 -> 0
A27: ='Item Catalog'!$B$27 -> ITM-025 · 1M SF 20S LW ( QUARTERLY (2PC) FOR PURIFIED/MINERAL ) | B27: ='Item Catalog'!$C$27 -> 1M SF 20S LW ( QUARTERLY (2PC) FOR PURIFIED/MINERAL ) | C27: =SUMIFS('Stock Movements'!$E:$E,'Stock Movements'!$C:$C,$A27,'Stock Movements'!$F:$F,C$2,'Stock Movements'!$D:$D,"Out") -> 12 | D27: =SUMIFS('Stock Movements'!$E:$E,'Stock Movements'!$C:$C,$A27,'Stock Movements'!$F:$F,D$2,'Stock Movements'!$D:$D,"Out") -> 0 | E27: =SUMIFS('Stock Movements'!$E:$E,'Stock Movements'!$C:$C,$A27,'Stock Movements'!$F:$F,E$2,'Stock Movements'!$D:$D,"Out") -> 0 | F27: =SUMIFS('Stock Movements'!$E:$E,'Stock Movements'!$C:$C,$A27,'Stock Movements'!$F:$F,F$2,'Stock Movements'!$D:$D,"Out") -> 0 | G27: =SUMIFS('Stock Movements'!$E:$E,'Stock Movements'!$C:$C,$A27,'Stock Movements'!$F:$F,G$2,'Stock Movements'!$D:$D,"Out") -> 0 | H27: =SUMIFS('Stock Movements'!$E:$E,'Stock Movements'!$C:$C,$A27,'Stock Movements'!$F:$F,H$2,'Stock Movements'!$D:$D,"Out") -> 0 | I27: =SUMIFS('Stock Movements'!$E:$E,'Stock Movements'!$C:$C,$A27,'Stock Movements'!$F:$F,I$2,'Stock Movements'!$D:$D,"Out") -> 0 | J27: =SUMIFS('Stock Movements'!$E:$E,'Stock Movements'!$C:$C,$A27,'Stock Movements'!$F:$F,J$2,'Stock Movements'!$D:$D,"Out") -> 0 | ... R27: =SUMIFS('Stock Movements'!$E:$E,'Stock Movements'!$C:$C,$A27,'Stock Movements'!$F:$F,R$2,'Stock Movements'!$D:$D,"Out") -> 0 | S27: =SUM(C27:R27) -> 13 | T27: =S27-'Item Catalog'!$M$27 -> 0
A28: ='Item Catalog'!$B$28 -> ITM-026 · SEDIMENT: LWS 20" SLIM 1-MIC | B28: ='Item Catalog'!$C$28 -> SEDIMENT: LWS 20" SLIM 1-MIC | C28: =SUMIFS('Stock Movements'!$E:$E,'Stock Movements'!$C:$C,$A28,'Stock Movements'!$F:$F,C$2,'Stock Movements'!$D:$D,"Out") -> 0 | D28: =SUMIFS('Stock Movements'!$E:$E,'Stock Movements'!$C:$C,$A28,'Stock Movements'!$F:$F,D$2,'Stock Movements'!$D:$D,"Out") -> 0 | E28: =SUMIFS('Stock Movements'!$E:$E,'Stock Movements'!$C:$C,$A28,'Stock Movements'!$F:$F,E$2,'Stock Movements'!$D:$D,"Out") -> 0 | F28: =SUMIFS('Stock Movements'!$E:$E,'Stock Movements'!$C:$C,$A28,'Stock Movements'!$F:$F,F$2,'Stock Movements'!$D:$D,"Out") -> 0 | G28: =SUMIFS('Stock Movements'!$E:$E,'Stock Movements'!$C:$C,$A28,'Stock Movements'!$F:$F,G$2,'Stock Movements'!$D:$D,"Out") -> 0 | H28: =SUMIFS('Stock Movements'!$E:$E,'Stock Movements'!$C:$C,$A28,'Stock Movements'!$F:$F,H$2,'Stock Movements'!$D:$D,"Out") -> 0 | I28: =SUMIFS('Stock Movements'!$E:$E,'Stock Movements'!$C:$C,$A28,'Stock Movements'!$F:$F,I$2,'Stock Movements'!$D:$D,"Out") -> 0 | J28: =SUMIFS('Stock Movements'!$E:$E,'Stock Movements'!$C:$C,$A28,'Stock Movements'!$F:$F,J$2,'Stock Movements'!$D:$D,"Out") -> 0 | ... R28: =SUMIFS('Stock Movements'!$E:$E,'Stock Movements'!$C:$C,$A28,'Stock Movements'!$F:$F,R$2,'Stock Movements'!$D:$D,"Out") -> 0 | S28: =SUM(C28:R28) -> 0 | T28: =S28-'Item Catalog'!$M$28 -> 0
A29: ='Item Catalog'!$B$29 -> ITM-027 · 1M SF 10SL LW ( QUARTERLY (1PC) FOR ALKALINE ) (SEDIMENT: LWS 10" SLIM 1-MIC) | B29: ='Item Catalog'!$C$29 -> 1M SF 10SL LW ( QUARTERLY (1PC) FOR ALKALINE ) (SEDIMENT: LWS 10" SLIM 1-MIC) | C29: =SUMIFS('Stock Movements'!$E:$E,'Stock Movements'!$C:$C,$A29,'Stock Movements'!$F:$F,C$2,'Stock Movements'!$D:$D,"Out") -> 6 | D29: =SUMIFS('Stock Movements'!$E:$E,'Stock Movements'!$C:$C,$A29,'Stock Movements'!$F:$F,D$2,'Stock Movements'!$D:$D,"Out") -> 0 | E29: =SUMIFS('Stock Movements'!$E:$E,'Stock Movements'!$C:$C,$A29,'Stock Movements'!$F:$F,E$2,'Stock Movements'!$D:$D,"Out") -> 0 | F29: =SUMIFS('Stock Movements'!$E:$E,'Stock Movements'!$C:$C,$A29,'Stock Movements'!$F:$F,F$2,'Stock Movements'!$D:$D,"Out") -> 0 | G29: =SUMIFS('Stock Movements'!$E:$E,'Stock Movements'!$C:$C,$A29,'Stock Movements'!$F:$F,G$2,'Stock Movements'!$D:$D,"Out") -> 0 | H29: =SUMIFS('Stock Movements'!$E:$E,'Stock Movements'!$C:$C,$A29,'Stock Movements'!$F:$F,H$2,'Stock Movements'!$D:$D,"Out") -> 0 | I29: =SUMIFS('Stock Movements'!$E:$E,'Stock Movements'!$C:$C,$A29,'Stock Movements'!$F:$F,I$2,'Stock Movements'!$D:$D,"Out") -> 0 | J29: =SUMIFS('Stock Movements'!$E:$E,'Stock Movements'!$C:$C,$A29,'Stock Movements'!$F:$F,J$2,'Stock Movements'!$D:$D,"Out") -> 0 | ... R29: =SUMIFS('Stock Movements'!$E:$E,'Stock Movements'!$C:$C,$A29,'Stock Movements'!$F:$F,R$2,'Stock Movements'!$D:$D,"Out") -> 0 | S29: =SUM(C29:R29) -> 6 | T29: =S29-'Item Catalog'!$M$29 -> 0
A30: ='Item Catalog'!$B$30 -> ITM-028 · HYDROSEP CTO 20SL ( QUARTERLY (2PC) FOR PURIFIED/MINERAL ) | B30: ='Item Catalog'!$C$30 -> HYDROSEP CTO 20SL ( QUARTERLY (2PC) FOR PURIFIED/MINERAL ) | C30: =SUMIFS('Stock Movements'!$E:$E,'Stock Movements'!$C:$C,$A30,'Stock Movements'!$F:$F,C$2,'Stock Movements'!$D:$D,"Out") -> 13 | D30: =SUMIFS('Stock Movements'!$E:$E,'Stock Movements'!$C:$C,$A30,'Stock Movements'!$F:$F,D$2,'Stock Movements'!$D:$D,"Out") -> 0 | E30: =SUMIFS('Stock Movements'!$E:$E,'Stock Movements'!$C:$C,$A30,'Stock Movements'!$F:$F,E$2,'Stock Movements'!$D:$D,"Out") -> 2 | F30: =SUMIFS('Stock Movements'!$E:$E,'Stock Movements'!$C:$C,$A30,'Stock Movements'!$F:$F,F$2,'Stock Movements'!$D:$D,"Out") -> 0 | G30: =SUMIFS('Stock Movements'!$E:$E,'Stock Movements'!$C:$C,$A30,'Stock Movements'!$F:$F,G$2,'Stock Movements'!$D:$D,"Out") -> 0 | H30: =SUMIFS('Stock Movements'!$E:$E,'Stock Movements'!$C:$C,$A30,'Stock Movements'!$F:$F,H$2,'Stock Movements'!$D:$D,"Out") -> 0 | I30: =SUMIFS('Stock Movements'!$E:$E,'Stock Movements'!$C:$C,$A30,'Stock Movements'!$F:$F,I$2,'Stock Movements'!$D:$D,"Out") -> 0 | J30: =SUMIFS('Stock Movements'!$E:$E,'Stock Movements'!$C:$C,$A30,'Stock Movements'!$F:$F,J$2,'Stock Movements'!$D:$D,"Out") -> 0 | ... R30: =SUMIFS('Stock Movements'!$E:$E,'Stock Movements'!$C:$C,$A30,'Stock Movements'!$F:$F,R$2,'Stock Movements'!$D:$D,"Out") -> 0 | S30: =SUM(C30:R30) -> 20 | T30: =S30-'Item Catalog'!$M$30 -> 0
A31: ='Item Catalog'!$B$31 -> ITM-029 · HYDROSEP CTO 10SL ( QUARTERLY (1PC) FOR ALKALINE ) | B31: ='Item Catalog'!$C$31 -> HYDROSEP CTO 10SL ( QUARTERLY (1PC) FOR ALKALINE ) | C31: =SUMIFS('Stock Movements'!$E:$E,'Stock Movements'!$C:$C,$A31,'Stock Movements'!$F:$F,C$2,'Stock Movements'!$D:$D,"Out") -> 6 | D31: =SUMIFS('Stock Movements'!$E:$E,'Stock Movements'!$C:$C,$A31,'Stock Movements'!$F:$F,D$2,'Stock Movements'!$D:$D,"Out") -> 0 | E31: =SUMIFS('Stock Movements'!$E:$E,'Stock Movements'!$C:$C,$A31,'Stock Movements'!$F:$F,E$2,'Stock Movements'!$D:$D,"Out") -> 0 | F31: =SUMIFS('Stock Movements'!$E:$E,'Stock Movements'!$C:$C,$A31,'Stock Movements'!$F:$F,F$2,'Stock Movements'!$D:$D,"Out") -> 0 | G31: =SUMIFS('Stock Movements'!$E:$E,'Stock Movements'!$C:$C,$A31,'Stock Movements'!$F:$F,G$2,'Stock Movements'!$D:$D,"Out") -> 0 | H31: =SUMIFS('Stock Movements'!$E:$E,'Stock Movements'!$C:$C,$A31,'Stock Movements'!$F:$F,H$2,'Stock Movements'!$D:$D,"Out") -> 0 | I31: =SUMIFS('Stock Movements'!$E:$E,'Stock Movements'!$C:$C,$A31,'Stock Movements'!$F:$F,I$2,'Stock Movements'!$D:$D,"Out") -> 0 | J31: =SUMIFS('Stock Movements'!$E:$E,'Stock Movements'!$C:$C,$A31,'Stock Movements'!$F:$F,J$2,'Stock Movements'!$D:$D,"Out") -> 0 | ... R31: =SUMIFS('Stock Movements'!$E:$E,'Stock Movements'!$C:$C,$A31,'Stock Movements'!$F:$F,R$2,'Stock Movements'!$D:$D,"Out") -> 0 | S31: =SUM(C31:R31) -> 6 | T31: =S31-'Item Catalog'!$M$31 -> 0
A32: ='Item Catalog'!$B$32 -> ITM-030 · CERAMIC FILTER 10SL ( QUARTERLY (1PC) FOR ALKALINE ) | B32: ='Item Catalog'!$C$32 -> CERAMIC FILTER 10SL ( QUARTERLY (1PC) FOR ALKALINE ) | C32: =SUMIFS('Stock Movements'!$E:$E,'Stock Movements'!$C:$C,$A32,'Stock Movements'!$F:$F,C$2,'Stock Movements'!$D:$D,"Out") -> 3 | D32: =SUMIFS('Stock Movements'!$E:$E,'Stock Movements'!$C:$C,$A32,'Stock Movements'!$F:$F,D$2,'Stock Movements'!$D:$D,"Out") -> 0 | E32: =SUMIFS('Stock Movements'!$E:$E,'Stock Movements'!$C:$C,$A32,'Stock Movements'!$F:$F,E$2,'Stock Movements'!$D:$D,"Out") -> 0 | F32: =SUMIFS('Stock Movements'!$E:$E,'Stock Movements'!$C:$C,$A32,'Stock Movements'!$F:$F,F$2,'Stock Movements'!$D:$D,"Out") -> 0 | G32: =SUMIFS('Stock Movements'!$E:$E,'Stock Movements'!$C:$C,$A32,'Stock Movements'!$F:$F,G$2,'Stock Movements'!$D:$D,"Out") -> 0 | H32: =SUMIFS('Stock Movements'!$E:$E,'Stock Movements'!$C:$C,$A32,'Stock Movements'!$F:$F,H$2,'Stock Movements'!$D:$D,"Out") -> 0 | I32: =SUMIFS('Stock Movements'!$E:$E,'Stock Movements'!$C:$C,$A32,'Stock Movements'!$F:$F,I$2,'Stock Movements'!$D:$D,"Out") -> 0 | J32: =SUMIFS('Stock Movements'!$E:$E,'Stock Movements'!$C:$C,$A32,'Stock Movements'!$F:$F,J$2,'Stock Movements'!$D:$D,"Out") -> 0 | ... R32: =SUMIFS('Stock Movements'!$E:$E,'Stock Movements'!$C:$C,$A32,'Stock Movements'!$F:$F,R$2,'Stock Movements'!$D:$D,"Out") -> 0 | S32: =SUM(C32:R32) -> 3 | T32: =S32-'Item Catalog'!$M$32 -> 0
A33: ='Item Catalog'!$B$33 -> ITM-031 · BIO FILTER 10SL ( QUARTERLY (1PC) FOR ALKALINE ) | B33: ='Item Catalog'!$C$33 -> BIO FILTER 10SL ( QUARTERLY (1PC) FOR ALKALINE ) | C33: =SUMIFS('Stock Movements'!$E:$E,'Stock Movements'!$C:$C,$A33,'Stock Movements'!$F:$F,C$2,'Stock Movements'!$D:$D,"Out") -> 2 | D33: =SUMIFS('Stock Movements'!$E:$E,'Stock Movements'!$C:$C,$A33,'Stock Movements'!$F:$F,D$2,'Stock Movements'!$D:$D,"Out") -> 0 | E33: =SUMIFS('Stock Movements'!$E:$E,'Stock Movements'!$C:$C,$A33,'Stock Movements'!$F:$F,E$2,'Stock Movements'!$D:$D,"Out") -> 0 | F33: =SUMIFS('Stock Movements'!$E:$E,'Stock Movements'!$C:$C,$A33,'Stock Movements'!$F:$F,F$2,'Stock Movements'!$D:$D,"Out") -> 0 | G33: =SUMIFS('Stock Movements'!$E:$E,'Stock Movements'!$C:$C,$A33,'Stock Movements'!$F:$F,G$2,'Stock Movements'!$D:$D,"Out") -> 0 | H33: =SUMIFS('Stock Movements'!$E:$E,'Stock Movements'!$C:$C,$A33,'Stock Movements'!$F:$F,H$2,'Stock Movements'!$D:$D,"Out") -> 0 | I33: =SUMIFS('Stock Movements'!$E:$E,'Stock Movements'!$C:$C,$A33,'Stock Movements'!$F:$F,I$2,'Stock Movements'!$D:$D,"Out") -> 0 | J33: =SUMIFS('Stock Movements'!$E:$E,'Stock Movements'!$C:$C,$A33,'Stock Movements'!$F:$F,J$2,'Stock Movements'!$D:$D,"Out") -> 0 | ... R33: =SUMIFS('Stock Movements'!$E:$E,'Stock Movements'!$C:$C,$A33,'Stock Movements'!$F:$F,R$2,'Stock Movements'!$D:$D,"Out") -> 0 | S33: =SUM(C33:R33) -> 2 | T33: =S33-'Item Catalog'!$M$33 -> 0
A34: ='Item Catalog'!$B$34 -> ITM-032 · WOW 20" SLIM 5-MIC | B34: ='Item Catalog'!$C$34 -> WOW 20" SLIM 5-MIC | C34: =SUMIFS('Stock Movements'!$E:$E,'Stock Movements'!$C:$C,$A34,'Stock Movements'!$F:$F,C$2,'Stock Movements'!$D:$D,"Out") -> 0 | D34: =SUMIFS('Stock Movements'!$E:$E,'Stock Movements'!$C:$C,$A34,'Stock Movements'!$F:$F,D$2,'Stock Movements'!$D:$D,"Out") -> 2 | E34: =SUMIFS('Stock Movements'!$E:$E,'Stock Movements'!$C:$C,$A34,'Stock Movements'!$F:$F,E$2,'Stock Movements'!$D:$D,"Out") -> 0 | F34: =SUMIFS('Stock Movements'!$E:$E,'Stock Movements'!$C:$C,$A34,'Stock Movements'!$F:$F,F$2,'Stock Movements'!$D:$D,"Out") -> 0 | G34: =SUMIFS('Stock Movements'!$E:$E,'Stock Movements'!$C:$C,$A34,'Stock Movements'!$F:$F,G$2,'Stock Movements'!$D:$D,"Out") -> 0 | H34: =SUMIFS('Stock Movements'!$E:$E,'Stock Movements'!$C:$C,$A34,'Stock Movements'!$F:$F,H$2,'Stock Movements'!$D:$D,"Out") -> 0 | I34: =SUMIFS('Stock Movements'!$E:$E,'Stock Movements'!$C:$C,$A34,'Stock Movements'!$F:$F,I$2,'Stock Movements'!$D:$D,"Out") -> 0 | J34: =SUMIFS('Stock Movements'!$E:$E,'Stock Movements'!$C:$C,$A34,'Stock Movements'!$F:$F,J$2,'Stock Movements'!$D:$D,"Out") -> 0 | ... R34: =SUMIFS('Stock Movements'!$E:$E,'Stock Movements'!$C:$C,$A34,'Stock Movements'!$F:$F,R$2,'Stock Movements'!$D:$D,"Out") -> 0 | S34: =SUM(C34:R34) -> 10 | T34: =S34-'Item Catalog'!$M$34 -> 0
A35: ='Item Catalog'!$B$35 -> ITM-033 · WOW 20" SLIM 1-MIC | B35: ='Item Catalog'!$C$35 -> WOW 20" SLIM 1-MIC | C35: =SUMIFS('Stock Movements'!$E:$E,'Stock Movements'!$C:$C,$A35,'Stock Movements'!$F:$F,C$2,'Stock Movements'!$D:$D,"Out") -> 0 | D35: =SUMIFS('Stock Movements'!$E:$E,'Stock Movements'!$C:$C,$A35,'Stock Movements'!$F:$F,D$2,'Stock Movements'!$D:$D,"Out") -> 2 | E35: =SUMIFS('Stock Movements'!$E:$E,'Stock Movements'!$C:$C,$A35,'Stock Movements'!$F:$F,E$2,'Stock Movements'!$D:$D,"Out") -> 0 | F35: =SUMIFS('Stock Movements'!$E:$E,'Stock Movements'!$C:$C,$A35,'Stock Movements'!$F:$F,F$2,'Stock Movements'!$D:$D,"Out") -> 0 | G35: =SUMIFS('Stock Movements'!$E:$E,'Stock Movements'!$C:$C,$A35,'Stock Movements'!$F:$F,G$2,'Stock Movements'!$D:$D,"Out") -> 0 | H35: =SUMIFS('Stock Movements'!$E:$E,'Stock Movements'!$C:$C,$A35,'Stock Movements'!$F:$F,H$2,'Stock Movements'!$D:$D,"Out") -> 0 | I35: =SUMIFS('Stock Movements'!$E:$E,'Stock Movements'!$C:$C,$A35,'Stock Movements'!$F:$F,I$2,'Stock Movements'!$D:$D,"Out") -> 0 | J35: =SUMIFS('Stock Movements'!$E:$E,'Stock Movements'!$C:$C,$A35,'Stock Movements'!$F:$F,J$2,'Stock Movements'!$D:$D,"Out") -> 0 | ... R35: =SUMIFS('Stock Movements'!$E:$E,'Stock Movements'!$C:$C,$A35,'Stock Movements'!$F:$F,R$2,'Stock Movements'!$D:$D,"Out") -> 0 | S35: =SUM(C35:R35) -> 10 | T35: =S35-'Item Catalog'!$M$35 -> 0
A36: ='Item Catalog'!$B$36 -> ITM-034 · WOW 10" SLIM 1-MIC | B36: ='Item Catalog'!$C$36 -> WOW 10" SLIM 1-MIC | C36: =SUMIFS('Stock Movements'!$E:$E,'Stock Movements'!$C:$C,$A36,'Stock Movements'!$F:$F,C$2,'Stock Movements'!$D:$D,"Out") -> 0 | D36: =SUMIFS('Stock Movements'!$E:$E,'Stock Movements'!$C:$C,$A36,'Stock Movements'!$F:$F,D$2,'Stock Movements'!$D:$D,"Out") -> 0 | E36: =SUMIFS('Stock Movements'!$E:$E,'Stock Movements'!$C:$C,$A36,'Stock Movements'!$F:$F,E$2,'Stock Movements'!$D:$D,"Out") -> 0 | F36: =SUMIFS('Stock Movements'!$E:$E,'Stock Movements'!$C:$C,$A36,'Stock Movements'!$F:$F,F$2,'Stock Movements'!$D:$D,"Out") -> 0 | G36: =SUMIFS('Stock Movements'!$E:$E,'Stock Movements'!$C:$C,$A36,'Stock Movements'!$F:$F,G$2,'Stock Movements'!$D:$D,"Out") -> 0 | H36: =SUMIFS('Stock Movements'!$E:$E,'Stock Movements'!$C:$C,$A36,'Stock Movements'!$F:$F,H$2,'Stock Movements'!$D:$D,"Out") -> 0 | I36: =SUMIFS('Stock Movements'!$E:$E,'Stock Movements'!$C:$C,$A36,'Stock Movements'!$F:$F,I$2,'Stock Movements'!$D:$D,"Out") -> 0 | J36: =SUMIFS('Stock Movements'!$E:$E,'Stock Movements'!$C:$C,$A36,'Stock Movements'!$F:$F,J$2,'Stock Movements'!$D:$D,"Out") -> 0 | ... R36: =SUMIFS('Stock Movements'!$E:$E,'Stock Movements'!$C:$C,$A36,'Stock Movements'!$F:$F,R$2,'Stock Movements'!$D:$D,"Out") -> 0 | S36: =SUM(C36:R36) -> 0 | T36: =S36-'Item Catalog'!$M$36 -> 0
A37: ='Item Catalog'!$B$37 -> ITM-035 · UV LAMPS: UVC-PRO 6 GPM 14W | B37: ='Item Catalog'!$C$37 -> UV LAMPS: UVC-PRO 6 GPM 14W | C37: =SUMIFS('Stock Movements'!$E:$E,'Stock Movements'!$C:$C,$A37,'Stock Movements'!$F:$F,C$2,'Stock Movements'!$D:$D,"Out") -> 0 | D37: =SUMIFS('Stock Movements'!$E:$E,'Stock Movements'!$C:$C,$A37,'Stock Movements'!$F:$F,D$2,'Stock Movements'!$D:$D,"Out") -> 0 | E37: =SUMIFS('Stock Movements'!$E:$E,'Stock Movements'!$C:$C,$A37,'Stock Movements'!$F:$F,E$2,'Stock Movements'!$D:$D,"Out") -> 0 | F37: =SUMIFS('Stock Movements'!$E:$E,'Stock Movements'!$C:$C,$A37,'Stock Movements'!$F:$F,F$2,'Stock Movements'!$D:$D,"Out") -> 0 | G37: =SUMIFS('Stock Movements'!$E:$E,'Stock Movements'!$C:$C,$A37,'Stock Movements'!$F:$F,G$2,'Stock Movements'!$D:$D,"Out") -> 0 | H37: =SUMIFS('Stock Movements'!$E:$E,'Stock Movements'!$C:$C,$A37,'Stock Movements'!$F:$F,H$2,'Stock Movements'!$D:$D,"Out") -> 0 | I37: =SUMIFS('Stock Movements'!$E:$E,'Stock Movements'!$C:$C,$A37,'Stock Movements'!$F:$F,I$2,'Stock Movements'!$D:$D,"Out") -> 0 | J37: =SUMIFS('Stock Movements'!$E:$E,'Stock Movements'!$C:$C,$A37,'Stock Movements'!$F:$F,J$2,'Stock Movements'!$D:$D,"Out") -> 0 | ... R37: =SUMIFS('Stock Movements'!$E:$E,'Stock Movements'!$C:$C,$A37,'Stock Movements'!$F:$F,R$2,'Stock Movements'!$D:$D,"Out") -> 0 | S37: =SUM(C37:R37) -> 0 | T37: =S37-'Item Catalog'!$M$37 -> 0
A38: ='Item Catalog'!$B$38 -> ITM-036 · 350 ML PET BOTTLE (WITH CAP) | B38: ='Item Catalog'!$C$38 -> 350 ML PET BOTTLE (WITH CAP) | C38: =SUMIFS('Stock Movements'!$E:$E,'Stock Movements'!$C:$C,$A38,'Stock Movements'!$F:$F,C$2,'Stock Movements'!$D:$D,"Out") -> 19 | D38: =SUMIFS('Stock Movements'!$E:$E,'Stock Movements'!$C:$C,$A38,'Stock Movements'!$F:$F,D$2,'Stock Movements'!$D:$D,"Out") -> 0 | E38: =SUMIFS('Stock Movements'!$E:$E,'Stock Movements'!$C:$C,$A38,'Stock Movements'!$F:$F,E$2,'Stock Movements'!$D:$D,"Out") -> 0 | F38: =SUMIFS('Stock Movements'!$E:$E,'Stock Movements'!$C:$C,$A38,'Stock Movements'!$F:$F,F$2,'Stock Movements'!$D:$D,"Out") -> 0 | G38: =SUMIFS('Stock Movements'!$E:$E,'Stock Movements'!$C:$C,$A38,'Stock Movements'!$F:$F,G$2,'Stock Movements'!$D:$D,"Out") -> 0 | H38: =SUMIFS('Stock Movements'!$E:$E,'Stock Movements'!$C:$C,$A38,'Stock Movements'!$F:$F,H$2,'Stock Movements'!$D:$D,"Out") -> 0 | I38: =SUMIFS('Stock Movements'!$E:$E,'Stock Movements'!$C:$C,$A38,'Stock Movements'!$F:$F,I$2,'Stock Movements'!$D:$D,"Out") -> 0 | J38: =SUMIFS('Stock Movements'!$E:$E,'Stock Movements'!$C:$C,$A38,'Stock Movements'!$F:$F,J$2,'Stock Movements'!$D:$D,"Out") -> 2 | ... R38: =SUMIFS('Stock Movements'!$E:$E,'Stock Movements'!$C:$C,$A38,'Stock Movements'!$F:$F,R$2,'Stock Movements'!$D:$D,"Out") -> 0 | S38: =SUM(C38:R38) -> 23 | T38: =S38-'Item Catalog'!$M$38 -> 0
A39: ='Item Catalog'!$B$39 -> ITM-037 · 350 ML PET BOTTLE (WITH CAP) | B39: ='Item Catalog'!$C$39 -> 350 ML PET BOTTLE (WITH CAP) | C39: =SUMIFS('Stock Movements'!$E:$E,'Stock Movements'!$C:$C,$A39,'Stock Movements'!$F:$F,C$2,'Stock Movements'!$D:$D,"Out") -> 4 | D39: =SUMIFS('Stock Movements'!$E:$E,'Stock Movements'!$C:$C,$A39,'Stock Movements'!$F:$F,D$2,'Stock Movements'!$D:$D,"Out") -> 0 | E39: =SUMIFS('Stock Movements'!$E:$E,'Stock Movements'!$C:$C,$A39,'Stock Movements'!$F:$F,E$2,'Stock Movements'!$D:$D,"Out") -> 1 | F39: =SUMIFS('Stock Movements'!$E:$E,'Stock Movements'!$C:$C,$A39,'Stock Movements'!$F:$F,F$2,'Stock Movements'!$D:$D,"Out") -> 0 | G39: =SUMIFS('Stock Movements'!$E:$E,'Stock Movements'!$C:$C,$A39,'Stock Movements'!$F:$F,G$2,'Stock Movements'!$D:$D,"Out") -> 0 | H39: =SUMIFS('Stock Movements'!$E:$E,'Stock Movements'!$C:$C,$A39,'Stock Movements'!$F:$F,H$2,'Stock Movements'!$D:$D,"Out") -> 0 | I39: =SUMIFS('Stock Movements'!$E:$E,'Stock Movements'!$C:$C,$A39,'Stock Movements'!$F:$F,I$2,'Stock Movements'!$D:$D,"Out") -> 0 | J39: =SUMIFS('Stock Movements'!$E:$E,'Stock Movements'!$C:$C,$A39,'Stock Movements'!$F:$F,J$2,'Stock Movements'!$D:$D,"Out") -> 9 | ... R39: =SUMIFS('Stock Movements'!$E:$E,'Stock Movements'!$C:$C,$A39,'Stock Movements'!$F:$F,R$2,'Stock Movements'!$D:$D,"Out") -> 0 | S39: =SUM(C39:R39) -> 15 | T39: =S39-'Item Catalog'!$M$39 -> 0
A40: ='Item Catalog'!$B$40 -> ITM-038 · 500 ML PET BOTTLE (WITH CAP) | B40: ='Item Catalog'!$C$40 -> 500 ML PET BOTTLE (WITH CAP) | C40: =SUMIFS('Stock Movements'!$E:$E,'Stock Movements'!$C:$C,$A40,'Stock Movements'!$F:$F,C$2,'Stock Movements'!$D:$D,"Out") -> 4 | D40: =SUMIFS('Stock Movements'!$E:$E,'Stock Movements'!$C:$C,$A40,'Stock Movements'!$F:$F,D$2,'Stock Movements'!$D:$D,"Out") -> 0 | E40: =SUMIFS('Stock Movements'!$E:$E,'Stock Movements'!$C:$C,$A40,'Stock Movements'!$F:$F,E$2,'Stock Movements'!$D:$D,"Out") -> 0 | F40: =SUMIFS('Stock Movements'!$E:$E,'Stock Movements'!$C:$C,$A40,'Stock Movements'!$F:$F,F$2,'Stock Movements'!$D:$D,"Out") -> 0 | G40: =SUMIFS('Stock Movements'!$E:$E,'Stock Movements'!$C:$C,$A40,'Stock Movements'!$F:$F,G$2,'Stock Movements'!$D:$D,"Out") -> 0 | H40: =SUMIFS('Stock Movements'!$E:$E,'Stock Movements'!$C:$C,$A40,'Stock Movements'!$F:$F,H$2,'Stock Movements'!$D:$D,"Out") -> 0 | I40: =SUMIFS('Stock Movements'!$E:$E,'Stock Movements'!$C:$C,$A40,'Stock Movements'!$F:$F,I$2,'Stock Movements'!$D:$D,"Out") -> 0 | J40: =SUMIFS('Stock Movements'!$E:$E,'Stock Movements'!$C:$C,$A40,'Stock Movements'!$F:$F,J$2,'Stock Movements'!$D:$D,"Out") -> 0 | ... R40: =SUMIFS('Stock Movements'!$E:$E,'Stock Movements'!$C:$C,$A40,'Stock Movements'!$F:$F,R$2,'Stock Movements'!$D:$D,"Out") -> 0 | S40: =SUM(C40:R40) -> 4 | T40: =S40-'Item Catalog'!$M$40 -> 0
A41: ='Item Catalog'!$B$41 -> ITM-039 · 1000 ML PET BOTTLE (WITH CAP) | B41: ='Item Catalog'!$C$41 -> 1000 ML PET BOTTLE (WITH CAP) | C41: =SUMIFS('Stock Movements'!$E:$E,'Stock Movements'!$C:$C,$A41,'Stock Movements'!$F:$F,C$2,'Stock Movements'!$D:$D,"Out") -> 3 | D41: =SUMIFS('Stock Movements'!$E:$E,'Stock Movements'!$C:$C,$A41,'Stock Movements'!$F:$F,D$2,'Stock Movements'!$D:$D,"Out") -> 0 | E41: =SUMIFS('Stock Movements'!$E:$E,'Stock Movements'!$C:$C,$A41,'Stock Movements'!$F:$F,E$2,'Stock Movements'!$D:$D,"Out") -> 0 | F41: =SUMIFS('Stock Movements'!$E:$E,'Stock Movements'!$C:$C,$A41,'Stock Movements'!$F:$F,F$2,'Stock Movements'!$D:$D,"Out") -> 0 | G41: =SUMIFS('Stock Movements'!$E:$E,'Stock Movements'!$C:$C,$A41,'Stock Movements'!$F:$F,G$2,'Stock Movements'!$D:$D,"Out") -> 0 | H41: =SUMIFS('Stock Movements'!$E:$E,'Stock Movements'!$C:$C,$A41,'Stock Movements'!$F:$F,H$2,'Stock Movements'!$D:$D,"Out") -> 0 | I41: =SUMIFS('Stock Movements'!$E:$E,'Stock Movements'!$C:$C,$A41,'Stock Movements'!$F:$F,I$2,'Stock Movements'!$D:$D,"Out") -> 0 | J41: =SUMIFS('Stock Movements'!$E:$E,'Stock Movements'!$C:$C,$A41,'Stock Movements'!$F:$F,J$2,'Stock Movements'!$D:$D,"Out") -> 0 | ... R41: =SUMIFS('Stock Movements'!$E:$E,'Stock Movements'!$C:$C,$A41,'Stock Movements'!$F:$F,R$2,'Stock Movements'!$D:$D,"Out") -> 0 | S41: =SUM(C41:R41) -> 3 | T41: =S41-'Item Catalog'!$M$41 -> 0
A42: ='Item Catalog'!$B$42 -> ITM-040 · 350 ML LABEL SHRINKABLE LW | B42: ='Item Catalog'!$C$42 -> 350 ML LABEL SHRINKABLE LW | C42: =SUMIFS('Stock Movements'!$E:$E,'Stock Movements'!$C:$C,$A42,'Stock Movements'!$F:$F,C$2,'Stock Movements'!$D:$D,"Out") -> 8 | D42: =SUMIFS('Stock Movements'!$E:$E,'Stock Movements'!$C:$C,$A42,'Stock Movements'!$F:$F,D$2,'Stock Movements'!$D:$D,"Out") -> 0 | E42: =SUMIFS('Stock Movements'!$E:$E,'Stock Movements'!$C:$C,$A42,'Stock Movements'!$F:$F,E$2,'Stock Movements'!$D:$D,"Out") -> 0 | F42: =SUMIFS('Stock Movements'!$E:$E,'Stock Movements'!$C:$C,$A42,'Stock Movements'!$F:$F,F$2,'Stock Movements'!$D:$D,"Out") -> 0 | G42: =SUMIFS('Stock Movements'!$E:$E,'Stock Movements'!$C:$C,$A42,'Stock Movements'!$F:$F,G$2,'Stock Movements'!$D:$D,"Out") -> 0 | H42: =SUMIFS('Stock Movements'!$E:$E,'Stock Movements'!$C:$C,$A42,'Stock Movements'!$F:$F,H$2,'Stock Movements'!$D:$D,"Out") -> 0 | I42: =SUMIFS('Stock Movements'!$E:$E,'Stock Movements'!$C:$C,$A42,'Stock Movements'!$F:$F,I$2,'Stock Movements'!$D:$D,"Out") -> 0 | J42: =SUMIFS('Stock Movements'!$E:$E,'Stock Movements'!$C:$C,$A42,'Stock Movements'!$F:$F,J$2,'Stock Movements'!$D:$D,"Out") -> 11 | ... R42: =SUMIFS('Stock Movements'!$E:$E,'Stock Movements'!$C:$C,$A42,'Stock Movements'!$F:$F,R$2,'Stock Movements'!$D:$D,"Out") -> 0 | S42: =SUM(C42:R42) -> 19 | T42: =S42-'Item Catalog'!$M$42 -> 0
A43: ='Item Catalog'!$B$43 -> ITM-041 · 500 ML LABEL SHRINKABLE LW | B43: ='Item Catalog'!$C$43 -> 500 ML LABEL SHRINKABLE LW | C43: =SUMIFS('Stock Movements'!$E:$E,'Stock Movements'!$C:$C,$A43,'Stock Movements'!$F:$F,C$2,'Stock Movements'!$D:$D,"Out") -> 0 | D43: =SUMIFS('Stock Movements'!$E:$E,'Stock Movements'!$C:$C,$A43,'Stock Movements'!$F:$F,D$2,'Stock Movements'!$D:$D,"Out") -> 0 | E43: =SUMIFS('Stock Movements'!$E:$E,'Stock Movements'!$C:$C,$A43,'Stock Movements'!$F:$F,E$2,'Stock Movements'!$D:$D,"Out") -> 0 | F43: =SUMIFS('Stock Movements'!$E:$E,'Stock Movements'!$C:$C,$A43,'Stock Movements'!$F:$F,F$2,'Stock Movements'!$D:$D,"Out") -> 0 | G43: =SUMIFS('Stock Movements'!$E:$E,'Stock Movements'!$C:$C,$A43,'Stock Movements'!$F:$F,G$2,'Stock Movements'!$D:$D,"Out") -> 0 | H43: =SUMIFS('Stock Movements'!$E:$E,'Stock Movements'!$C:$C,$A43,'Stock Movements'!$F:$F,H$2,'Stock Movements'!$D:$D,"Out") -> 0 | I43: =SUMIFS('Stock Movements'!$E:$E,'Stock Movements'!$C:$C,$A43,'Stock Movements'!$F:$F,I$2,'Stock Movements'!$D:$D,"Out") -> 0 | J43: =SUMIFS('Stock Movements'!$E:$E,'Stock Movements'!$C:$C,$A43,'Stock Movements'!$F:$F,J$2,'Stock Movements'!$D:$D,"Out") -> 0 | ... R43: =SUMIFS('Stock Movements'!$E:$E,'Stock Movements'!$C:$C,$A43,'Stock Movements'!$F:$F,R$2,'Stock Movements'!$D:$D,"Out") -> 0 | S43: =SUM(C43:R43) -> 0 | T43: =S43-'Item Catalog'!$M$43 -> 0
A44: ='Item Catalog'!$B$44 -> ITM-042 · 1000 ML LABEL SHRINKABLE LW | B44: ='Item Catalog'!$C$44 -> 1000 ML LABEL SHRINKABLE LW | C44: =SUMIFS('Stock Movements'!$E:$E,'Stock Movements'!$C:$C,$A44,'Stock Movements'!$F:$F,C$2,'Stock Movements'!$D:$D,"Out") -> 1 | D44: =SUMIFS('Stock Movements'!$E:$E,'Stock Movements'!$C:$C,$A44,'Stock Movements'!$F:$F,D$2,'Stock Movements'!$D:$D,"Out") -> 0 | E44: =SUMIFS('Stock Movements'!$E:$E,'Stock Movements'!$C:$C,$A44,'Stock Movements'!$F:$F,E$2,'Stock Movements'!$D:$D,"Out") -> 0 | F44: =SUMIFS('Stock Movements'!$E:$E,'Stock Movements'!$C:$C,$A44,'Stock Movements'!$F:$F,F$2,'Stock Movements'!$D:$D,"Out") -> 0 | G44: =SUMIFS('Stock Movements'!$E:$E,'Stock Movements'!$C:$C,$A44,'Stock Movements'!$F:$F,G$2,'Stock Movements'!$D:$D,"Out") -> 0 | H44: =SUMIFS('Stock Movements'!$E:$E,'Stock Movements'!$C:$C,$A44,'Stock Movements'!$F:$F,H$2,'Stock Movements'!$D:$D,"Out") -> 0 | I44: =SUMIFS('Stock Movements'!$E:$E,'Stock Movements'!$C:$C,$A44,'Stock Movements'!$F:$F,I$2,'Stock Movements'!$D:$D,"Out") -> 0 | J44: =SUMIFS('Stock Movements'!$E:$E,'Stock Movements'!$C:$C,$A44,'Stock Movements'!$F:$F,J$2,'Stock Movements'!$D:$D,"Out") -> 0 | ... R44: =SUMIFS('Stock Movements'!$E:$E,'Stock Movements'!$C:$C,$A44,'Stock Movements'!$F:$F,R$2,'Stock Movements'!$D:$D,"Out") -> 0 | S44: =SUM(C44:R44) -> 1 | T44: =S44-'Item Catalog'!$M$44 -> 0
A45: ='Item Catalog'!$B$45 -> ITM-043 · 350 ML LABEL SHRINKABLE REFRESHING | B45: ='Item Catalog'!$C$45 -> 350 ML LABEL SHRINKABLE REFRESHING | C45: =SUMIFS('Stock Movements'!$E:$E,'Stock Movements'!$C:$C,$A45,'Stock Movements'!$F:$F,C$2,'Stock Movements'!$D:$D,"Out") -> 0 | D45: =SUMIFS('Stock Movements'!$E:$E,'Stock Movements'!$C:$C,$A45,'Stock Movements'!$F:$F,D$2,'Stock Movements'!$D:$D,"Out") -> 0 | E45: =SUMIFS('Stock Movements'!$E:$E,'Stock Movements'!$C:$C,$A45,'Stock Movements'!$F:$F,E$2,'Stock Movements'!$D:$D,"Out") -> 0 | F45: =SUMIFS('Stock Movements'!$E:$E,'Stock Movements'!$C:$C,$A45,'Stock Movements'!$F:$F,F$2,'Stock Movements'!$D:$D,"Out") -> 0 | G45: =SUMIFS('Stock Movements'!$E:$E,'Stock Movements'!$C:$C,$A45,'Stock Movements'!$F:$F,G$2,'Stock Movements'!$D:$D,"Out") -> 0 | H45: =SUMIFS('Stock Movements'!$E:$E,'Stock Movements'!$C:$C,$A45,'Stock Movements'!$F:$F,H$2,'Stock Movements'!$D:$D,"Out") -> 0 | I45: =SUMIFS('Stock Movements'!$E:$E,'Stock Movements'!$C:$C,$A45,'Stock Movements'!$F:$F,I$2,'Stock Movements'!$D:$D,"Out") -> 0 | J45: =SUMIFS('Stock Movements'!$E:$E,'Stock Movements'!$C:$C,$A45,'Stock Movements'!$F:$F,J$2,'Stock Movements'!$D:$D,"Out") -> 0 | ... R45: =SUMIFS('Stock Movements'!$E:$E,'Stock Movements'!$C:$C,$A45,'Stock Movements'!$F:$F,R$2,'Stock Movements'!$D:$D,"Out") -> 0 | S45: =SUM(C45:R45) -> 2 | T45: =S45-'Item Catalog'!$M$45 -> 0
A46: ='Item Catalog'!$B$46 -> ITM-044 · 500 ML LABEL SHRINKABLE REFRESHING | B46: ='Item Catalog'!$C$46 -> 500 ML LABEL SHRINKABLE REFRESHING | C46: =SUMIFS('Stock Movements'!$E:$E,'Stock Movements'!$C:$C,$A46,'Stock Movements'!$F:$F,C$2,'Stock Movements'!$D:$D,"Out") -> 0 | D46: =SUMIFS('Stock Movements'!$E:$E,'Stock Movements'!$C:$C,$A46,'Stock Movements'!$F:$F,D$2,'Stock Movements'!$D:$D,"Out") -> 0 | E46: =SUMIFS('Stock Movements'!$E:$E,'Stock Movements'!$C:$C,$A46,'Stock Movements'!$F:$F,E$2,'Stock Movements'!$D:$D,"Out") -> 0 | F46: =SUMIFS('Stock Movements'!$E:$E,'Stock Movements'!$C:$C,$A46,'Stock Movements'!$F:$F,F$2,'Stock Movements'!$D:$D,"Out") -> 0 | G46: =SUMIFS('Stock Movements'!$E:$E,'Stock Movements'!$C:$C,$A46,'Stock Movements'!$F:$F,G$2,'Stock Movements'!$D:$D,"Out") -> 0 | H46: =SUMIFS('Stock Movements'!$E:$E,'Stock Movements'!$C:$C,$A46,'Stock Movements'!$F:$F,H$2,'Stock Movements'!$D:$D,"Out") -> 0 | I46: =SUMIFS('Stock Movements'!$E:$E,'Stock Movements'!$C:$C,$A46,'Stock Movements'!$F:$F,I$2,'Stock Movements'!$D:$D,"Out") -> 0 | J46: =SUMIFS('Stock Movements'!$E:$E,'Stock Movements'!$C:$C,$A46,'Stock Movements'!$F:$F,J$2,'Stock Movements'!$D:$D,"Out") -> 0 | ... R46: =SUMIFS('Stock Movements'!$E:$E,'Stock Movements'!$C:$C,$A46,'Stock Movements'!$F:$F,R$2,'Stock Movements'!$D:$D,"Out") -> 0 | S46: =SUM(C46:R46) -> 0 | T46: =S46-'Item Catalog'!$M$46 -> 0
A47: ='Item Catalog'!$B$47 -> ITM-045 · STICKER LW WITH PIOLO - 5 GAL 6X4 | B47: ='Item Catalog'!$C$47 -> STICKER LW WITH PIOLO - 5 GAL 6X4 | C47: =SUMIFS('Stock Movements'!$E:$E,'Stock Movements'!$C:$C,$A47,'Stock Movements'!$F:$F,C$2,'Stock Movements'!$D:$D,"Out") -> 2 | D47: =SUMIFS('Stock Movements'!$E:$E,'Stock Movements'!$C:$C,$A47,'Stock Movements'!$F:$F,D$2,'Stock Movements'!$D:$D,"Out") -> 0 | E47: =SUMIFS('Stock Movements'!$E:$E,'Stock Movements'!$C:$C,$A47,'Stock Movements'!$F:$F,E$2,'Stock Movements'!$D:$D,"Out") -> 0 | F47: =SUMIFS('Stock Movements'!$E:$E,'Stock Movements'!$C:$C,$A47,'Stock Movements'!$F:$F,F$2,'Stock Movements'!$D:$D,"Out") -> 0 | G47: =SUMIFS('Stock Movements'!$E:$E,'Stock Movements'!$C:$C,$A47,'Stock Movements'!$F:$F,G$2,'Stock Movements'!$D:$D,"Out") -> 0 | H47: =SUMIFS('Stock Movements'!$E:$E,'Stock Movements'!$C:$C,$A47,'Stock Movements'!$F:$F,H$2,'Stock Movements'!$D:$D,"Out") -> 0 | I47: =SUMIFS('Stock Movements'!$E:$E,'Stock Movements'!$C:$C,$A47,'Stock Movements'!$F:$F,I$2,'Stock Movements'!$D:$D,"Out") -> 0 | J47: =SUMIFS('Stock Movements'!$E:$E,'Stock Movements'!$C:$C,$A47,'Stock Movements'!$F:$F,J$2,'Stock Movements'!$D:$D,"Out") -> 0 | ... R47: =SUMIFS('Stock Movements'!$E:$E,'Stock Movements'!$C:$C,$A47,'Stock Movements'!$F:$F,R$2,'Stock Movements'!$D:$D,"Out") -> 0 | S47: =SUM(C47:R47) -> 2 | T47: =S47-'Item Catalog'!$M$47 -> 0
A48: ='Item Catalog'!$B$48 -> ITM-046 · BIG CAP REPLACEMENT - 5 GAL SLIM | B48: ='Item Catalog'!$C$48 -> BIG CAP REPLACEMENT - 5 GAL SLIM | C48: =SUMIFS('Stock Movements'!$E:$E,'Stock Movements'!$C:$C,$A48,'Stock Movements'!$F:$F,C$2,'Stock Movements'!$D:$D,"Out") -> 23 | D48: =SUMIFS('Stock Movements'!$E:$E,'Stock Movements'!$C:$C,$A48,'Stock Movements'!$F:$F,D$2,'Stock Movements'!$D:$D,"Out") -> 6 | E48: =SUMIFS('Stock Movements'!$E:$E,'Stock Movements'!$C:$C,$A48,'Stock Movements'!$F:$F,E$2,'Stock Movements'!$D:$D,"Out") -> 0 | F48: =SUMIFS('Stock Movements'!$E:$E,'Stock Movements'!$C:$C,$A48,'Stock Movements'!$F:$F,F$2,'Stock Movements'!$D:$D,"Out") -> 0 | G48: =SUMIFS('Stock Movements'!$E:$E,'Stock Movements'!$C:$C,$A48,'Stock Movements'!$F:$F,G$2,'Stock Movements'!$D:$D,"Out") -> 55 | H48: =SUMIFS('Stock Movements'!$E:$E,'Stock Movements'!$C:$C,$A48,'Stock Movements'!$F:$F,H$2,'Stock Movements'!$D:$D,"Out") -> 0 | I48: =SUMIFS('Stock Movements'!$E:$E,'Stock Movements'!$C:$C,$A48,'Stock Movements'!$F:$F,I$2,'Stock Movements'!$D:$D,"Out") -> 100 | J48: =SUMIFS('Stock Movements'!$E:$E,'Stock Movements'!$C:$C,$A48,'Stock Movements'!$F:$F,J$2,'Stock Movements'!$D:$D,"Out") -> 20 | ... R48: =SUMIFS('Stock Movements'!$E:$E,'Stock Movements'!$C:$C,$A48,'Stock Movements'!$F:$F,R$2,'Stock Movements'!$D:$D,"Out") -> 0 | S48: =SUM(C48:R48) -> 259 | T48: =S48-'Item Catalog'!$M$48 -> 0
A49: ='Item Catalog'!$B$49 -> ITM-047 · SMALL CAP REPLACEMENT - 5 GAL SLIM | B49: ='Item Catalog'!$C$49 -> SMALL CAP REPLACEMENT - 5 GAL SLIM | C49: =SUMIFS('Stock Movements'!$E:$E,'Stock Movements'!$C:$C,$A49,'Stock Movements'!$F:$F,C$2,'Stock Movements'!$D:$D,"Out") -> 46 | D49: =SUMIFS('Stock Movements'!$E:$E,'Stock Movements'!$C:$C,$A49,'Stock Movements'!$F:$F,D$2,'Stock Movements'!$D:$D,"Out") -> 0 | E49: =SUMIFS('Stock Movements'!$E:$E,'Stock Movements'!$C:$C,$A49,'Stock Movements'!$F:$F,E$2,'Stock Movements'!$D:$D,"Out") -> 0 | F49: =SUMIFS('Stock Movements'!$E:$E,'Stock Movements'!$C:$C,$A49,'Stock Movements'!$F:$F,F$2,'Stock Movements'!$D:$D,"Out") -> 0 | G49: =SUMIFS('Stock Movements'!$E:$E,'Stock Movements'!$C:$C,$A49,'Stock Movements'!$F:$F,G$2,'Stock Movements'!$D:$D,"Out") -> 175 | H49: =SUMIFS('Stock Movements'!$E:$E,'Stock Movements'!$C:$C,$A49,'Stock Movements'!$F:$F,H$2,'Stock Movements'!$D:$D,"Out") -> 0 | I49: =SUMIFS('Stock Movements'!$E:$E,'Stock Movements'!$C:$C,$A49,'Stock Movements'!$F:$F,I$2,'Stock Movements'!$D:$D,"Out") -> 100 | J49: =SUMIFS('Stock Movements'!$E:$E,'Stock Movements'!$C:$C,$A49,'Stock Movements'!$F:$F,J$2,'Stock Movements'!$D:$D,"Out") -> 20 | ... R49: =SUMIFS('Stock Movements'!$E:$E,'Stock Movements'!$C:$C,$A49,'Stock Movements'!$F:$F,R$2,'Stock Movements'!$D:$D,"Out") -> 0 | S49: =SUM(C49:R49) -> 389 | T49: =S49-'Item Catalog'!$M$49 -> 0
A50: ='Item Catalog'!$B$50 -> ITM-048 · FAUCET REPLACEMENT - 5 GAL SLIM | B50: ='Item Catalog'!$C$50 -> FAUCET REPLACEMENT - 5 GAL SLIM | C50: =SUMIFS('Stock Movements'!$E:$E,'Stock Movements'!$C:$C,$A50,'Stock Movements'!$F:$F,C$2,'Stock Movements'!$D:$D,"Out") -> 1 | D50: =SUMIFS('Stock Movements'!$E:$E,'Stock Movements'!$C:$C,$A50,'Stock Movements'!$F:$F,D$2,'Stock Movements'!$D:$D,"Out") -> 0 | E50: =SUMIFS('Stock Movements'!$E:$E,'Stock Movements'!$C:$C,$A50,'Stock Movements'!$F:$F,E$2,'Stock Movements'!$D:$D,"Out") -> 0 | F50: =SUMIFS('Stock Movements'!$E:$E,'Stock Movements'!$C:$C,$A50,'Stock Movements'!$F:$F,F$2,'Stock Movements'!$D:$D,"Out") -> 0 | G50: =SUMIFS('Stock Movements'!$E:$E,'Stock Movements'!$C:$C,$A50,'Stock Movements'!$F:$F,G$2,'Stock Movements'!$D:$D,"Out") -> 0 | H50: =SUMIFS('Stock Movements'!$E:$E,'Stock Movements'!$C:$C,$A50,'Stock Movements'!$F:$F,H$2,'Stock Movements'!$D:$D,"Out") -> 0 | I50: =SUMIFS('Stock Movements'!$E:$E,'Stock Movements'!$C:$C,$A50,'Stock Movements'!$F:$F,I$2,'Stock Movements'!$D:$D,"Out") -> 0 | J50: =SUMIFS('Stock Movements'!$E:$E,'Stock Movements'!$C:$C,$A50,'Stock Movements'!$F:$F,J$2,'Stock Movements'!$D:$D,"Out") -> 0 | ... R50: =SUMIFS('Stock Movements'!$E:$E,'Stock Movements'!$C:$C,$A50,'Stock Movements'!$F:$F,R$2,'Stock Movements'!$D:$D,"Out") -> 0 | S50: =SUM(C50:R50) -> 2 | T50: =S50-'Item Catalog'!$M$50 -> 0
A51: ='Item Catalog'!$B$51 -> ITM-049 · WHITE CAP REPLACEMENT - 5 GAL SLIM | B51: ='Item Catalog'!$C$51 -> WHITE CAP REPLACEMENT - 5 GAL SLIM | C51: =SUMIFS('Stock Movements'!$E:$E,'Stock Movements'!$C:$C,$A51,'Stock Movements'!$F:$F,C$2,'Stock Movements'!$D:$D,"Out") -> 0 | D51: =SUMIFS('Stock Movements'!$E:$E,'Stock Movements'!$C:$C,$A51,'Stock Movements'!$F:$F,D$2,'Stock Movements'!$D:$D,"Out") -> 0 | E51: =SUMIFS('Stock Movements'!$E:$E,'Stock Movements'!$C:$C,$A51,'Stock Movements'!$F:$F,E$2,'Stock Movements'!$D:$D,"Out") -> 0 | F51: =SUMIFS('Stock Movements'!$E:$E,'Stock Movements'!$C:$C,$A51,'Stock Movements'!$F:$F,F$2,'Stock Movements'!$D:$D,"Out") -> 0 | G51: =SUMIFS('Stock Movements'!$E:$E,'Stock Movements'!$C:$C,$A51,'Stock Movements'!$F:$F,G$2,'Stock Movements'!$D:$D,"Out") -> 0 | H51: =SUMIFS('Stock Movements'!$E:$E,'Stock Movements'!$C:$C,$A51,'Stock Movements'!$F:$F,H$2,'Stock Movements'!$D:$D,"Out") -> 0 | I51: =SUMIFS('Stock Movements'!$E:$E,'Stock Movements'!$C:$C,$A51,'Stock Movements'!$F:$F,I$2,'Stock Movements'!$D:$D,"Out") -> 100 | J51: =SUMIFS('Stock Movements'!$E:$E,'Stock Movements'!$C:$C,$A51,'Stock Movements'!$F:$F,J$2,'Stock Movements'!$D:$D,"Out") -> 0 | ... R51: =SUMIFS('Stock Movements'!$E:$E,'Stock Movements'!$C:$C,$A51,'Stock Movements'!$F:$F,R$2,'Stock Movements'!$D:$D,"Out") -> 0 | S51: =SUM(C51:R51) -> 100 | T51: =S51-'Item Catalog'!$M$51 -> 0
A52: ='Item Catalog'!$B$52 -> ITM-050 · CAP NON SPILL T-BACK - 5 GAL PET ROUND | B52: ='Item Catalog'!$C$52 -> CAP NON SPILL T-BACK - 5 GAL PET ROUND | C52: =SUMIFS('Stock Movements'!$E:$E,'Stock Movements'!$C:$C,$A52,'Stock Movements'!$F:$F,C$2,'Stock Movements'!$D:$D,"Out") -> 11 | D52: =SUMIFS('Stock Movements'!$E:$E,'Stock Movements'!$C:$C,$A52,'Stock Movements'!$F:$F,D$2,'Stock Movements'!$D:$D,"Out") -> 6 | E52: =SUMIFS('Stock Movements'!$E:$E,'Stock Movements'!$C:$C,$A52,'Stock Movements'!$F:$F,E$2,'Stock Movements'!$D:$D,"Out") -> 0 | F52: =SUMIFS('Stock Movements'!$E:$E,'Stock Movements'!$C:$C,$A52,'Stock Movements'!$F:$F,F$2,'Stock Movements'!$D:$D,"Out") -> 0 | G52: =SUMIFS('Stock Movements'!$E:$E,'Stock Movements'!$C:$C,$A52,'Stock Movements'!$F:$F,G$2,'Stock Movements'!$D:$D,"Out") -> 15 | H52: =SUMIFS('Stock Movements'!$E:$E,'Stock Movements'!$C:$C,$A52,'Stock Movements'!$F:$F,H$2,'Stock Movements'!$D:$D,"Out") -> 0 | I52: =SUMIFS('Stock Movements'!$E:$E,'Stock Movements'!$C:$C,$A52,'Stock Movements'!$F:$F,I$2,'Stock Movements'!$D:$D,"Out") -> 0 | J52: =SUMIFS('Stock Movements'!$E:$E,'Stock Movements'!$C:$C,$A52,'Stock Movements'!$F:$F,J$2,'Stock Movements'!$D:$D,"Out") -> 0 | ... R52: =SUMIFS('Stock Movements'!$E:$E,'Stock Movements'!$C:$C,$A52,'Stock Movements'!$F:$F,R$2,'Stock Movements'!$D:$D,"Out") -> 0 | S52: =SUM(C52:R52) -> 32 | T52: =S52-'Item Catalog'!$M$52 -> 0
A53: ='Item Catalog'!$B$53 -> ITM-051 · HOT AND COLD LIVINGWATER | B53: ='Item Catalog'!$C$53 -> HOT AND COLD LIVINGWATER | C53: =SUMIFS('Stock Movements'!$E:$E,'Stock Movements'!$C:$C,$A53,'Stock Movements'!$F:$F,C$2,'Stock Movements'!$D:$D,"Out") -> 0 | D53: =SUMIFS('Stock Movements'!$E:$E,'Stock Movements'!$C:$C,$A53,'Stock Movements'!$F:$F,D$2,'Stock Movements'!$D:$D,"Out") -> 0 | E53: =SUMIFS('Stock Movements'!$E:$E,'Stock Movements'!$C:$C,$A53,'Stock Movements'!$F:$F,E$2,'Stock Movements'!$D:$D,"Out") -> 0 | F53: =SUMIFS('Stock Movements'!$E:$E,'Stock Movements'!$C:$C,$A53,'Stock Movements'!$F:$F,F$2,'Stock Movements'!$D:$D,"Out") -> 0 | G53: =SUMIFS('Stock Movements'!$E:$E,'Stock Movements'!$C:$C,$A53,'Stock Movements'!$F:$F,G$2,'Stock Movements'!$D:$D,"Out") -> 0 | H53: =SUMIFS('Stock Movements'!$E:$E,'Stock Movements'!$C:$C,$A53,'Stock Movements'!$F:$F,H$2,'Stock Movements'!$D:$D,"Out") -> 0 | I53: =SUMIFS('Stock Movements'!$E:$E,'Stock Movements'!$C:$C,$A53,'Stock Movements'!$F:$F,I$2,'Stock Movements'!$D:$D,"Out") -> 0 | J53: =SUMIFS('Stock Movements'!$E:$E,'Stock Movements'!$C:$C,$A53,'Stock Movements'!$F:$F,J$2,'Stock Movements'!$D:$D,"Out") -> 0 | ... R53: =SUMIFS('Stock Movements'!$E:$E,'Stock Movements'!$C:$C,$A53,'Stock Movements'!$F:$F,R$2,'Stock Movements'!$D:$D,"Out") -> 0 | S53: =SUM(C53:R53) -> 0 | T53: =S53-'Item Catalog'!$M$53 -> 0

Sheet Restock Orders
A1: RESTOCK ORDERS (purchase order log)
A2: SO Number | B2: Order Date | C2: Received Date | D2: Amount | E2: Trucking Fee | F2: Order Total | G2: Note
A3: SO111897 | B3: 2023-10-13 | C3: 2023-11-05 | D3: 250480 | F3: =SUM(D3:E3) -> 250480 | G3: Initial capital order 1 of 3
A4: SO112258 | B4: 2023-10-23 | C4: 2023-11-05 | D4: 63988 | F4: =SUM(D4:E4) -> 63988 | G4: Initial capital order 2 of 3
A5: SO112635 | B5: 2023-11-03 | C5: 2023-11-05 | E5: 16000 | F5: =SUM(D5:E5) -> 16000 | G5: Trucking for initial capital order 3 of 3
A6: SO124878 | B6: 2024-09-30 | C6: 2024-10-03 | D6: 50085 | F6: =SUM(D6:E6) -> 50085
A7: SO124878 | B7: 2024-09-30 | C7: 2024-10-03 | E7: 12300 | F7: =SUM(D7:E7) -> 12300 | G7: Lalamove trucking for SO124878
A8: SO136446 | B8: 2025-10-07 | C8: 2025-10-15 | D8: 50210 | F8: =SUM(D8:E8) -> 50210
A9: SO136446 | B9: 2025-10-07 | C9: 2025-10-15 | E9: 11615 | F9: =SUM(D9:E9) -> 11615 | G9: Lalamove trucking for SO136446
A10: SO141459 | B10: 2026-05-15 | C10: 2026-05-16 | D10: 55186 | F10: =SUM(D10:E10) -> 55186
A11: SO141459 | B11: 2026-05-15 | C11: 2026-05-16 | E11: 12700 | F11: =SUM(D11:E11) -> 12700 | G11: Lalamove trucking for SO141459
C13: TOTAL SPENT TO DATE | F13: =SUM(F3:F11) -> 522564

Sheet Buyers
A1: BUYERS (reference list)
A2: Buyer Name | B2: Is Own Shop
A3: A&G (LW-BAAO) | B3: =TRUE() -> TRUE
A4: ALKAVIVA (BAAO) | B4: =FALSE() -> FALSE
A5: OTHERS (CUSTOMER) | B5: =FALSE() -> FALSE
A6: CRISPY KING | B6: =FALSE() -> FALSE
A7: CITY WATER (LW-TAPAYAS) | B7: =FALSE() -> FALSE
A8: PURE DROP | B8: =FALSE() -> FALSE
A9: LW (SORSOGON) | B9: =FALSE() -> FALSE
A10: LW (BATO) | B10: =FALSE() -> FALSE
A11: SARALEX | B11: =FALSE() -> FALSE
A12: CRYSTAL REF. STATION | B12: =FALSE() -> FALSE
A13: WATER MARKET (BAAO) | B13: =FALSE() -> FALSE
A14: AQUARES | B14: =FALSE() -> FALSE
A15: LANON W.R.S. | B15: =FALSE() -> FALSE
... A18: SHAUNTI REF. STN. | B18: =FALSE() -> FALSE

Sheet Categories
A1: CATEGORIES (reference list)
A2: Category
A3: CONTAINERS
A4: CAPSEALS
A5: SOAP SANITIZER
A6: SALT 50KG
A7: FILTERS
A8: PET BOTTLE
A9: LABELS
A10: STICKER
A11: CAPS REPLACEMENT
A12: DISPENSERS
